Workbook
Name \a: #REF!
Name \a: #REF!
Name \b: #REF!
Name \b: #REF!
Name _ACC1: #REF!
Name _ADD1: #REF!
Name _ADD2: #REF!
Name _ADD3: #REF!
Name _CAP1: #REF!
Name _CAP2: #REF!
Name _CAP3: #REF!
Name _dcc4: #REF!
Name _IRR1: #REF!
Name _IRR2: #REF!
Name _IRR3: #REF!
Name _IRR4: #REF!
Name _IRR5: #REF!
Name _IRR6: #REF!
Name _Mei97: #REF!
Name _NO1: #REF!
Name _NO2: #REF!
Name _NO3: #REF!
Name _NO4: #REF!
Name _NO5: #REF!
Name _NO6: #REF!
Name _NO7: #REF!
Name _RAN1: #REF!
Name _RAN2: #REF!
Name _RAN3: #REF!
Name _tb2: #REF!
Name a_case: #REF!
Name aaa: #REF!
Name aaaa: #REF!
Name aaaaaaaaaa: #REF!
Name aaaaaaaaaaa: #REF!
Name aaaaaaaaaaaaaarrrrrrrrr: #REF!
Name aaaaaaaaassssssssssssssshhhh: #REF!
Name aashi: #REF!
Name abc: {17}
Name abc: {17}
Name abc: {17}
Name abc: {17}
Name abc: {17}
Name abc: {17}
Name abc: {17}
Name abc: {17}
Name abcd: #REF!
Name AC: #REF!
Name ACapital: #REF!
Name ACapital: #REF!
Name AcqData: #REF!
Name AcqData2: #REF!
Name ADD: #REF!
Name ADR_SWITCH: #REF!
Name AllTables: {17}
Name AllTables: {17}
Name AllTables: {17}
Name AllTables: {17}
Name AllTables: {17}
Name AllTables: {17}

Sheet Charts
E2: Charts | L2: USD | M2: lacs
L3: INR | M3: Crore
L4: AED | M4: Million
E6: Revenue & Profitability | L6: AED | M6: Million
A7: AED | E7: AED | F7: Million | I7: AED | J7: Million
E26: Cash Analysis & Balance Sheet
R30: =E26 -> Cash Analysis & Balance Sheet | S30: =Dashboard!D5 -> 25-26 | T30: =Dashboard!E5 -> 26-27 | U30: =Dashboard!F5 -> 27-28 | V30: =Dashboard!G5 -> 28-29 | W30: =Dashboard!H5 -> 29-30
R31: Cash Burn/Cash Saving | S31: =Dashboard!D29 -> 2737.6442 | T31: =Dashboard!E29 -> -36.440992 | U31: =Dashboard!F29 -> 352.5965 | V31: =Dashboard!G29 -> 677.84776 | W31: =Dashboard!H29 -> 1052.7073
R32: Ending Cash Balance | S32: =Dashboard!D30 -> 2738.0139 | T32: =Dashboard!E30 -> 2701.5729 | U32: =Dashboard!F30 -> 3054.1694 | V32: =Dashboard!G30 -> 3732.0171 | W32: =Dashboard!H30 -> 4784.7245
E44: Funding Requirement
B46: Total Funds Requirement | E46: =Config!C30 -> 300 | G46: Funds Utilization
B47: Valuation | E47: =Dashboard!D36 -> 2724.0294 | J47: =$E$46*I47 -> 0
B48: Equity Dilution | E48: =E46/E47 -> 0.11013097 | J48: =$E$46*I48 -> 0
J49: =$E$46*I49 -> 0
J50: =$E$46*I50 -> 0
J51: =$E$46*I51 -> 0

Sheet Dashboard
B2: 5-Year Financial Projections - Semis Foods
B4: Amount in INR Lakhs
B5: Revenue | D5: 25-26 | E5: 26-27 | F5: 27-28 | G5: 28-29 | H5: 29-30 | J5: Segmental Revenue | K5: =D5 -> 25-26 | L5: =E5 -> 26-27 | M5: =F5 -> 27-28 | N5: =G5 -> 28-29 | O5: =H5 -> 29-30
B6: ="Revenue from - " &'P&L'!D9 -> Revenue from - Corporate Sales | D6: ='P&L'!F9 -> 135 | E6: ='P&L'!G9 -> 162 | F6: ='P&L'!H9 -> 202.5 | G6: ='P&L'!I9 -> 253.125 | H6: ='P&L'!J9 -> 316.40625 | J6: =B6 -> Revenue from - Corporate Sales | K6: =D6/$D$10 -> 0.21428571 | L6: =E6/$E$10 -> 0.075208914 | M6: =F6/$F$10 -> 0.053066038 | N6: =G6/$G$10 -> 0.042598684 | O6: =H6/$H$10 -> 0.036439809
B7: ="Revenue from - " &'P&L'!D11 -> Revenue from - Millet Cafeteria | D7: ='P&L'!F11 -> 270 | E7: ='P&L'!G11 -> 792 | F7: ='P&L'!H11 -> 1633.5 | G7: ='P&L'!I11 -> 2874.96 | H7: ='P&L'!J11 -> 4348.377 | J7: =B7 -> Revenue from - Millet Cafeteria | K7: =D7/$D$10 -> 0.42857143 | L7: =E7/$E$10 -> 0.36768802 | M7: =F7/$F$10 -> 0.42806604 | N7: =G7/$G$10 -> 0.48383017 | O7: =H7/$H$10 -> 0.50079297
B8: ="Revenue from - " &'P&L'!D13 -> Revenue from - Retail Market Sales | D8: ='P&L'!F13 -> 75 | E8: ='P&L'!G13 -> 600 | F8: ='P&L'!H13 -> 1200 | G8: ='P&L'!I13 -> 1800 | H8: ='P&L'!J13 -> 2700 | J8: =B8 -> Revenue from - Retail Market Sales | K8: =D8/$D$10 -> 0.11904762 | L8: =E8/$E$10 -> 0.27855153 | M8: =F8/$F$10 -> 0.31446541 | N8: =G8/$G$10 -> 0.30292397 | O8: =H8/$H$10 -> 0.31095304
B9: ="Revenue from - " &'P&L'!D15 -> Revenue from - Export Sales | D9: ='P&L'!F15 -> 150 | E9: ='P&L'!G15 -> 600 | F9: ='P&L'!H15 -> 780 | G9: ='P&L'!I15 -> 1014 | H9: ='P&L'!J15 -> 1318.2 | J9: =B9 -> Revenue from - Export Sales | K9: =D9/$D$10 -> 0.23809524 | L9: =E9/$E$10 -> 0.27855153 | M9: =F9/$F$10 -> 0.20440252 | N9: =G9/$G$10 -> 0.17064717 | O9: =H9/$H$10 -> 0.15181418
B10: Total Revenue | D10: =D6+D7+D8+D9 -> 630 | E10: =E6+E7+E8+E9 -> 2154 | F10: =F6+F7+F8+F9 -> 3816 | G10: =G6+G7+G8+G9 -> 5942.085 | H10: =H6+H7+H8+H9 -> 8682.9833 | J10: =B10 -> Total Revenue | K10: =SUM(K6:K9) -> 1 | L10: =SUM(L6:L9) -> 1 | M10: =SUM(M6:M9) -> 1 | N10: =SUM(N6:N9) -> 1 | O10: =SUM(O6:O9) -> 1
B11: % Net Profit | D11: =K22 -> -0.051137554 | E11: =L22 -> 0.14242167 | F11: =M22 -> 0.1488808 | G11: =N22 -> 0.14098645 | H11: =O22 -> 0.21307386
B13: Profit & Loss | D13: =D5 -> 25-26 | E13: =E5 -> 26-27 | F13: =F5 -> 27-28 | G13: =G5 -> 28-29 | H13: =H5 -> 29-30 | J13: Profit & Loss | K13: =D13 -> 25-26 | L13: =E13 -> 26-27 | M13: =F13 -> 27-28 | N13: =G13 -> 28-29 | O13: =H13 -> 29-30
B14: Net Revenue | D14: ='P&L'!F7 -> 630 | E14: ='P&L'!G7 -> 2154 | F14: ='P&L'!H7 -> 3816 | G14: ='P&L'!I7 -> 5942.085 | H14: ='P&L'!J7 -> 8682.9833 | J14: =B14 -> Net Revenue | K14: =D14/D$14 -> 1 | L14: =E14/E$14 -> 1 | M14: =F14/F$14 -> 1 | N14: =G14/G$14 -> 1 | O14: =H14/H$14 -> 1
B15: Direct Cost | D15: ='P&L'!F17 -> 272.4 | E15: ='P&L'!G17 -> 1088.94 | F15: ='P&L'!H17 -> 1818.645 | G15: ='P&L'!I17 -> 2682.005 | H15: ='P&L'!J17 -> 3850.5811 | J15: =B15 -> Direct Cost | K15: =D15/D$14 -> 0.43238095 | L15: =E15/E$14 -> 0.50554318 | M15: =F15/F$14 -> 0.47658412 | N15: =G15/G$14 -> 0.45135755 | O15: =H15/H$14 -> 0.44346292
B16: Gross Profit | D16: =D14-D15 -> 357.6 | E16: =E14-E15 -> 1065.06 | F16: =F14-F15 -> 1997.355 | G16: =G14-G15 -> 3260.0801 | H16: =H14-H15 -> 4832.4021 | J16: =B16 -> Gross Profit | K16: =D16/D$14 -> 0.56761905 | L16: =E16/E$14 -> 0.49445682 | M16: =F16/F$14 -> 0.52341588 | N16: =G16/G$14 -> 0.54864245 | O16: =H16/H$14 -> 0.55653708
B17: Marketing | D17: ='P&L'!F32 -> 20.25 | E17: ='P&L'!G32 -> 47.7 | F17: ='P&L'!H32 -> 91.8 | G17: ='P&L'!I32 -> 156.40425 | H17: ='P&L'!J32 -> 233.23916 | J17: =B17 -> Marketing | K17: =D17/D$14 -> 0.032142857 | L17: =E17/E$14 -> 0.022144847 | M17: =F17/F$14 -> 0.024056604 | N17: =G17/G$14 -> 0.026321443 | O17: =H17/H$14 -> 0.026861639
B18: Payroll | D18: ='P&L'!F36 -> 13.5 | E18: ='P&L'!G36 -> 16.2 | F18: ='P&L'!H36 -> 20.25 | G18: ='P&L'!I36 -> 25.3125 | H18: ='P&L'!J36 -> 31.640625 | J18: =B18 -> Payroll | K18: =D18/D$14 -> 0.021428571 | L18: =E18/E$14 -> 0.0075208914 | M18: =F18/F$14 -> 0.0053066038 | N18: =G18/G$14 -> 0.0042598684 | O18: =H18/H$14 -> 0.0036439809
B19: Other Operating Expenses | D19: ='P&L'!F28-'P&L'!F32-'P&L'!F36 -> 139.05 | E19: ='P&L'!G28-'P&L'!G32-'P&L'!G36 -> 349.38 | F19: ='P&L'!H28-'P&L'!H32-'P&L'!H36 -> 687.69 | G19: ='P&L'!I28-'P&L'!I32-'P&L'!I36 -> 1184.5157 | H19: ='P&L'!J28-'P&L'!J32-'P&L'!J36 -> 1774.9686 | J19: =B19 -> Other Operating Expenses | K19: =D19/D$14 -> 0.22071429 | L19: =E19/E$14 -> 0.16220056 | M19: =F19/F$14 -> 0.18021226 | N19: =G19/G$14 -> 0.19934344 | O19: =H19/H$14 -> 0.20441921
B20: EBITDA | D20: =D16-SUM(D17:D19) -> 184.8 | E20: =E16-SUM(E17:E19) -> 651.78 | F20: =F16-SUM(F17:F19) -> 1197.615 | G20: =G16-SUM(G17:G19) -> 1893.8477 | H20: =H16-SUM(H17:H19) -> 2792.5537 | J20: =B20 -> EBITDA | K20: =D20/D$14 -> 0.29333333 | L20: =E20/E$14 -> 0.30259053 | M20: =F20/F$14 -> 0.31384041 | N20: =G20/G$14 -> 0.3187177 | O20: =H20/H$14 -> 0.32161225
B21: EBIT | D21: ='P&L'!F46 -> 147.44829 | E21: ='P&L'!G46 -> 611.92709 | F21: ='P&L'!H46 -> 1152.6457 | G21: ='P&L'!I46 -> 1840.1825 | H21: ='P&L'!J46 -> 2730.4053 | J21: =B21 -> EBIT | K21: =D21/D$14 -> 0.23404491 | L21: =E21/E$14 -> 0.28408871 | M21: =F21/F$14 -> 0.30205601 | N21: =G21/G$14 -> 0.30968632 | O21: =H21/H$14 -> 0.31445474
B22: Net Profit | D22: ='P&L'!F56 -> -32.216659 | E22: ='P&L'!G56 -> 306.77627 | F22: ='P&L'!H56 -> 568.12913 | G22: ='P&L'!I56 -> 837.75348 | H22: ='P&L'!J56 -> 1850.1168 | J22: =B22 -> Net Profit | K22: =D22/D$14 -> -0.051137554 | L22: =E22/E$14 -> 0.14242167 | M22: =F22/F$14 -> 0.1488808 | N22: =G22/G$14 -> 0.14098645 | O22: =H22/H$14 -> 0.21307386
B24: Cash Flow Statement | D24: =D13 -> 25-26 | E24: =E13 -> 26-27 | F24: =F13 -> 27-28 | G24: =G13 -> 28-29 | H24: =H13 -> 29-30 | J24: Balance Sheet | K24: =K5 -> 25-26 | L24: =L5 -> 26-27 | M24: =M5 -> 27-28 | N24: =N5 -> 28-29 | O24: =O5 -> 29-30
B25: Opening Balance | D25: =CFS!F56 -> 0.3696979 | E25: =CFS!G56 -> 2738.0139 | F25: =CFS!H56 -> 2701.5729 | G25: =CFS!I56 -> 3054.1694 | H25: =CFS!J56 -> 3732.0171 | J25: Assets
B26: Cash Flow from Operating Activities | D26: =CFS!F24 -> 116.49248 | E26: =CFS!G24 -> 448.22137 | F26: =CFS!H24 -> 859.565 | G26: =CFS!I24 -> 1218.814 | H26: =CFS!J24 -> 1612.4049 | J26: Fixed Assets (Tangible & Intangible) | K26: =BS!F38 -> 165.90675 | L26: =BS!G38 -> 190.05384 | M26: =BS!H38 -> 220.08457 | N26: =BS!I38 -> 263.41938 | O26: =BS!J38 -> 304.27091
B27: Cash Flow from Investing Activities | D27: =CFS!F50 -> -43 | E27: =CFS!G50 -> -64 | F27: =CFS!H50 -> -75 | G27: =CFS!I50 -> -97 | H27: =CFS!J50 -> -103 | J27: Current Assets | K27: =BS!F45 -> 2890.2639 | L27: =BS!G45 -> 3079.7525 | M27: =BS!H45 -> 3658.9153 | N27: =BS!I45 -> 4617.9514 | O27: =BS!J45 -> 6040.0091
B28: Cash Flow from Financing Activities | D28: =CFS!F38 -> 2664.1517 | E28: =CFS!G38 -> -420.66236 | F28: =CFS!H38 -> -431.9685 | G28: =CFS!I38 -> -443.96626 | H28: =CFS!J38 -> -456.69755 | J28: Total Assets | K28: =K26+K27 -> 3056.1706 | L28: =L26+L27 -> 3269.8063 | M28: =M26+M27 -> 3878.9999 | N28: =N26+N27 -> 4881.3708 | O28: =O26+O27 -> 6344.28
B29: Net Cash Flow | D29: =D26+D27+D28 -> 2737.6442 | E29: =E26+E27+E28 -> -36.440992 | F29: =F26+F27+F28 -> 352.5965 | G29: =G26+G27+G28 -> 677.84776 | H29: =H26+H27+H28 -> 1052.7073 | J29: Liabilities
B30: Closing Balance | D30: =D25+D29 -> 2738.0139 | E30: =E25+E29 -> 2701.5729 | F30: =F25+F29 -> 3054.1694 | G30: =G25+G29 -> 3732.0171 | H30: =H25+H29 -> 4784.7245 | J30: Current Liabilities | K30: =BS!F21 -> 584.40745 | L30: =BS!G21 -> 756.21774 | M30: =BS!H21 -> 1081.6338 | N30: =BS!I21 -> 1551.5689 | O30: =BS!J21 -> 1490.3971
J31: Non-current liabilities | K31: =BS!F19 -> 2433.8957 | L31: =BS!G19 -> 2168.9448 | M31: =BS!H19 -> 1884.5932 | N31: =BS!I19 -> 1579.2756 | O31: =BS!J19 -> 1253.2398
B32: Valuation Method | D32: Amt in INR Lakhs (Pre Funding) | J32: Equity Share Capital | K32: =BS!F11 -> 37.867463 | L32: =BS!G11 -> 344.64373 | M32: =BS!H11 -> 912.77286 | N32: =BS!I11 -> 1750.5263 | O32: =BS!J11 -> 3600.6431
B33: DCF Perpetual Method | D33: ='Valuation-DCF-Terminal Growth '!C35 -> 1772.8052 | J33: Total Liabilities | K33: =K30+K31+K32 -> 3056.1706 | L33: =L30+L31+L32 -> 3269.8063 | M33: =M30+M31+M32 -> 3878.9999 | N33: =N30+N31+N32 -> 4881.3708 | O33: =O30+O31+O32 -> 6344.28
B34: Comparables - Revenue Multiple Method | D34: ='Valuation-Comparables'!D14 -> 2926.0895
B35: VC Method | E35: ='Valuation-VC '!C13 -> 3473.1933
B36: Average Enterprise Valuation | D36: =AVERAGE(D33:E35) -> 2724.0294
B38: plus Cash in Hand | E38: =Config!C8 -> 0.3696979
B39: minus Existing Debt | E39: =Config!G9 -> 137.06614
B40: Equity Valuation (Post Money) | E40: =D36+E38-E39 -> 2587.3329
B42: Fund Raised (total) | E42: =SUM(Config!C15:C19) -> 300
B43: Equity Valuation (Pre-Money) | E43: =E40-E42 -> 2287.3329
B44: Fund Raised (1st Round) | E44: =Config!C15 -> 300
B45: Equity Dilution | E45: =E44/(E44+E43) -> 0.11594952

Sheet Config
B2: Config
B4: Feel free to change the cells in orange
B7: Opening Balance - Current Assets in Lakhs | C7: Value | F7: Liabilities in Lakhs | G7: Value
B8: Cash in Hand | C8: =36969.79/100000 -> 0.3696979 | F8: Opening A/C Payable | G8: =8279574.94/100000 -> 82.795749
B9: Opening Inventory | C9: =3175974.94/100000 -> 31.759749 | F9: Opening Loan | G9: =13706613.83/100000 -> 137.06614
B10: Opening A/C Receivable | C10: =6062984.61/100000 -> 60.629846
B14: Funding Round | C14: Amount | D14: Month
B15: Round-1 | C15: 300 | D15: M1
B16: Round-2 | C16: 0 | D16: M13
B17: Round-3 | D17: M25
B18: Round-4 | D18: M37
B19: Round-5
B21: Round | C21: M1 | D21: M2 | E21: M3 | F21: M4 | G21: M5 | H21: M6 | I21: M7 | J21: M8 | K21: M9 | L21: M10 | M21: M11 | N21: M12 | O21: M13 | P21: M14 | Q21: M15 | R21: M16 | S21: M17 | T21: M18 | U21: M19 | V21: M20 | W21: M21 | X21: M22 | Y21: M23 | Z21: M24 | AA21: M25 | AB21: M26 | AC21: M27 | AD21: M28 | AE21: M29 | AF21: M30 | AG21: M31 | AH21: M32 | AI21: M33 | AJ21: M34 | AK21: M35 | AL21: M36 | AM21: M37 | AN21: M38 | AO21: M39 | AP21: M40 | AQ21: M41 | AR21: M42 | AS21: M43 | AT21: M44 | AU21: M45 | AV21: M46 | AW21: M47 | AX21: M48 | AY21: M49 | AZ21: M50 | BA21: M51 | BB21: M52 | BC21: M53 | BD21: M54 | BE21: M55 | BF21: M56 | BG21: M57 | BH21: M58 | BI21: M59 | BJ21: M60
B22: =B15 -> Round-1 | C22: =IF(C$21=$D$15,$C$15,0) -> 300 | D22: =IF(D$21=$D$15,$C$15,0) -> 0 | E22: =IF(E$21=$D$15,$C$15,0) -> 0 | F22: =IF(F$21=$D$15,$C$15,0) -> 0 | G22: =IF(G$21=$D$15,$C$15,0) -> 0 | H22: =IF(H$21=$D$15,$C$15,0) -> 0 | I22: =IF(I$21=$D$15,$C$15,0) -> 0 | J22: =IF(J$21=$D$15,$C$15,0) -> 0 | ... BJ22: =IF(BJ$21=$D$15,$C$15,0) -> 0
B23: =B16 -> Round-2 | C23: =IF(C$21=$D$16,$C$16,0) -> 0 | D23: =IF(D$21=$D$16,$C$16,0) -> 0 | E23: =IF(E$21=$D$16,$C$16,0) -> 0 | F23: =IF(F$21=$D$16,$C$16,0) -> 0 | G23: =IF(G$21=$D$16,$C$16,0) -> 0 | H23: =IF(H$21=$D$16,$C$16,0) -> 0 | I23: =IF(I$21=$D$16,$C$16,0) -> 0 | J23: =IF(J$21=$D$16,$C$16,0) -> 0 | ... BJ23: =IF(BJ$21=$D$16,$C$16,0) -> 0
B24: =B17 -> Round-3 | C24: =IF(C$21=$D$17,$C$17,0) -> 0 | D24: =IF(D$21=$D$17,$C$17,0) -> 0 | E24: =IF(E$21=$D$17,$C$17,0) -> 0 | F24: =IF(F$21=$D$17,$C$17,0) -> 0 | G24: =IF(G$21=$D$17,$C$17,0) -> 0 | H24: =IF(H$21=$D$17,$C$17,0) -> 0 | I24: =IF(I$21=$D$17,$C$17,0) -> 0 | J24: =IF(J$21=$D$17,$C$17,0) -> 0 | ... BJ24: =IF(BJ$21=$D$17,$C$17,0) -> 0
B25: =B18 -> Round-4 | C25: =IF(C$21=$D$18,$C$18,0) -> 0 | D25: =IF(D$21=$D$18,$C$18,0) -> 0 | E25: =IF(E$21=$D$18,$C$18,0) -> 0 | F25: =IF(F$21=$D$18,$C$18,0) -> 0 | G25: =IF(G$21=$D$18,$C$18,0) -> 0 | H25: =IF(H$21=$D$18,$C$18,0) -> 0 | I25: =IF(I$21=$D$18,$C$18,0) -> 0 | J25: =IF(J$21=$D$18,$C$18,0) -> 0 | ... BJ25: =IF(BJ$21=$D$18,$C$18,0) -> 0
B26: =B19 -> Round-5 | C26: =IF(C$21=$D$19,$C$19,0) -> 0 | D26: =IF(D$21=$D$19,$C$19,0) -> 0 | E26: =IF(E$21=$D$19,$C$19,0) -> 0 | F26: =IF(F$21=$D$19,$C$19,0) -> 0 | G26: =IF(G$21=$D$19,$C$19,0) -> 0 | H26: =IF(H$21=$D$19,$C$19,0) -> 0 | I26: =IF(I$21=$D$19,$C$19,0) -> 0 | J26: =IF(J$21=$D$19,$C$19,0) -> 0 | ... BJ26: =IF(BJ$21=$D$19,$C$19,0) -> 0
B27: Total | C27: =SUM(C22:C26) -> 300 | D27: =SUM(D22:D26) -> 0 | E27: =SUM(E22:E26) -> 0 | F27: =SUM(F22:F26) -> 0 | G27: =SUM(G22:G26) -> 0 | H27: =SUM(H22:H26) -> 0 | I27: =SUM(I22:I26) -> 0 | J27: =SUM(J22:J26) -> 0 | ... BJ27: =SUM(BJ22:BJ26) -> 0
B29: Effective Income Tax | C29: 25-26 | D29: 26-27 | E29: 27-28 | F29: 28-29 | G29: 29-30
B30: Total Funding in Lakhs | C30: =SUM(C27:N27) -> 300 | D30: =SUM(O27:Z27) -> 0 | E30: =SUM(AA27:AL27) -> 0 | F30: =SUM(AM27:AX27) -> 0 | G30: =SUM(AY27:BJ27) -> 0

Sheet PAG-2
B5: Annual Sales / Revenue
B7: SI No. | D7: Particulars | F7: FY 2025-26 (₹)
B9: 1 | D9: Corporate Sales | F9: =WC!E7*Ro -> 13500000
B11: =B9+1 -> 2 | D11: Millet Cafeteria | F11: =WC!E8*Ro -> 27000000
B13: =B11+1 -> 3 | D13: Retail Market Sales | F13: =WC!E9*Ro -> 7500000
B15: =B13+1 -> 4 | D15: Export Sales | F15: =WC!E10*Ro -> 15000000
B17: Total | F17: =SUM(F9:F15) -> 63000000

Sheet BS
B2: Check (Assets - Liabilities) | F2: =F56-F32 -> 0 | G2: =G56-G32 -> 0 | H2: =H56-H32 -> 0 | I2: =I56-I32 -> 0 | J2: =J56-J32 -> 0 | K2: =K56-K32 -> 0 | L2: =L56-L32 -> 0 | M2: =M56-M32 -> 0 | ... O2: =O56-O32 -> 0
B4: Balance sheet
O5: =Do -> (₹ in Lakhs)
B7: SI No. | D7: Particulars | F7: 25-26 | G7: 26-27 | H7: 27-28 | I7: 28-29 | J7: 29-30 | K7: 30-31 | L7: 31-32 | M7: 32-33 | N7: 33-34 | O7: 34-35
B9: Liabilities
B11: A | D11: Closing Capital ( i + ii + iii - iv ) | F11: =F13+F15+F17 -> 37.867463 | G11: =G13+G15+G17 -> 344.64373 | H11: =H13+H15+H17 -> 912.77286 | I11: =I13+I15+I17 -> 1750.5263 | J11: =J13+J15+J17 -> 3600.6431 | K11: =K13+K15+K17 -> 5995.5619 | L11: =L13+L15+L17 -> 9069.7514 | M11: =M13+M15+M17 -> 12972.938 | ... O11: =O13+O15+O17 -> 23852.186
D13: i) Equity Capital | F13: 75 | G13: =F13 -> 75 | H13: =G13 -> 75 | I13: =H13 -> 75 | J13: =I13 -> 75 | K13: =J13 -> 75 | L13: =K13 -> 75 | M13: =L13 -> 75 | N13: =M13 -> 75 | O13: =N13 -> 75
D15: ii) Additional Capital | F15: =CFS!F30 -> 300 | G15: =F15+CFS!G30 -> 300 | H15: =G15+CFS!H30 -> 300 | I15: =H15+CFS!I30 -> 300 | J15: =I15+CFS!J30 -> 300 | K15: =J15+CFS!K30 -> 300 | L15: =K15+CFS!L30 -> 300 | M15: =L15+CFS!M30 -> 300 | N15: =M15+CFS!N30 -> 300 | O15: =N15+CFS!O30 -> 300
D17: iii) Profit / (Loss) | F17: ='P&L'!F56+(-30491587.8/10^5) -> -337.13254 | G17: ='P&L'!G56+F17 -> -30.356269 | H17: ='P&L'!H56+G17 -> 537.77286 | I17: ='P&L'!I56+H17 -> 1375.5263 | J17: ='P&L'!J56+I17 -> 3225.6431 | K17: ='P&L'!K56+J17 -> 5620.5619 | L17: ='P&L'!L56+K17 -> 8694.7514 | M17: ='P&L'!M56+L17 -> 12597.938 | N17: ='P&L'!N56+M17 -> 17470.025 | O17: ='P&L'!O56+N17 -> 23477.186
B19: B | D19: Non-Current Liabilities | F19: ='Debt Schedule'!C70 -> 2433.8957 | G19: ='Debt Schedule'!D70 -> 2168.9448 | H19: ='Debt Schedule'!E70 -> 1884.5932 | I19: ='Debt Schedule'!F70 -> 1579.2756 | J19: ='Debt Schedule'!G70 -> 1253.2398 | K19: ='Debt Schedule'!H70 -> 968.47482 | L19: ='Debt Schedule'!I70 -> 665.48845 | M19: ='Debt Schedule'!J70 -> 343.08801 | ... O19: ='Debt Schedule'!L70 -> 1.5254464e-13
B21: C | D21: Current Liabilities | F21: =SUM(F22:F29) -> 584.40745 | G21: =SUM(G22:G29) -> 756.21774 | H21: =SUM(H22:H29) -> 1081.6338 | I21: =SUM(I22:I29) -> 1551.5689 | J21: =SUM(J22:J29) -> 1490.3971 | K21: =SUM(K22:K29) -> 1776.6574 | L21: =SUM(L22:L29) -> 2122.5867 | M21: =SUM(M22:M29) -> 2542.9617 | ... O21: =SUM(O22:O29) -> 3247.1477
D23: Trade Payables | F23: =WC!E38 -> 7.4630137 | G23: =WC!F38 -> 29.833973 | H23: =WC!G38 -> 49.82589 | I23: =WC!H38 -> 73.479588 | J23: =WC!I38 -> 105.49537 | K23: =WC!J38 -> 135.54124 | L23: =WC!K38 -> 172.13322 | M23: =WC!L38 -> 217.80956 | ... O23: =WC!N38 -> 342.6926 | X23: Payables Days | Z23: 0
D25: Other liabilities | F25: =(31476895.65+1518839.4)/100000 -> 329.95735 | G25: =F25 -> 329.95735 | H25: =G25 -> 329.95735 | I25: =H25 -> 329.95735 | J25: =I25 -> 329.95735 | K25: =J25 -> 329.95735 | L25: =K25 -> 329.95735 | M25: =L25 -> 329.95735 | N25: =M25 -> 329.95735 | O25: =N25 -> 329.95735
D27: Current portion of Loang term Debt | F27: ='Debt Schedule'!C69 -> 246.98709 | G27: ='Debt Schedule'!D69 -> 264.95088 | H27: ='Debt Schedule'!E69 -> 284.3516 | I27: ='Debt Schedule'!F69 -> 305.31765 | J27: ='Debt Schedule'!G69 -> 326.03574 | K27: ='Debt Schedule'!H69 -> 284.76501 | L27: ='Debt Schedule'!I69 -> 302.98637 | M27: ='Debt Schedule'!J69 -> 322.40044 | ... O27: ='Debt Schedule'!L69 -> 0
D29: Provision for Tax | F29: ='P&L'!F54 -> 0 | G29: ='P&L'!G54 -> 131.47554 | H29: ='P&L'!H54 -> 417.49898 | I29: ='P&L'!I54 -> 842.81432 | J29: ='P&L'!J54 -> 728.90861 | K29: ='P&L'!K54 -> 1026.3937 | L29: ='P&L'!L54 -> 1317.5098 | M29: ='P&L'!M54 -> 1672.7943 | ... O29: ='P&L'!O54 -> 2574.4977
D32: Total Liabilities | F32: =F11+F19+F21 -> 3056.1706 | G32: =G11+G19+G21 -> 3269.8063 | H32: =H11+H19+H21 -> 3878.9999 | I32: =I11+I19+I21 -> 4881.3708 | J32: =J11+J19+J21 -> 6344.28 | K32: =K11+K19+K21 -> 8740.694 | L32: =L11+L19+L21 -> 11857.827 | M32: =M11+M19+M21 -> 15858.988 | ... O32: =O11+O19+O21 -> 27099.334
B36: Assets
B38: D | D38: Non-Current Assets | F38: =SUM(F40:F42) -> 165.90675 | G38: =SUM(G40:G42) -> 190.05384 | H38: =SUM(H40:H42) -> 220.08457 | I38: =SUM(I40:I42) -> 263.41938 | J38: =SUM(J40:J42) -> 304.27091 | K38: =SUM(K40:K42) -> 338.0183 | L38: =SUM(L40:L42) -> 396.15422 | M38: =SUM(M40:M42) -> 443.90101 | ... O38: =SUM(O40:O42) -> 597.55329
D40: Fixed Assets | F40: =DAS!F90 -> 142.86852 | G40: =DAS!H90 -> 167.01561 | H40: =DAS!J90 -> 197.04634 | I40: =DAS!L90 -> 240.38115 | J40: =DAS!N90 -> 281.23268 | K40: =DAS!P90 -> 314.98007 | L40: =DAS!R90 -> 373.11599 | M40: =DAS!T90 -> 420.86278 | N40: =DAS!V90 -> 480.53499 | O40: =DAS!X90 -> 574.51506
D42: Other Non-Current Assets | F42: =(145000+333223+1825600)/100000 -> 23.03823 | G42: =F42 -> 23.03823 | H42: =G42 -> 23.03823 | I42: =H42 -> 23.03823 | J42: =I42 -> 23.03823 | K42: =J42 -> 23.03823 | L42: =K42 -> 23.03823 | M42: =L42 -> 23.03823 | N42: =M42 -> 23.03823 | O42: =N42 -> 23.03823
B45: E | D45: Current Assets | F45: =SUM(F46:F53) -> 2890.2639 | G45: =SUM(G46:G53) -> 3079.7525 | H45: =SUM(H46:H53) -> 3658.9153 | I45: =SUM(I46:I53) -> 4617.9514 | J45: =SUM(J46:J53) -> 6040.0091 | K45: =SUM(K46:K53) -> 8402.6757 | L45: =SUM(L46:L53) -> 11461.672 | M45: =SUM(M46:M53) -> 15415.087 | ... O45: =SUM(O46:O53) -> 26501.78
D47: Inventory | F47: =WC!E52 -> 33.583562 | G47: =WC!F52 -> 134.25288 | H47: =WC!G52 -> 224.21651 | I47: =WC!H52 -> 330.65814 | J47: =WC!I52 -> 474.72918 | K47: =WC!J52 -> 609.93559 | L47: =WC!K52 -> 774.59949 | M47: =WC!L52 -> 980.14301 | ... O47: =WC!N52 -> 1542.1167
D49: Trade Receivables | F49: =WC!E24 -> 51.780822 | G49: =WC!F24 -> 177.0411 | H49: =WC!G24 -> 313.64384 | I49: =WC!H24 -> 488.39055 | J49: =WC!I24 -> 713.66986 | K49: =WC!J24 -> 928.37102 | L49: =WC!K24 -> 1179.4466 | M49: =WC!L24 -> 1487.0456 | ... O49: =WC!N24 -> 2278.508 | X49: Receivables Days | Z49: 0
D51: Cash and Cash equivalence | F51: =CFS!F58 -> 2738.0139 | G51: =CFS!G58 -> 2701.5729 | H51: =CFS!H58 -> 3054.1694 | I51: =CFS!I58 -> 3732.0171 | J51: =CFS!J58 -> 4784.7245 | K51: =CFS!K58 -> 6797.4835 | L51: =CFS!L58 -> 9440.7406 | M51: =CFS!M58 -> 12881.013 | ... O51: =CFS!O58 -> 22614.27
D53: Other Current Assets | F53: =(6617160.89+71400)/100000 -> 66.885609 | G53: =F53 -> 66.885609 | H53: =G53 -> 66.885609 | I53: =H53 -> 66.885609 | J53: =I53 -> 66.885609 | K53: =J53 -> 66.885609 | L53: =K53 -> 66.885609 | M53: =L53 -> 66.885609 | N53: =M53 -> 66.885609 | O53: =N53 -> 66.885609 | X53: Advance Tax
D56: Total Assets | F56: =F38+F45 -> 3056.1706 | G56: =G38+G45 -> 3269.8063 | H56: =H38+H45 -> 3878.9999 | I56: =I38+I45 -> 4881.3708 | J56: =J38+J45 -> 6344.28 | K56: =K38+K45 -> 8740.694 | L56: =L38+L45 -> 11857.827 | M56: =M38+M45 -> 15858.988 | ... O56: =O38+O45 -> 27099.334
F57: =F56-F32 -> 0 | G57: =G56-G32 -> 0 | H57: =H56-H32 -> 0 | I57: =I56-I32 -> 0 | J57: =J56-J32 -> 0 | K57: =K56-K32 -> 0 | L57: =L56-L32 -> 0 | M57: =M56-M32 -> 0 | ... O57: =O56-O32 -> 0
B62: Net Worth | F62: =F11 -> 37.867463 | G62: =G11 -> 344.64373 | H62: =H11 -> 912.77286 | I62: =I11 -> 1750.5263 | J62: =J11 -> 3600.6431 | K62: =K11 -> 5995.5619 | L62: =L11 -> 9069.7514 | M62: =M11 -> 12972.938 | ... O62: =O11 -> 23852.186
B64: Average Net Worth | F64: =(E62+F62)/2 -> 18.933732 | G64: =(F62+G62)/2 -> 191.2556 | H64: =(G62+H62)/2 -> 628.7083 | I64: =(H62+I62)/2 -> 1331.6496 | J64: =(I62+J62)/2 -> 2675.5847 | K64: =(J62+K62)/2 -> 4798.1025 | L64: =(K62+L62)/2 -> 7532.6566 | M64: =(L62+M62)/2 -> 11021.345 | ... O64: =(N62+O62)/2 -> 20848.605
B66: Capital Employed | F66: =F11+F19 -> 2471.7632 | G66: =G11+G19 -> 2513.5886 | H66: =H11+H19 -> 2797.3661 | I66: =I11+I19 -> 3329.8019 | J66: =J11+J19 -> 4853.8829 | K66: =K11+K19 -> 6964.0367 | L66: =L11+L19 -> 9735.2398 | M66: =M11+M19 -> 13316.026 | ... O66: =O11+O19 -> 23852.186
B68: Average Capital Employed | F68: =(E66+F66)/2 -> 1235.8816 | G68: =(F66+G66)/2 -> 2492.6759 | H68: =(G66+H66)/2 -> 2655.4773 | I68: =(H66+I66)/2 -> 3063.584 | J68: =(I66+J66)/2 -> 4091.8424 | K68: =(J66+K66)/2 -> 5908.9598 | L68: =(K66+L66)/2 -> 8349.6383 | M68: =(L66+M66)/2 -> 11525.633 | ... O68: =(N66+O66)/2 -> 20848.605
B70: Fixed Assets | F70: =F40 -> 142.86852 | G70: =G40 -> 167.01561 | H70: =H40 -> 197.04634 | I70: =I40 -> 240.38115 | J70: =J40 -> 281.23268 | K70: =K40 -> 314.98007 | L70: =L40 -> 373.11599 | M70: =M40 -> 420.86278 | ... O70: =O40 -> 574.51506
B72: Average Fixed Assets | F72: =(E70+F70)/2 -> 71.43426 | G72: =(F70+G70)/2 -> 154.94206 | H72: =(G70+H70)/2 -> 182.03098 | I72: =(H70+I70)/2 -> 218.71375 | J72: =(I70+J70)/2 -> 260.80691 | K72: =(J70+K70)/2 -> 298.10637 | L72: =(K70+L70)/2 -> 344.04803 | M72: =(L70+M70)/2 -> 396.98939 | ... O72: =(N70+O70)/2 -> 527.52503
B74: Total Assets | F74: =F56 -> 3056.1706 | G74: =G56 -> 3269.8063 | H74: =H56 -> 3878.9999 | I74: =I56 -> 4881.3708 | J74: =J56 -> 6344.28 | K74: =K56 -> 8740.694 | L74: =L56 -> 11857.827 | M74: =M56 -> 15858.988 | ... O74: =O56 -> 27099.334
B76: Average Fixed Assets | F76: =(E74+F74)/2 -> 1528.0853 | G76: =(F74+G74)/2 -> 3162.9885 | H76: =(G74+H74)/2 -> 3574.4031 | I76: =(H74+I74)/2 -> 4380.1854 | J76: =(I74+J74)/2 -> 5612.8254 | K76: =(J74+K74)/2 -> 7542.487 | L76: =(K74+L74)/2 -> 10299.26 | M76: =(L74+M74)/2 -> 13858.407 | ... O76: =(N74+O74)/2 -> 23989.617
B79: Increase in Trade Receivables | F79: =Config!C10-BS!F49 -> 8.8490242 | G79: =F49-G49 -> -125.26027 | H79: =G49-H49 -> -136.60274 | I79: =H49-I49 -> -174.74671 | J79: =I49-J49 -> -225.27931 | K79: =J49-K49 -> -214.70116 | L79: =K49-L49 -> -251.07563 | M79: =L49-M49 -> -307.59896 | N79: =M49-N49 -> -362.34944 | O79: =N49-O49 -> -429.11297
B81: Increase in Trade Pyables | F81: =F23-Config!G8 -> -75.332736 | G81: =G23-F23 -> 22.370959 | H81: =H23-G23 -> 19.991918 | I81: =I23-H23 -> 23.653697 | J81: =J23-I23 -> 32.015786 | K81: =K23-J23 -> 30.04587 | L81: =L23-K23 -> 36.591977 | M81: =M23-L23 -> 45.676339 | N81: =N23-M23 -> 55.983834 | O81: =O23-N23 -> 68.899208
B83: Increase in Inventory | F83: =Config!C9-BS!F47 -> -1.8238122 | G83: =F47-G47 -> -100.66932 | H83: =G47-H47 -> -89.96363 | I83: =H47-I47 -> -106.44164 | J83: =I47-J47 -> -144.07104 | K83: =J47-K47 -> -135.20641 | L83: =K47-L47 -> -164.6639 | M83: =L47-M47 -> -205.54352 | N83: =M47-N47 -> -251.92725 | O83: =N47-O47 -> -310.04643

Sheet P&L
B2: Profitability Statement
O3: =Do -> (₹ in Lakhs)
B5: SI No. | D5: Particulars | F5: =[2]Ratios!F4 -> 2025-26 | G5: =[2]Ratios!H4 -> 2026-27 | H5: =[2]Ratios!J4 -> 2027-28 | I5: =[2]Ratios!L4 -> 2028-29 | J5: =[2]Ratios!N4 -> 2029-30 | K5: =[2]Ratios!P4 -> 2030-31 | L5: =[2]Ratios!R4 -> 2031-32 | M5: =[2]Ratios!T4 -> 2032-33 | N5: =[2]Ratios!V4 -> 2033-34 | O5: =[2]Ratios!X4 -> 2034-35 | Q5: Ref Sheet
B7: 1 | D7: Revenue from Operations | F7: =SUM(F8:F15) -> 630 | G7: =SUM(G8:G15) -> 2154 | H7: =SUM(H8:H15) -> 3816 | I7: =SUM(I8:I15) -> 5942.085 | J7: =SUM(J8:J15) -> 8682.9833 | K7: =SUM(K8:K15) -> 11295.181 | L7: =SUM(L8:L15) -> 14349.934 | M7: =SUM(M8:M15) -> 18092.388 | ... O7: =SUM(O8:O15) -> 27721.848 | Q7: RFO
D9: ='PAG-2'!D9 -> Corporate Sales | F9: {=TRANSPOSE('Revenue generation breakup'!D7:D16)} -> 135 | G9: 162 | H9: 202.5 | I9: 253.125 | J9: 316.40625 | K9: 395.50781 | L9: 494.38477 | M9: 617.98096 | N9: 772.4762 | O9: 965.59525
D11: ='PAG-2'!D11 -> Millet Cafeteria | F11: {=TRANSPOSE('Revenue generation breakup'!E7:E16)} -> 270 | G11: 792 | H11: 1633.5 | I11: 2874.96 | J11: 4348.377 | K11: 5811.0129 | L11: 7409.0414 | M11: 9304.8844 | N11: 11371.789 | O11: 13622.122
D13: ='PAG-2'!D13 -> Retail Market Sales | F13: {=TRANSPOSE('Revenue generation breakup'!F7:F16)} -> 75 | G13: 600 | H13: 1200 | I13: 1800 | J13: 2700 | K13: 3375 | L13: 4218.75 | M13: 5273.4375 | N13: 6591.7969 | O13: 8239.7461
D15: ='PAG-2'!D15 -> Export Sales | F15: {=TRANSPOSE('Revenue generation breakup'!G7:G16)} -> 150 | G15: 600 | H15: 780 | I15: 1014 | J15: 1318.2 | K15: 1713.66 | L15: 2227.758 | M15: 2896.0854 | N15: 3764.911 | O15: 4894.3843
B17: 2 | D17: Cost of Materials Sold | F17: =SUM(F19:F23) -> 272.4 | G17: =SUM(G19:G23) -> 1088.94 | H17: =SUM(H19:H23) -> 1818.645 | I17: =SUM(I19:I23) -> 2682.005 | J17: =SUM(J19:J23) -> 3850.5811 | K17: =SUM(K19:K23) -> 4947.2554 | L17: =SUM(L19:L23) -> 6282.8625 | M17: =SUM(M19:M23) -> 7950.0489 | ... O17: =SUM(O19:O23) -> 12508.28 | Q17: MC
D19: ='All Costs'!D19 -> Direct Cost (Corporate Sales ) | F19: ='All Costs'!E19 -> 47.25 | G19: ='All Costs'!F19 -> 56.7 | H19: ='All Costs'!G19 -> 70.875 | I19: ='All Costs'!H19 -> 88.59375 | J19: ='All Costs'!I19 -> 110.74219 | K19: ='All Costs'!J19 -> 138.42773 | L19: ='All Costs'!K19 -> 173.03467 | M19: ='All Costs'!L19 -> 216.29333 | ... O19: ='All Costs'!N19 -> 337.95834
D21: ='All Costs'!D20 -> Direct Cost ( Millet Cafeteria ) | F21: ='All Costs'!E20 -> 59.4 | G21: ='All Costs'!F20 -> 174.24 | H21: ='All Costs'!G20 -> 359.37 | I21: ='All Costs'!H20 -> 632.4912 | J21: ='All Costs'!I20 -> 956.64294 | K21: ='All Costs'!J20 -> 1278.4228 | L21: ='All Costs'!K20 -> 1629.9891 | M21: ='All Costs'!L20 -> 2047.0746 | ... O21: ='All Costs'!N20 -> 2996.8668
D23: Direct Cost (Retail + Exports) | F23: ='All Costs'!E22+'All Costs'!E21 -> 165.75 | G23: ='All Costs'!F22+'All Costs'!F21 -> 858 | H23: ='All Costs'!G22+'All Costs'!G21 -> 1388.4 | I23: ='All Costs'!H22+'All Costs'!H21 -> 1960.92 | J23: ='All Costs'!I22+'All Costs'!I21 -> 2783.196 | K23: ='All Costs'!J22+'All Costs'!J21 -> 3530.4048 | L23: ='All Costs'!K22+'All Costs'!K21 -> 4479.8387 | M23: ='All Costs'!L22+'All Costs'!L21 -> 5686.681 | ... O23: ='All Costs'!N22+'All Costs'!N21 -> 9173.4547
B25: 3 | D25: Gross Profit [1-2] | F25: =F7-F17 -> 357.6 | G25: =G7-G17 -> 1065.06 | H25: =H7-H17 -> 1997.355 | I25: =I7-I17 -> 3260.0801 | J25: =J7-J17 -> 4832.4021 | K25: =K7-K17 -> 6347.9253 | L25: =L7-L17 -> 8067.0717 | M25: =M7-M17 -> 10142.339 | ... O25: =O7-O17 -> 15213.568
D26: Gross Profit % | F26: =F25/F$7 -> 0.56761905 | G26: =G25/G$7 -> 0.49445682 | H26: =H25/H$7 -> 0.52341588 | I26: =I25/I$7 -> 0.54864245 | J26: =J25/J$7 -> 0.55653708 | K26: =K25/K$7 -> 0.56200299 | L26: =L25/L$7 -> 0.56216785 | M26: =M25/M$7 -> 0.56058599 | ... O26: =O25/O$7 -> 0.54879343
B28: 4 | D28: Indirect Expenses | F28: =SUM(F30:F39) -> 172.8 | G28: =SUM(G30:G40) -> 413.28 | H28: =SUM(H30:H40) -> 799.74 | I28: =SUM(I30:I40) -> 1366.2324 | J28: =SUM(J30:J39) -> 2039.8484 | K28: =SUM(K30:K39) -> 2715.0488 | L28: =SUM(L30:L39) -> 3457.7321 | M28: =SUM(M30:M39) -> 4341.3415 | N28: =SUM(N30:N39) -> 5312.5777 | O28: =SUM(O30:O39) -> 6379.9718
D30: Employee Costs | F30: ='All Costs'!E29+'All Costs'!E30 -> 101.25 | G30: ='All Costs'!F29+'All Costs'!F30 -> 238.5 | H30: ='All Costs'!G29+'All Costs'!G30 -> 459 | I30: ='All Costs'!H29+'All Costs'!H30 -> 782.02125 | J30: ='All Costs'!I29+'All Costs'!I30 -> 1166.1958 | K30: ='All Costs'!J29+'All Costs'!J30 -> 1551.6302 | L30: ='All Costs'!K29+'All Costs'!K30 -> 1975.8566 | M30: ='All Costs'!L29+'All Costs'!L30 -> 2480.7163 | ... O30: ='All Costs'!N29+'All Costs'!N30 -> 3646.9293 | Q30: IE
D32: Promotional Expenses | F32: ='All Costs'!E37+'All Costs'!E38 -> 20.25 | G32: ='All Costs'!F37+'All Costs'!F38 -> 47.7 | H32: ='All Costs'!G37+'All Costs'!G38 -> 91.8 | I32: ='All Costs'!H37+'All Costs'!H38 -> 156.40425 | J32: ='All Costs'!I37+'All Costs'!I38 -> 233.23916 | K32: ='All Costs'!J37+'All Costs'!J38 -> 310.32604 | L32: ='All Costs'!K37+'All Costs'!K38 -> 395.17131 | M32: ='All Costs'!L37+'All Costs'!L38 -> 496.14327 | ... O32: ='All Costs'!N37+'All Costs'!N38 -> 729.38586 | Q32: IE
D34: Rent | F34: ='All Costs'!E51 -> 27 | G34: ='All Costs'!F51 -> 79.2 | H34: ='All Costs'!G51 -> 163.35 | I34: ='All Costs'!H51 -> 287.496 | J34: ='All Costs'!I51 -> 434.8377 | K34: ='All Costs'!J51 -> 581.10129 | L34: ='All Costs'!K51 -> 740.90414 | M34: ='All Costs'!L51 -> 930.48844 | ... O34: ='All Costs'!N51 -> 1362.2122 | Q34: IE
D36: Other Expenses | F36: ='All Costs'!E44 -> 13.5 | G36: ='All Costs'!F44 -> 16.2 | H36: ='All Costs'!G44 -> 20.25 | I36: ='All Costs'!H44 -> 25.3125 | J36: ='All Costs'!I44 -> 31.640625 | K36: ='All Costs'!J44 -> 39.550781 | L36: ='All Costs'!K44 -> 49.438477 | M36: ='All Costs'!L44 -> 61.798096 | ... O36: ='All Costs'!N44 -> 96.559525 | Q36: IE
D38: Misc Expenses | F38: ='All Costs'!E52 -> 10.8 | G38: ='All Costs'!F52 -> 31.68 | H38: ='All Costs'!G52 -> 65.34 | I38: ='All Costs'!H52 -> 114.9984 | J38: ='All Costs'!I52 -> 173.93508 | K38: ='All Costs'!J52 -> 232.44052 | L38: ='All Costs'!K52 -> 296.36166 | M38: ='All Costs'!L52 -> 372.19538 | ... O38: ='All Costs'!N52 -> 544.88488 | Q38: IE
B41: 5 | D41: EBITDA [3-4] | F41: =F25-F28 -> 184.8 | G41: =G25-G28 -> 651.78 | H41: =H25-H28 -> 1197.615 | I41: =I25-I28 -> 1893.8477 | J41: =J25-J28 -> 2792.5537 | K41: =K25-K28 -> 3632.8765 | L41: =L25-L28 -> 4609.3395 | M41: =M25-M28 -> 5800.9979 | ... O41: =O25-O28 -> 8833.596
D42: EBITDA % | F42: =F41/F$7 -> 0.29333333 | G42: =G41/G$7 -> 0.30259053 | H42: =H41/H$7 -> 0.31384041 | I42: =I41/I$7 -> 0.3187177 | J42: =J41/J$7 -> 0.32161225 | K42: =K41/K$7 -> 0.32163067 | L42: =L41/L$7 -> 0.3212098 | M42: =M41/M$7 -> 0.32063196 | ... O42: =O41/O$7 -> 0.31865105
B44: 6 | D44: Depreciation & Amortisation | F44: =DAS!F85 -> 37.351708 | G44: =DAS!H85 -> 39.852912 | H44: =DAS!J85 -> 44.969264 | I44: =DAS!L85 -> 53.665192 | J44: =DAS!N85 -> 62.148476 | K44: =DAS!P85 -> 69.252604 | L44: =DAS!R85 -> 81.864079 | M44: =DAS!T85 -> 92.253211 | N44: =DAS!V85 -> 105.32779 | O44: =DAS!X85 -> 126.01992 | Q44: DAS
B46: 7 | D46: EBIT [5-7] | F46: =F41-F44 -> 147.44829 | G46: =G41-G44 -> 611.92709 | H46: =H41-H44 -> 1152.6457 | I46: =I41-I44 -> 1840.1825 | J46: =J41-J44 -> 2730.4053 | K46: =K41-K44 -> 3563.6239 | L46: =L41-L44 -> 4527.4755 | M46: =M41-M44 -> 5708.7446 | ... O46: =O41-O44 -> 8707.576
D47: EBIT % | F47: =F46/F$7 -> 0.23404491 | G47: =G46/G$7 -> 0.28408871 | H47: =H46/H$7 -> 0.30205601 | I47: =I46/I$7 -> 0.30968632 | J47: =J46/J$7 -> 0.31445474 | K47: =K46/K$7 -> 0.31549951 | L47: =L46/L$7 -> 0.31550496 | M47: =M46/M$7 -> 0.31553295 | ... O47: =O46/O$7 -> 0.31410518
B49: 8 | D49: Finance Cost | F49: ='Debt Schedule'!C66 -> 179.66495 | G49: ='Debt Schedule'!D66 -> 173.67528 | H49: ='Debt Schedule'!E66 -> 167.01762 | I49: ='Debt Schedule'!F66 -> 159.61466 | J49: ='Debt Schedule'!G66 -> 151.37989 | K49: ='Debt Schedule'!H66 -> 142.31144 | L49: ='Debt Schedule'!I66 -> 135.77614 | M49: ='Debt Schedule'!J66 -> 132.7635 | ... O49: ='Debt Schedule'!L66 -> 125.917 | Q49: LRS
B51: 9 | D51: PBT [8-9] | F51: =F46-F49 -> -32.216659 | G51: =G46-G49 -> 438.25181 | H51: =H46-H49 -> 985.62811 | I51: =I46-I49 -> 1680.5678 | J51: =J46-J49 -> 2579.0254 | K51: =K46-K49 -> 3421.3125 | L51: =L46-L49 -> 4391.6993 | M51: =M46-M49 -> 5575.9811 | ... O51: =O46-O49 -> 8581.659
D52: PBT % | F52: =F51/F$7 -> -0.051137554 | G52: =G51/G$7 -> 0.20345952 | H52: =H51/H$7 -> 0.25828829 | I52: =I51/I$7 -> 0.2828246 | J52: =J51/J$7 -> 0.29702066 | K52: =K51/K$7 -> 0.3029002 | L52: =L51/L$7 -> 0.30604317 | M52: =M51/M$7 -> 0.30819486 | ... O52: =O51/O$7 -> 0.30956303
B54: 10 | D54: Tax Expenses | F54: =MAX(0,F51*$Q$54) -> 0 | G54: =MAX(0,G51*$Q$54) -> 131.47554 | H54: =MAX(0,SUM(F51:H51)*$Q$54) -> 417.49898 | I54: =MAX(0,SUM(F51:I51)-262.85)*$Q$54 -> 842.81432 | J54: =MAX(0,(J51-149.33)*$Q$54) -> 728.90861 | K54: =MAX(0,K51*$Q$54) -> 1026.3937 | L54: =MAX(0,L51*$Q$54) -> 1317.5098 | M54: =MAX(0,M51*$Q$54) -> 1672.7943 | N54: =MAX(0,N51*$Q$54) -> 2088.037 | O54: =MAX(0,O51*$Q$54) -> 2574.4977 | Q54: 0.3
B56: 11 | D56: PAT [10-11] | F56: =F51-F54 -> -32.216659 | G56: =G51-G54 -> 306.77627 | H56: =H51-H54 -> 568.12913 | I56: =I51-I54 -> 837.75348 | J56: =J51-J54 -> 1850.1168 | K56: =K51-K54 -> 2394.9187 | L56: =L51-L54 -> 3074.1895 | M56: =M51-M54 -> 3903.1868 | ... O56: =O51-O54 -> 6007.1613
D57: PAT % | F57: =F56/F$7 -> -0.051137554 | G57: =G56/G$7 -> 0.14242167 | H57: =H56/H$7 -> 0.1488808 | I57: =I56/I$7 -> 0.14098645 | J57: =J56/J$7 -> 0.21307386 | K57: =K56/K$7 -> 0.21203014 | L57: =L56/L$7 -> 0.21423022 | M57: =M56/M$7 -> 0.2157364 | ... O57: =O56/O$7 -> 0.21669412

Sheet CFS
D2: As Per BS | F2: =BS!F51 -> 2738.0139 | G2: =BS!G51 -> 2701.5729 | H2: =BS!H51 -> 3054.1694 | I2: =BS!I51 -> 3732.0171 | J2: =BS!J51 -> 4784.7245 | K2: =BS!K51 -> 6797.4835 | L2: =BS!L51 -> 9440.7406 | M2: =BS!M51 -> 12881.013 | ... O2: =BS!O51 -> 22614.27
D3: Check | F3: =F2-F58 -> 0 | G3: =G2-G58 -> 0 | H3: =H2-H58 -> 0 | I3: =I2-I58 -> 0 | J3: =J2-J58 -> 0 | K3: =K2-K58 -> 0 | L3: =L2-L58 -> 0 | M3: =M2-M58 -> 0 | ... O3: =O2-O58 -> 0
B5: Cash Flow Statement
O6: =Do -> (₹ in Lakhs)
B8: SI No. | D8: Particulars | F8: =BS!F7 -> 25-26 | G8: =BS!G7 -> 26-27 | H8: =BS!H7 -> 27-28 | I8: =BS!I7 -> 28-29 | J8: =BS!J7 -> 29-30 | K8: =BS!K7 -> 30-31 | L8: =BS!L7 -> 31-32 | M8: =BS!M7 -> 32-33 | ... O8: =BS!O7 -> 34-35
B10: A. Operating Activities
B12: 1 | D12: Net Profit After Tax | F12: ='P&L'!F56 -> -32.216659 | G12: ='P&L'!G56 -> 306.77627 | H12: ='P&L'!H56 -> 568.12913 | I12: ='P&L'!I56 -> 837.75348 | J12: ='P&L'!J56 -> 1850.1168 | K12: ='P&L'!K56 -> 2394.9187 | L12: ='P&L'!L56 -> 3074.1895 | M12: ='P&L'!M56 -> 3903.1868 | ... O12: ='P&L'!O56 -> 6007.1613
B14: 2 | D14: Adjustments to net profits
B16: 2.1 | D16: Depreciation & Amortisation | F16: ='P&L'!F44 -> 37.351708 | G16: ='P&L'!G44 -> 39.852912 | H16: ='P&L'!H44 -> 44.969264 | I16: ='P&L'!I44 -> 53.665192 | J16: ='P&L'!J44 -> 62.148476 | K16: ='P&L'!K44 -> 69.252604 | L16: ='P&L'!L44 -> 81.864079 | M16: ='P&L'!M44 -> 92.253211 | ... O16: ='P&L'!O44 -> 126.01992
B18: 2.2 | D18: Finance Cost | F18: ='P&L'!F49 -> 179.66495 | G18: ='P&L'!G49 -> 173.67528 | H18: ='P&L'!H49 -> 167.01762 | I18: ='P&L'!I49 -> 159.61466 | J18: ='P&L'!J49 -> 151.37989 | K18: ='P&L'!K49 -> 142.31144 | L18: ='P&L'!L49 -> 135.77614 | M18: ='P&L'!M49 -> 132.7635 | ... O18: ='P&L'!O49 -> 125.917
B20: 2.3 | D20: Movement in Working Capital | F20: =BS!F79+BS!F81+BS!F83 -> -68.307524 | G20: =BS!G79+BS!G81+BS!G83 -> -203.55863 | H20: =BS!H79+BS!H81+BS!H83 -> -206.57445 | I20: =BS!I79+BS!I81+BS!I83 -> -257.53465 | J20: =BS!J79+BS!J81+BS!J83 -> -337.33456 | K20: =BS!K79+BS!K81+BS!K83 -> -319.86171 | L20: =BS!L79+BS!L81+BS!L83 -> -379.14755 | M20: =BS!M79+BS!M81+BS!M83 -> -467.46615 | ... O20: =BS!O79+BS!O81+BS!O83 -> -670.2602
B22: 2.4 | D22: Tax Provision | F22: =-BS!F29 -> 0 | G22: =-BS!F29+BS!G29 -> 131.47554 | H22: =-BS!G29+BS!H29 -> 286.02344 | I22: =-BS!H29+BS!I29 -> 425.31534 | J22: =-BS!I29+BS!J29 -> -113.90571 | K22: =-BS!J29+BS!K29 -> 297.48514 | L22: =-BS!K29+BS!L29 -> 291.11605 | M22: =-BS!L29+BS!M29 -> 355.28454 | N22: =-BS!M29+BS!N29 -> 415.24268 | O22: =-BS!N29+BS!O29 -> 486.46069
D24: Cash flows from Operating Activities | F24: =SUM(F12:F22) -> 116.49248 | G24: =SUM(G12:G22) -> 448.22137 | H24: =SUM(H12:H22) -> 859.565 | I24: =SUM(I12:I22) -> 1218.814 | J24: =SUM(J12:J22) -> 1612.4049 | K24: =SUM(K12:K22) -> 2584.1062 | L24: =SUM(L12:L22) -> 3203.7982 | M24: =SUM(M12:M22) -> 4016.0219 | ... O24: =SUM(O12:O22) -> 6075.2987
B28: B. Financing Activities
B30: 3 | D30: Promoters contribution | F30: =Config!C15 -> 300
B32: 4 | D32: Term loans & Borrowings | F32: ='Debt Schedule'!C73 -> 2774.16 | G32: ='Debt Schedule'!D73 -> 0 | H32: ='Debt Schedule'!E73 -> 0 | I32: ='Debt Schedule'!F73 -> 0 | J32: ='Debt Schedule'!G73 -> 0 | K32: ='Debt Schedule'!H73 -> 0 | L32: ='Debt Schedule'!I73 -> 0 | M32: ='Debt Schedule'!J73 -> 0 | ... O32: ='Debt Schedule'!L73 -> 0
B34: 5 | D34: Loan repayment | F34: =-('Debt Schedule'!C65) -> -230.34335 | G34: =-('Debt Schedule'!D65) -> -246.98709 | H34: =-('Debt Schedule'!E65) -> -264.95088 | I34: =-('Debt Schedule'!F65) -> -284.3516 | J34: =-('Debt Schedule'!G65) -> -305.31765 | K34: =-('Debt Schedule'!H65) -> -326.03574 | L34: =-('Debt Schedule'!I65) -> -284.76501 | M34: =-('Debt Schedule'!J65) -> -302.98637 | ... O34: =-('Debt Schedule'!L65) -> -343.08801
B36: 6 | D36: Interest Repayment | F36: =-F18 -> -179.66495 | G36: =-G18 -> -173.67528 | H36: =-H18 -> -167.01762 | I36: =-I18 -> -159.61466 | J36: =-J18 -> -151.37989 | K36: =-K18 -> -142.31144 | L36: =-L18 -> -135.77614 | M36: =-M18 -> -132.7635 | ... O36: =-O18 -> -125.917
D38: Cash flows from Financing Activities | F38: =SUM(F30:F36) -> 2664.1517 | G38: =SUM(G30:G36) -> -420.66236 | H38: =SUM(H30:H36) -> -431.9685 | I38: =SUM(I30:I36) -> -443.96626 | J38: =SUM(J30:J36) -> -456.69755 | K38: =SUM(K30:K36) -> -468.34717 | L38: =SUM(L30:L36) -> -420.54115 | M38: =SUM(M30:M36) -> -435.74987 | ... O38: =SUM(O30:O36) -> -469.00501
B42: C. Investing Activities
B44: 7 | D44: Acquisition of fixed assets | F44: =-DAS!F83 -> -43 | G44: =-DAS!H83 -> -64 | H44: =-DAS!J83 -> -75 | I44: =-DAS!L83 -> -97 | J44: =-DAS!N83 -> -103 | K44: =-DAS!P83 -> -103 | L44: =-DAS!R83 -> -140 | M44: =-DAS!T83 -> -140 | N44: =-DAS!V83 -> -165 | O44: =-DAS!X83 -> -220
B46: 8 | D46: Disposal of fixed assets | F46: 0 | G46: 0 | H46: 0 | I46: 0 | J46: 0 | K46: 0 | L46: 0 | M46: 0 | N46: 0 | O46: 0
B48: 9 | D48: Movement in other non-current assets | F48: 0 | G48: 0 | H48: 0 | I48: 0 | J48: 0 | K48: 0 | L48: 0 | M48: 0 | N48: 0 | O48: 0
D50: Cash flows from Investing Activities | F50: =SUM(F44:F48) -> -43 | G50: =SUM(G44:G48) -> -64 | H50: =SUM(H44:H48) -> -75 | I50: =SUM(I44:I48) -> -97 | J50: =SUM(J44:J48) -> -103 | K50: =SUM(K44:K48) -> -103 | L50: =SUM(L44:L48) -> -140 | M50: =SUM(M44:M48) -> -140 | ... O50: =SUM(O44:O48) -> -220
D54: Net cash flows from all activities | F54: =F24+F38+F50 -> 2737.6442 | G54: =G24+G38+G50 -> -36.440992 | H54: =H24+H38+H50 -> 352.5965 | I54: =I24+I38+I50 -> 677.84776 | J54: =J24+J38+J50 -> 1052.7073 | K54: =K24+K38+K50 -> 2012.759 | L54: =L24+L38+L50 -> 2643.2571 | M54: =M24+M38+M50 -> 3440.272 | ... O54: =O24+O38+O50 -> 5386.2937
D56: Opening cash balance | F56: =Config!C8 -> 0.3696979 | G56: =F58 -> 2738.0139 | H56: =G58 -> 2701.5729 | I56: =H58 -> 3054.1694 | J56: =I58 -> 3732.0171 | K56: =J58 -> 4784.7245 | L56: =K58 -> 6797.4835 | M56: =L58 -> 9440.7406 | N56: =M58 -> 12881.013 | O56: =N58 -> 17227.976
D58: Closing cash balance | F58: =F56+F54 -> 2738.0139 | G58: =G56+G54 -> 2701.5729 | H58: =H56+H54 -> 3054.1694 | I58: =I56+I54 -> 3732.0171 | J58: =J56+J54 -> 4784.7245 | K58: =K56+K54 -> 6797.4835 | L58: =L56+L54 -> 9440.7406 | M58: =M56+M54 -> 12881.013 | ... O58: =O56+O54 -> 22614.27

Sheet Revenue generation breakup
B2: Summary of Revenue
B5: Revenue Generation Breakup ( Lakhs) | J5: Revenue, Expenses and Profit _Generation Breakup ( Lakhs)
B6: SL.No | C6: Year | D6: Corporate Sales | E6: Millet Cafeterias | F6: Retail Market Sales | G6: Exports | H6: Total Revenue | J6: SL.No | K6: Year | L6: Corporate Snacks- Revenue | M6: Expenses | N6: Gross Profit | O6: Gross Profit% | P6: Millet Cafeterias-Revenue | Q6: Expenses | R6: Gross Profit | S6: Gross Profit% | T6: Retail Market -Revenue | U6: Expenses | V6: Gross Profit | W6: Gross Profit% | X6: Exports -Revenue | Y6: Expenses | Z6: Gross Profit | AA6: Gross Profit% | AB6: Total Revenue | AC6: Total Expenses | AD6: Total Gross Profit
B7: 1 | C7: 2025 | D7: ='Revenue generation breakup'!I23 -> 135 | E7: ='Revenue generation breakup'!F50 -> 270 | F7: ='Revenue generation breakup'!E65 -> 75 | G7: ='Revenue generation breakup'!E81 -> 150 | H7: =SUM(D7:G7) -> 630 | J7: 1 | K7: 2025 | L7: =D7 -> 135 | M7: =L7*0.75 -> 101.25 | N7: =L7-M7 -> 33.75 | O7: =(L7-M7)/L7 -> 0.25 | P7: =E7 -> 270 | Q7: =P7*60% -> 162 | R7: =P7-Q7 -> 108 | S7: =(P7-Q7)/P7 -> 0.4 | T7: =F7 -> 75 | U7: =T7*78% -> 58.5 | V7: =T7-U7 -> 16.5 | W7: =(T7-U7)/T7 -> 0.22 | X7: =G7 -> 150 | Y7: =X7*65% -> 97.5 | Z7: =X7-Y7 -> 52.5 | AA7: =(X7-Y7)/X7 -> 0.35 | AB7: =L7+P7+T7+X7 -> 630 | AC7: =M7+Q7+U7+Y7 -> 419.25 | AD7: =N7+R7+V7+Z7 -> 210.75
B8: 2 | C8: 2026 | D8: ='Revenue generation breakup'!I24 -> 162 | E8: ='Revenue generation breakup'!F51 -> 792 | F8: ='Revenue generation breakup'!E66 -> 600 | G8: ='Revenue generation breakup'!E82 -> 600 | H8: =SUM(D8:G8) -> 2154 | J8: 2 | K8: 2026 | L8: =D8 -> 162 | M8: =L8*0.75 -> 121.5 | N8: =L8-M8 -> 40.5 | O8: =(L8-M8)/L8 -> 0.25 | P8: =E8 -> 792 | Q8: =P8*60% -> 475.2 | R8: =P8-Q8 -> 316.8 | S8: =(P8-Q8)/P8 -> 0.4 | T8: =F8 -> 600 | U8: =T8*78% -> 468 | V8: =T8-U8 -> 132 | W8: =(T8-U8)/T8 -> 0.22 | X8: =G8 -> 600 | Y8: =X8*65% -> 390 | Z8: =X8-Y8 -> 210 | AA8: =(X8-Y8)/X8 -> 0.35 | AB8: =L8+P8+T8+X8 -> 2154 | AC8: =M8+Q8+U8+Y8 -> 1454.7 | AD8: =N8+R8+V8+Z8 -> 699.3
B9: 3 | C9: 2027 | D9: ='Revenue generation breakup'!I25 -> 202.5 | E9: ='Revenue generation breakup'!F52 -> 1633.5 | F9: ='Revenue generation breakup'!E67 -> 1200 | G9: ='Revenue generation breakup'!E83 -> 780 | H9: =SUM(D9:G9) -> 3816 | J9: 3 | K9: 2027 | L9: =D9 -> 202.5 | M9: =L9*0.75 -> 151.875 | N9: =L9-M9 -> 50.625 | O9: =(L9-M9)/L9 -> 0.25 | P9: =E9 -> 1633.5 | Q9: =P9*60% -> 980.1 | R9: =P9-Q9 -> 653.4 | S9: =(P9-Q9)/P9 -> 0.4 | T9: =F9 -> 1200 | U9: =T9*78% -> 936 | V9: =T9-U9 -> 264 | W9: =(T9-U9)/T9 -> 0.22 | X9: =G9 -> 780 | Y9: =X9*65% -> 507 | Z9: =X9-Y9 -> 273 | AA9: =(X9-Y9)/X9 -> 0.35 | AB9: =L9+P9+T9+X9 -> 3816 | AC9: =M9+Q9+U9+Y9 -> 2574.975 | AD9: =N9+R9+V9+Z9 -> 1241.025
B10: 4 | C10: 2028 | D10: ='Revenue generation breakup'!I26 -> 253.125 | E10: ='Revenue generation breakup'!F53 -> 2874.96 | F10: ='Revenue generation breakup'!E68 -> 1800 | G10: ='Revenue generation breakup'!E84 -> 1014 | H10: =SUM(D10:G10) -> 5942.085 | J10: 4 | K10: 2028 | L10: =D10 -> 253.125 | M10: =L10*0.75 -> 189.84375 | N10: =L10-M10 -> 63.28125 | O10: =(L10-M10)/L10 -> 0.25 | P10: =E10 -> 2874.96 | Q10: =P10*60% -> 1724.976 | R10: =P10-Q10 -> 1149.984 | S10: =(P10-Q10)/P10 -> 0.4 | T10: =F10 -> 1800 | U10: =T10*78% -> 1404 | V10: =T10-U10 -> 396 | W10: =(T10-U10)/T10 -> 0.22 | X10: =G10 -> 1014 | Y10: =X10*65% -> 659.1 | Z10: =X10-Y10 -> 354.9 | AA10: =(X10-Y10)/X10 -> 0.35 | AB10: =L10+P10+T10+X10 -> 5942.085 | AC10: =M10+Q10+U10+Y10 -> 3977.9198 | AD10: =N10+R10+V10+Z10 -> 1964.1653
B11: 5 | C11: 2029 | D11: ='Revenue generation breakup'!I27 -> 316.40625 | E11: ='Revenue generation breakup'!F54 -> 4348.377 | F11: ='Revenue generation breakup'!E69 -> 2700 | G11: ='Revenue generation breakup'!E85 -> 1318.2 | H11: =SUM(D11:G11) -> 8682.9833 | J11: 5 | K11: 2029 | L11: =D11 -> 316.40625 | M11: =L11*0.75 -> 237.30469 | N11: =L11-M11 -> 79.101562 | O11: =(L11-M11)/L11 -> 0.25 | P11: =E11 -> 4348.377 | Q11: =P11*60% -> 2609.0262 | R11: =P11-Q11 -> 1739.3508 | S11: =(P11-Q11)/P11 -> 0.4 | T11: =F11 -> 2700 | U11: =T11*78% -> 2106 | V11: =T11-U11 -> 594 | W11: =(T11-U11)/T11 -> 0.22 | X11: =G11 -> 1318.2 | Y11: =X11*65% -> 856.83 | Z11: =X11-Y11 -> 461.37 | AA11: =(X11-Y11)/X11 -> 0.35 | AB11: =L11+P11+T11+X11 -> 8682.9833 | AC11: =M11+Q11+U11+Y11 -> 5809.1609 | AD11: =N11+R11+V11+Z11 -> 2873.8224
B12: 6 | C12: 2030 | D12: ='Revenue generation breakup'!I28 -> 395.50781 | E12: ='Revenue generation breakup'!F55 -> 5811.0129 | F12: ='Revenue generation breakup'!E70 -> 3375 | G12: ='Revenue generation breakup'!E86 -> 1713.66 | H12: =SUM(D12:G12) -> 11295.181 | J12: 6 | K12: 2030 | L12: =D12 -> 395.50781 | M12: =L12*0.75 -> 296.63086 | N12: =L12-M12 -> 98.876953 | O12: =(L12-M12)/L12 -> 0.25 | P12: =E12 -> 5811.0129 | Q12: =P12*60% -> 3486.6077 | R12: =P12-Q12 -> 2324.4052 | S12: =(P12-Q12)/P12 -> 0.4 | T12: =F12 -> 3375 | U12: =T12*78% -> 2632.5 | V12: =T12-U12 -> 742.5 | W12: =(T12-U12)/T12 -> 0.22 | X12: =G12 -> 1713.66 | Y12: =X12*65% -> 1113.879 | Z12: =X12-Y12 -> 599.781 | AA12: =(X12-Y12)/X12 -> 0.35 | AB12: =L12+P12+T12+X12 -> 11295.181 | AC12: =M12+Q12+U12+Y12 -> 7529.6176 | AD12: =N12+R12+V12+Z12 -> 3765.5631
B13: 7 | C13: 2031 | D13: ='Revenue generation breakup'!I29 -> 494.38477 | E13: ='Revenue generation breakup'!F56 -> 7409.0414 | F13: ='Revenue generation breakup'!E71 -> 4218.75 | G13: ='Revenue generation breakup'!E87 -> 2227.758 | H13: =SUM(D13:G13) -> 14349.934 | J13: 7 | K13: 2031 | L13: =D13 -> 494.38477 | M13: =L13*0.75 -> 370.78857 | N13: =L13-M13 -> 123.59619 | O13: =(L13-M13)/L13 -> 0.25 | P13: =E13 -> 7409.0414 | Q13: =P13*60% -> 4445.4249 | R13: =P13-Q13 -> 2963.6166 | S13: =(P13-Q13)/P13 -> 0.4 | T13: =F13 -> 4218.75 | U13: =T13*78% -> 3290.625 | V13: =T13-U13 -> 928.125 | W13: =(T13-U13)/T13 -> 0.22 | X13: =G13 -> 2227.758 | Y13: =X13*65% -> 1448.0427 | Z13: =X13-Y13 -> 779.7153 | AA13: =(X13-Y13)/X13 -> 0.35 | AB13: =L13+P13+T13+X13 -> 14349.934 | AC13: =M13+Q13+U13+Y13 -> 9554.8811 | AD13: =N13+R13+V13+Z13 -> 4795.0531
B14: 8 | C14: 2032 | D14: ='Revenue generation breakup'!I30 -> 617.98096 | E14: ='Revenue generation breakup'!F57 -> 9304.8844 | F14: ='Revenue generation breakup'!E72 -> 5273.4375 | G14: ='Revenue generation breakup'!E88 -> 2896.0854 | H14: =SUM(D14:G14) -> 18092.388 | J14: 8 | K14: 2032 | L14: =D14 -> 617.98096 | M14: =L14*0.75 -> 463.48572 | N14: =L14-M14 -> 154.49524 | O14: =(L14-M14)/L14 -> 0.25 | P14: =E14 -> 9304.8844 | Q14: =P14*60% -> 5582.9306 | R14: =P14-Q14 -> 3721.9538 | S14: =(P14-Q14)/P14 -> 0.4 | T14: =F14 -> 5273.4375 | U14: =T14*78% -> 4113.2812 | V14: =T14-U14 -> 1160.1562 | W14: =(T14-U14)/T14 -> 0.22 | X14: =G14 -> 2896.0854 | Y14: =X14*65% -> 1882.4555 | Z14: =X14-Y14 -> 1013.6299 | AA14: =(X14-Y14)/X14 -> 0.35 | AB14: =L14+P14+T14+X14 -> 18092.388 | AC14: =M14+Q14+U14+Y14 -> 12042.153 | AD14: =N14+R14+V14+Z14 -> 6050.2351
B15: 9 | C15: 2033 | D15: ='Revenue generation breakup'!I31 -> 772.4762 | E15: ='Revenue generation breakup'!F58 -> 11371.789 | F15: ='Revenue generation breakup'!E73 -> 6591.7969 | G15: ='Revenue generation breakup'!E89 -> 3764.911 | H15: =SUM(D15:G15) -> 22500.973 | J15: 9 | K15: 2033 | L15: =D15 -> 772.4762 | M15: =L15*0.75 -> 579.35715 | N15: =L15-M15 -> 193.11905 | O15: =(L15-M15)/L15 -> 0.25 | P15: =E15 -> 11371.789 | Q15: =P15*60% -> 6823.0734 | R15: =P15-Q15 -> 4548.7156 | S15: =(P15-Q15)/P15 -> 0.4 | T15: =F15 -> 6591.7969 | U15: =T15*78% -> 5141.6016 | V15: =T15-U15 -> 1450.1953 | W15: =(T15-U15)/T15 -> 0.22 | X15: =G15 -> 3764.911 | Y15: =X15*65% -> 2447.1922 | Z15: =X15-Y15 -> 1317.7189 | AA15: =(X15-Y15)/X15 -> 0.35 | AB15: =L15+P15+T15+X15 -> 22500.973 | AC15: =M15+Q15+U15+Y15 -> 14991.224 | AD15: =N15+R15+V15+Z15 -> 7509.7488
B16: 10 | C16: 2034 | D16: ='Revenue generation breakup'!I32 -> 965.59525 | E16: ='Revenue generation breakup'!F59 -> 13622.122 | F16: ='Revenue generation breakup'!E74 -> 8239.7461 | G16: ='Revenue generation breakup'!E90 -> 4894.3843 | H16: =SUM(D16:G16) -> 27721.848 | J16: 10 | K16: 2034 | L16: =D16 -> 965.59525 | M16: =L16*0.75 -> 724.19643 | N16: =L16-M16 -> 241.39881 | O16: =(L16-M16)/L16 -> 0.25 | P16: =E16 -> 13622.122 | Q16: =P16*60% -> 8173.2732 | R16: =P16-Q16 -> 5448.8488 | S16: =(P16-Q16)/P16 -> 0.4 | T16: =F16 -> 8239.7461 | U16: =T16*78% -> 6427.002 | V16: =T16-U16 -> 1812.7441 | W16: =(T16-U16)/T16 -> 0.22 | X16: =G16 -> 4894.3843 | Y16: =X16*65% -> 3181.3498 | Z16: =X16-Y16 -> 1713.0345 | AA16: =(X16-Y16)/X16 -> 0.35 | AB16: =L16+P16+T16+X16 -> 27721.848 | AC16: =M16+Q16+U16+Y16 -> 18505.821 | AD16: =N16+R16+V16+Z16 -> 9216.0263
D17: =SUM(D7:D16) -> 4314.9762 | E17: =SUM(E7:E16) -> 57437.687 | F17: =SUM(F7:F16) -> 34073.73 | G17: =SUM(G7:G16) -> 19358.999 | H17: =SUM(H7:H16) -> 115185.39 | L17: =SUM(L7:L16) -> 4314.9762 | P17: =SUM(P7:P16) -> 57437.687 | T17: =SUM(T7:T16) -> 34073.73 | X17: =SUM(X7:X16) -> 19358.999 | AB17: =SUM(AB7:AB16) -> 115185.39 | AC17: =SUM(AC7:AC16) -> 76859.703 | AD17: =SUM(AD7:AD16) -> 38325.689
B19: Corporate Sales
K21: Operational Cost Breakup
B22: SL.No | C22: Year | D22: Average Clients Acquizition per month 4 Clients ( with growth of 25% year on year) | E22: Client Retention Ration 60% | F22: Average Product sales price to Client (INR) with increase of price 5% year on year | G22: Average Product Sales per Client 75000 per Month | H22: Average Product Sales per Client Annum | I22: Revenue in Lakhs | K22: SL.No | L22: Operation Head | M22: Expenses ratio on total revenue generation | N22: Remarks
B23: 1 | C23: 2025 | D23: 25 | E23: =D23*60% -> 15 | F23: 35 | G23: =75000*E23 -> 1125000 | H23: =G23*12 -> 13500000 | I23: =H23/100000 -> 135 | K23: 1 | L23: RM &Packing cost with Packing | M23: 0.35 | N23: Fixed, incraeses 5% year on year
B24: 2 | C24: 2026 | D24: =24*125% -> 30 | E24: =D24*60% -> 18 | F24: =F23*105% -> 36.75 | G24: =75000*E24 -> 1350000 | H24: =G24*12 -> 16200000 | I24: =H24/100000 -> 162 | K24: 2 | L24: Employee salaries | M24: 0.25 | N24: Every Employee handles 5 clients
B25: 3 | C25: 2027 | D25: =D24*125% -> 37.5 | E25: =D25*60% -> 22.5 | F25: =F24*105% -> 38.5875 | G25: =75000*E25 -> 1687500 | H25: =G25*12 -> 20250000 | I25: =H25/100000 -> 202.5 | K25: 3 | L25: Promotional expenses | M25: 0.05 | N25: Fixed, increase 5% year on year
B26: 4 | C26: 2028 | D26: =D25*125% -> 46.875 | E26: =D26*60% -> 28.125 | F26: =F25*105% -> 40.516875 | G26: =75000*E26 -> 2109375 | H26: =G26*12 -> 25312500 | I26: =H26/100000 -> 253.125 | K26: 4 | L26: Other expenses | M26: 0.1 | N26: Fixed, increase 5% year on year
B27: 5 | C27: 2029 | D27: =D26*125% -> 58.59375 | E27: =D27*60% -> 35.15625 | F27: =F26*105% -> 42.542719 | G27: =75000*E27 -> 2636718.8 | H27: =G27*12 -> 31640625 | I27: =H27/100000 -> 316.40625 | L27: Total Expenses on product price | M27: =SUM(M23:M26) -> 0.75
B28: 6 | C28: 2030 | D28: =D27*125% -> 73.242188 | E28: =D28*60% -> 43.945312 | F28: =F27*105% -> 44.669855 | G28: =75000*E28 -> 3295898.4 | H28: =G28*12 -> 39550781 | I28: =H28/100000 -> 395.50781
B29: 7 | C29: 2031 | D29: =D28*125% -> 91.552734 | E29: =D29*60% -> 54.931641 | F29: =F28*105% -> 46.903347 | G29: =75000*E29 -> 4119873 | H29: =G29*12 -> 49438477 | I29: =H29/100000 -> 494.38477
B30: 8 | C30: 2032 | D30: =D29*125% -> 114.44092 | E30: =D30*60% -> 68.664551 | F30: =F29*105% -> 49.248515 | G30: =75000*E30 -> 5149841.3 | H30: =G30*12 -> 61798096 | I30: =H30/100000 -> 617.98096
B31: 9 | C31: 2033 | D31: =D30*125% -> 143.05115 | E31: =D31*60% -> 85.830688 | F31: =F30*105% -> 51.710941 | G31: =75000*E31 -> 6437301.6 | H31: =G31*12 -> 77247620 | I31: =H31/100000 -> 772.4762
B32: 10 | C32: 2034 | D32: =D31*125% -> 178.81393 | E32: =D32*60% -> 107.28836 | F32: =F31*105% -> 54.296488 | G32: =75000*E32 -> 8046627 | H32: =G32*12 -> 96559525 | I32: =H32/100000 -> 965.59525
C33: Total | D33: =SUM(D23:D32) -> 799.06967 | E33: =SUM(E23:E32) -> 479.4418 | I33: =SUM(I23:I32) -> 4314.9762
B35: Millet Cafeteria
B37: SL.No | C37: Reveune genertaion from Millet Cafeteria | D37: Breakup (in Lakhs/Annum) | E37: Remarks | G37: Breakup for Revenue Generation fo 125 Lakhs
B38: 1 | C38: Revenue generation per cafeteria | D38: 90 | E38: 10% growth in revenue genertaion year on year for first 5 years and later 5 % growth year on year | G38: Cost of Items | H38: INR | I38: No of Plates Sales/day | J38: No. of Hours Operations | K38: Per hour Plates sales target | L38: Revenue Generation/day | M38: No.of working days in Month 25 days | N38: Revenue generation/Annum | O38: Revenue generation with consideration of 65% achievement of target | P38: Revenue in lakhs
B39: 2 | C39: Expenses Heads | G39: Average Breakfast Cost for Morning | H39: 75 | I39: 300 | J39: 5 | K39: =I39/J39 -> 60 | L39: =I39*H39 -> 22500 | M39: =L39*25 -> 562500 | N39: =M39*12 -> 6750000 | O39: =N39*65% -> 4387500 | P39: =O39/100000 -> 43.875
B40: 2.1 | C40: RM Cost | D40: =D38*22% -> 19.8 | E40: 8% increase of RM cost year on Year | G40: Average Meals/Thali Cost for Afternoon | H40: 110 | I40: 270 | J40: 4 | K40: =I40/J40 -> 67.5 | L40: =I40*H40 -> 29700 | M40: =L40*25 -> 742500 | N40: =M40*12 -> 8910000 | O40: =N40*65% -> 5791500 | P40: =O40/100000 -> 57.915
B41: 2.2 | C41: Cook and Staff Salaries | D41: =D38*25% -> 22.5 | E41: 10% increase of RM cost year on Year | G41: Average snacks cost for Evening | H41: 60 | I41: 200 | J41: 4 | K41: =I41/J41 -> 50 | L41: =I41*H41 -> 12000 | M41: =L41*25 -> 300000 | N41: =M41*12 -> 3600000 | O41: =N41*65% -> 2340000 | P41: =O41/100000 -> 23.4
B42: 2.3 | C42: Cafeteria Rent | D42: =D38*10% -> 9 | E42: 7% increase of RM cost year on Year | G42: Total | I42: =SUM(I39:I41) -> 770 | J42: =SUM(J39:J41) -> 13 | K42: =SUM(K39:K41) -> 177.5 | L42: =SUM(L39:L41) -> 64200 | M42: =SUM(M39:M41) -> 1605000 | N42: =SUM(N39:N41) -> 19260000 | O42: =SUM(O39:O41) -> 12519000 | P42: =O42/100000 -> 125.19
B43: 2.4 | C43: Miscelanous Expenses | D43: =D38*4% -> 3.6 | E43: 5% increase of RM cost year on Year
B44: 2.5 | C44: Promotional Expenses | D44: =D38*5% -> 4.5 | E44: 10% increase of RM cost year on Year
B45: 3 | C45: Total Expenses | D45: =SUM(D40:D44) -> 59.4
B46: 4 | C46: Gross Profit | D46: =D38-D45 -> 30.6
B47: 4.1 | C47: Gross Profit % | D47: =D46/D38 -> 0.34
B49: SL.No | C49: Year | D49: No. of Cafeterias Planning to Launch | E49: Total No. of Cafterias year on Year | F49: Revenue Generation in Lakhs | G49: Fixed Assets cost | I49: SL.No | J49: Year | K49: Revenue from each cafeteria with 15% increase year on year ( Lakhs)
B50: 1 | C50: 2025 | D50: 3 | E50: 3 | F50: =K50*E50 -> 270 | G50: =D50*8 -> 24 | I50: 1 | J50: 2025 | K50: =90 -> 90
B51: 2 | C51: 2026 | D51: 5 | E51: =SUM(D50:D51) -> 8 | F51: =K51*E51 -> 792 | G51: =D51*8 -> 40 | I51: 2 | J51: 2026 | K51: =K50*1.1 -> 99
B52: 3 | C52: 2027 | D52: 7 | E52: =SUM(D50:D52) -> 15 | F52: =K52*E52 -> 1633.5 | G52: =D52*8 -> 56 | I52: 3 | J52: 2027 | K52: =K51*1.1 -> 108.9
B53: 4 | C53: 2028 | D53: 9 | E53: =SUM(D50:D53) -> 24 | F53: =K53*E53 -> 2874.96 | G53: =D53*8 -> 72 | I53: 4 | J53: 2028 | K53: =K52*1.1 -> 119.79
B54: 5 | C54: 2029 | D54: 9 | E54: =SUM(D50:D54) -> 33 | F54: =K54*E54 -> 4348.377 | G54: =D54*8 -> 72 | I54: 5 | J54: 2029 | K54: =K53*1.1 -> 131.769
B55: 6 | C55: 2030 | D55: 9 | E55: =SUM(D50:D55) -> 42 | F55: =K55*E55 -> 5811.0129 | G55: =D55*8 -> 72 | I55: 6 | J55: 2030 | K55: =K54*1.05 -> 138.35745
B56: 7 | C56: 2031 | D56: 9 | E56: =SUM(D50:D56) -> 51 | F56: =K56*E56 -> 7409.0414 | G56: =D56*8 -> 72 | I56: 7 | J56: 2031 | K56: =K55*1.05 -> 145.27532
B57: 8 | C57: 2032 | D57: 10 | E57: =SUM(D50:D57) -> 61 | F57: =K57*E57 -> 9304.8844 | G57: =D57*8 -> 80 | I57: 8 | J57: 2032 | K57: =K56*1.05 -> 152.53909
B58: 9 | C58: 2033 | D58: 10 | E58: =SUM(D50:D58) -> 71 | F58: =K58*E58 -> 11371.789 | G58: =D58*8 -> 80 | I58: 9 | J58: 2033 | K58: =K57*1.05 -> 160.16604
B59: 10 | C59: 2034 | D59: 10 | E59: =SUM(D50:D59) -> 81 | F59: =K59*E59 -> 13622.122 | G59: =D59*8 -> 80 | I59: 10 | J59: 2034 | K59: =K58*1.05 -> 168.17435
B60: ` | C60: Total | D60: =SUM(D50:D59) -> 81 | E60: =D60 -> 81 | F60: =SUM(F50:F59) -> 57437.687 | K60: =SUM(K50:K59) -> 1313.9712
B62: Retail Market
B64: SL.No | C64: Year | D64: Sales Projection Per Month | E64: Sales Projection Per Annum | F64: Remarks
B65: 1 | C65: 2025 | D65: 25 | E65: =D65*12/4 -> 75 | F65: 25% growth year on year
B66: 2 | C66: 2026 | D66: =D65*2 -> 50 | E66: =D66*12 -> 600 | F66: 25% growth year on year
B67: 3 | C67: 2027 | D67: =D66*2 -> 100 | E67: =D67*12 -> 1200 | F67: 25% growth year on year
B68: 4 | C68: 2028 | D68: =D67*1.5 -> 150 | E68: =D68*12 -> 1800 | F68: 25% growth year on year
B69: 5 | C69: 2029 | D69: =D68*1.5 -> 225 | E69: =D69*12 -> 2700 | F69: 25% growth year on year
B70: 6 | C70: 2030 | D70: =D69*1.25 -> 281.25 | E70: =D70*12 -> 3375 | F70: 25% growth year on year
B71: 7 | C71: 2031 | D71: =D70*1.25 -> 351.5625 | E71: =D71*12 -> 4218.75 | F71: 15% growth year on year
B72: 8 | C72: 2032 | D72: =D71*1.25 -> 439.45312 | E72: =D72*12 -> 5273.4375 | F72: 15% growth year on year
B73: 9 | C73: 2033 | D73: =D72*1.25 -> 549.31641 | E73: =D73*12 -> 6591.7969 | F73: 15% growth year on year
B74: 10 | C74: 2034 | D74: =D73*1.25 -> 686.64551 | E74: =D74*12 -> 8239.7461 | F74: 15% growth year on year
C75: TOTAL | E75: =SUM(E65:E74) -> 34073.73
B77: Export
B79: Revenue Generation from Contarct Mfg & Exports
B80: SL.No | C80: Year | D80: Revenue generation from Export in INR | E80: Revenue in Lakhs | G80: SL.No | H80: Year | I80: Average Product Price per Kg for Exports | J80: No .Tons export/Annum to reach target | K80: Per Month Export in Ton
B81: 1 | C81: 2025 | D81: 15000000 | E81: =D81/100000 -> 150 | G81: 1 | H81: 2025 | I81: 1200 | J81: =D81/I81/1000 -> 12.5 | K81: =J81/3 -> 4.1666667
B82: 2 | C82: 2026 | D82: 60000000 | E82: =D82/100000 -> 600 | G82: 2 | H82: 2026 | I82: 1200 | J82: =D82/I82/1000 -> 50 | K82: =J82/12 -> 4.1666667
B83: 3 | C83: 2027 | D83: =D82*130% -> 78000000 | E83: =D83/100000 -> 780 | G83: 3 | H83: 2027 | I83: 1200 | J83: =D83/I83/1000 -> 65 | K83: =J83/12 -> 5.4166667
B84: 4 | C84: 2028 | D84: =D83*130% -> 101400000 | E84: =D84/100000 -> 1014 | G84: 4 | H84: 2028 | I84: 1200 | J84: =D84/I84/1000 -> 84.5 | K84: =J84/12 -> 7.0416667
B85: 5 | C85: 2029 | D85: =D84*130% -> 131820000 | E85: =D85/100000 -> 1318.2 | G85: 5 | H85: 2029 | I85: 1200 | J85: =D85/I85/1000 -> 109.85 | K85: =J85/12 -> 9.1541667
B86: 6 | C86: 2030 | D86: =D85*130% -> 171366000 | E86: =D86/100000 -> 1713.66 | G86: 6 | H86: 2030 | I86: 1200 | J86: =D86/I86/1000 -> 142.805 | K86: =J86/12 -> 11.900417
B87: 7 | C87: 2031 | D87: =D86*130% -> 222775800 | E87: =D87/100000 -> 2227.758 | G87: 7 | H87: 2031 | I87: 1200 | J87: =D87/I87/1000 -> 185.6465 | K87: =J87/12 -> 15.470542
B88: 8 | C88: 2032 | D88: =D87*130% -> 289608540 | E88: =D88/100000 -> 2896.0854 | G88: 8 | H88: 2032 | I88: 1200 | J88: =D88/I88/1000 -> 241.34045 | K88: =J88/12 -> 20.111704
B89: 9 | C89: 2033 | D89: =D88*130% -> 376491102 | E89: =D89/100000 -> 3764.911 | G89: 9 | H89: 2033 | I89: 1200 | J89: =D89/I89/1000 -> 313.74259 | K89: =J89/12 -> 26.145215
B90: 10 | C90: 2034 | D90: =D89*130% -> 4.8943843e+08 | E90: =D90/100000 -> 4894.3843 | G90: 10 | H90: 2034 | I90: 1200 | J90: =D90/I90/1000 -> 407.86536 | K90: =J90/12 -> 33.98878
C91: TOTAL | E91: =SUM(E81:E90) -> 19358.999 | H91: TOTAL | J91: =SUM(J81:J90) -> 1613.2499 | K91: =SUM(K81:K90) -> 137.56249

Sheet All Costs
D3: Assessment of All Costs (in Lakhs)
B6: SI No. | D6: Sales | E6: ='P&L'!F5 -> 2025-26 | F6: ='P&L'!G5 -> 2026-27 | G6: ='P&L'!H5 -> 2027-28 | H6: ='P&L'!I5 -> 2028-29 | I6: ='P&L'!J5 -> 2029-30 | J6: ='P&L'!K5 -> 2030-31 | K6: ='P&L'!L5 -> 2031-32 | L6: ='P&L'!M5 -> 2032-33 | ... N6: ='P&L'!O5 -> 2034-35
B7: 1 | D7: Corporate Sales | E7: ='P&L'!F9 -> 135 | F7: ='P&L'!G9 -> 162 | G7: ='P&L'!H9 -> 202.5 | H7: ='P&L'!I9 -> 253.125 | I7: ='P&L'!J9 -> 316.40625 | J7: ='P&L'!K9 -> 395.50781 | K7: ='P&L'!L9 -> 494.38477 | L7: ='P&L'!M9 -> 617.98096 | ... N7: ='P&L'!O9 -> 965.59525
B8: 2 | D8: Millet Cafeteria | E8: ='P&L'!F11 -> 270 | F8: ='P&L'!G11 -> 792 | G8: ='P&L'!H11 -> 1633.5 | H8: ='P&L'!I11 -> 2874.96 | I8: ='P&L'!J11 -> 4348.377 | J8: ='P&L'!K11 -> 5811.0129 | K8: ='P&L'!L11 -> 7409.0414 | L8: ='P&L'!M11 -> 9304.8844 | ... N8: ='P&L'!O11 -> 13622.122
B9: 3 | D9: Retail Market Sales | E9: ='P&L'!F13 -> 75 | F9: ='P&L'!G13 -> 600 | G9: ='P&L'!H13 -> 1200 | H9: ='P&L'!I13 -> 1800 | I9: ='P&L'!J13 -> 2700 | J9: ='P&L'!K13 -> 3375 | K9: ='P&L'!L13 -> 4218.75 | L9: ='P&L'!M13 -> 5273.4375 | ... N9: ='P&L'!O13 -> 8239.7461
B10: 4 | D10: Export Sales | E10: ='P&L'!F15 -> 150 | F10: ='P&L'!G15 -> 600 | G10: ='P&L'!H15 -> 780 | H10: ='P&L'!I15 -> 1014 | I10: ='P&L'!J15 -> 1318.2 | J10: ='P&L'!K15 -> 1713.66 | K10: ='P&L'!L15 -> 2227.758 | L10: ='P&L'!M15 -> 2896.0854 | ... N10: ='P&L'!O15 -> 4894.3843
B12: SI No. | D12: Direct Costs | E12: =E6 -> 2025-26 | F12: =F6 -> 2026-27 | G12: =G6 -> 2027-28 | H12: =H6 -> 2028-29 | I12: =I6 -> 2029-30 | J12: =J6 -> 2030-31 | K12: =K6 -> 2031-32 | L12: =L6 -> 2032-33 | ... N12: =N6 -> 2034-35
B13: 1 | D13: Direct Cost % ( % of Corporate Sales ) | E13: ='Revenue generation breakup'!M23 -> 0.35 | F13: =E13 -> 0.35 | G13: =F13 -> 0.35 | H13: =G13 -> 0.35 | I13: =H13 -> 0.35 | J13: =I13 -> 0.35 | K13: =J13 -> 0.35 | L13: =K13 -> 0.35 | M13: =L13 -> 0.35 | N13: =M13 -> 0.35
B14: 2 | D14: Direct Cost % ( % of Millet Cafeteria ) | E14: ='Revenue generation breakup'!D40/'Revenue generation breakup'!D38 -> 0.22 | F14: =E14 -> 0.22 | G14: =F14 -> 0.22 | H14: =G14 -> 0.22 | I14: =H14 -> 0.22 | J14: =I14 -> 0.22 | K14: =J14 -> 0.22 | L14: =K14 -> 0.22 | M14: =L14 -> 0.22 | N14: =M14 -> 0.22
B15: 3 | D15: Direct Cost % ( % of Retail Market Sales) | E15: 0.65 | F15: =E15 -> 0.65 | G15: =F15 -> 0.65 | H15: =G15 -> 0.65 | I15: =H15 -> 0.65 | J15: =I15 -> 0.65 | K15: =J15 -> 0.65 | L15: =K15 -> 0.65 | M15: =L15 -> 0.65 | N15: =M15 -> 0.65
B16: 4 | D16: Direct Cost % ( % of Export Sales ) | E16: 0.78 | F16: =E16 -> 0.78 | G16: =F16 -> 0.78 | H16: =G16 -> 0.78 | I16: =H16 -> 0.78 | J16: =I16 -> 0.78 | K16: =J16 -> 0.78 | L16: =K16 -> 0.78 | M16: =L16 -> 0.78 | N16: =M16 -> 0.78
B18: SI No. | D18: Direct Cost | E18: =E6 -> 2025-26 | F18: =F6 -> 2026-27 | G18: =G6 -> 2027-28 | H18: =H6 -> 2028-29 | I18: =I6 -> 2029-30 | J18: =J6 -> 2030-31 | K18: =K6 -> 2031-32 | L18: =L6 -> 2032-33 | ... N18: =N6 -> 2034-35
B19: 1 | D19: Direct Cost (Corporate Sales ) | E19: =E7*E13 -> 47.25 | F19: =F7*F13 -> 56.7 | G19: =G7*G13 -> 70.875 | H19: =H7*H13 -> 88.59375 | I19: =I7*I13 -> 110.74219 | J19: =J7*J13 -> 138.42773 | K19: =K7*K13 -> 173.03467 | L19: =L7*L13 -> 216.29333 | ... N19: =N7*N13 -> 337.95834
B20: =B19+1 -> 2 | D20: Direct Cost ( Millet Cafeteria ) | E20: =E8*E14 -> 59.4 | F20: =F8*F14 -> 174.24 | G20: =G8*G14 -> 359.37 | H20: =H8*H14 -> 632.4912 | I20: =I8*I14 -> 956.64294 | J20: =J8*J14 -> 1278.4228 | K20: =K8*K14 -> 1629.9891 | L20: =L8*L14 -> 2047.0746 | ... N20: =N8*N14 -> 2996.8668
B21: =B20+1 -> 3 | D21: Direct Cost ( Retail Market Sales) | E21: =E9*E15 -> 48.75 | F21: =F9*F15 -> 390 | G21: =G9*G15 -> 780 | H21: =H9*H15 -> 1170 | I21: =I9*I15 -> 1755 | J21: =J9*J15 -> 2193.75 | K21: =K9*K15 -> 2742.1875 | L21: =L9*L15 -> 3427.7344 | ... N21: =N9*N15 -> 5355.835
B22: =B21+1 -> 4 | D22: Direct Cost ( Export Sales ) | E22: =E10*E16 -> 117 | F22: =F10*F16 -> 468 | G22: =G10*G16 -> 608.4 | H22: =H10*H16 -> 790.92 | I22: =I10*I16 -> 1028.196 | J22: =J10*J16 -> 1336.6548 | K22: =K10*K16 -> 1737.6512 | L22: =L10*L16 -> 2258.9466 | ... N22: =N10*N16 -> 3817.6198
B24: SI No. | D24: Employee Costs | E24: =E18 -> 2025-26 | F24: =F18 -> 2026-27 | G24: =G18 -> 2027-28 | H24: =H18 -> 2028-29 | I24: =I18 -> 2029-30 | J24: =J18 -> 2030-31 | K24: =K18 -> 2031-32 | L24: =L18 -> 2032-33 | ... N24: =N18 -> 2034-35
B25: 1 | D25: Employee Cost % ( % of Corporate Sales ) | E25: ='Revenue generation breakup'!M24 -> 0.25 | F25: =E25 -> 0.25 | G25: =F25 -> 0.25 | H25: =G25 -> 0.25 | I25: =H25 -> 0.25 | J25: =I25 -> 0.25 | K25: =J25 -> 0.25 | L25: =K25 -> 0.25 | M25: =L25 -> 0.25 | N25: =M25 -> 0.25
B26: 2 | D26: Employee Cost % ( % of Millet Cafeteria ) | E26: ='Revenue generation breakup'!D41/'Revenue generation breakup'!D38 -> 0.25 | F26: =E26 -> 0.25 | G26: =F26 -> 0.25 | H26: =G26 -> 0.25 | I26: =H26 -> 0.25 | J26: =I26 -> 0.25 | K26: =J26 -> 0.25 | L26: =K26 -> 0.25 | M26: =L26 -> 0.25 | N26: =M26 -> 0.25
B28: SI No. | D28: Employee Costs | E28: =E24 -> 2025-26 | F28: =F24 -> 2026-27 | G28: =G24 -> 2027-28 | H28: =H24 -> 2028-29 | I28: =I24 -> 2029-30 | J28: =J24 -> 2030-31 | K28: =K24 -> 2031-32 | L28: =L24 -> 2032-33 | ... N28: =N24 -> 2034-35
B29: 1 | D29: Employee Cost ( Corporate Sales ) | E29: =E25*E7 -> 33.75 | F29: =F25*F7 -> 40.5 | G29: =G25*G7 -> 50.625 | H29: =H25*H7 -> 63.28125 | I29: =I25*I7 -> 79.101562 | J29: =J25*J7 -> 98.876953 | K29: =K25*K7 -> 123.59619 | L29: =L25*L7 -> 154.49524 | ... N29: =N25*N7 -> 241.39881
B30: =B29+1 -> 2 | D30: Employee Cost ( Millet Cafeteria ) | E30: =E26*E8 -> 67.5 | F30: =F26*F8 -> 198 | G30: =G26*G8 -> 408.375 | H30: =H26*H8 -> 718.74 | I30: =I26*I8 -> 1087.0943 | J30: =J26*J8 -> 1452.7532 | K30: =K26*K8 -> 1852.2604 | L30: =L26*L8 -> 2326.2211 | ... N30: =N26*N8 -> 3405.5305
B32: SI No. | D32: Promotional Costs | E32: =E28 -> 2025-26 | F32: =F28 -> 2026-27 | G32: =G28 -> 2027-28 | H32: =H28 -> 2028-29 | I32: =I28 -> 2029-30 | J32: =J28 -> 2030-31 | K32: =K28 -> 2031-32 | L32: =L28 -> 2032-33 | ... N32: =N28 -> 2034-35
B33: 1 | D33: Promotional Costs % ( % of Corporate Sales ) | E33: ='Revenue generation breakup'!M25 -> 0.05 | F33: =E33 -> 0.05 | G33: =F33 -> 0.05 | H33: =G33 -> 0.05 | I33: =H33 -> 0.05 | J33: =I33 -> 0.05 | K33: =J33 -> 0.05 | L33: =K33 -> 0.05 | M33: =L33 -> 0.05 | N33: =M33 -> 0.05
B34: 2 | D34: Promotional Costs % ( % of Millet Cafeteria ) | E34: ='Revenue generation breakup'!D44/'Revenue generation breakup'!D38 -> 0.05 | F34: =E34 -> 0.05 | G34: =F34 -> 0.05 | H34: =G34 -> 0.05 | I34: =H34 -> 0.05 | J34: =I34 -> 0.05 | K34: =J34 -> 0.05 | L34: =K34 -> 0.05 | M34: =L34 -> 0.05 | N34: =M34 -> 0.05
B36: SI No. | D36: =D32 -> Promotional Costs | E36: =E32 -> 2025-26 | F36: =F32 -> 2026-27 | G36: =G32 -> 2027-28 | H36: =H32 -> 2028-29 | I36: =I32 -> 2029-30 | J36: =J32 -> 2030-31 | K36: =K32 -> 2031-32 | ... N36: =N32 -> 2034-35
B37: 1 | D37: Promotional Costs ( Corporate Sales ) | E37: =E33*E7 -> 6.75 | F37: =F33*F7 -> 8.1 | G37: =G33*G7 -> 10.125 | H37: =H33*H7 -> 12.65625 | I37: =I33*I7 -> 15.820312 | J37: =J33*J7 -> 19.775391 | K37: =K33*K7 -> 24.719238 | L37: =L33*L7 -> 30.899048 | ... N37: =N33*N7 -> 48.279762
B38: =B37+1 -> 2 | D38: Promotional Costs ( Millet Cafeteria ) | E38: =E34*E8 -> 13.5 | F38: =F34*F8 -> 39.6 | G38: =G34*G8 -> 81.675 | H38: =H34*H8 -> 143.748 | I38: =I34*I8 -> 217.41885 | J38: =J34*J8 -> 290.55065 | K38: =K34*K8 -> 370.45207 | L38: =L34*L8 -> 465.24422 | ... N38: =N34*N8 -> 681.1061
B40: SI No. | D40: Other Expenses | E40: =E36 -> 2025-26 | F40: =F36 -> 2026-27 | G40: =G36 -> 2027-28 | H40: =H36 -> 2028-29 | I40: =I36 -> 2029-30 | J40: =J36 -> 2030-31 | K40: =K36 -> 2031-32 | L40: =L36 -> 2032-33 | ... N40: =N36 -> 2034-35
B41: 1 | D41: Other Expenses % ( % of Corporate Sales ) | E41: ='Revenue generation breakup'!M26 -> 0.1 | F41: =E41 -> 0.1 | G41: =F41 -> 0.1 | H41: =G41 -> 0.1 | I41: =H41 -> 0.1 | J41: =I41 -> 0.1 | K41: =J41 -> 0.1 | L41: =K41 -> 0.1 | M41: =L41 -> 0.1 | N41: =M41 -> 0.1
B43: SI No. | D43: =D40 -> Other Expenses | E43: =E40 -> 2025-26 | F43: =F40 -> 2026-27 | G43: =G40 -> 2027-28 | H43: =H40 -> 2028-29 | I43: =I40 -> 2029-30 | J43: =J40 -> 2030-31 | K43: =K40 -> 2031-32 | ... N43: =N40 -> 2034-35
B44: 1 | D44: Other Expenses ( Corporate Sales ) | E44: =E41*E7 -> 13.5 | F44: =F41*F7 -> 16.2 | G44: =G41*G7 -> 20.25 | H44: =H41*H7 -> 25.3125 | I44: =I41*I7 -> 31.640625 | J44: =J41*J7 -> 39.550781 | K44: =K41*K7 -> 49.438477 | L44: =L41*L7 -> 61.798096 | ... N44: =N41*N7 -> 96.559525
B46: SI No. | D46: Millet Cafeteria - Expenses | E46: =E43 -> 2025-26 | F46: =F43 -> 2026-27 | G46: =G43 -> 2027-28 | H46: =H43 -> 2028-29 | I46: =I43 -> 2029-30 | J46: =J43 -> 2030-31 | K46: =K43 -> 2031-32 | L46: =L43 -> 2032-33 | ... N46: =N43 -> 2034-35
B47: 1 | D47: Rent % ( % of Millet Cafeteria) | E47: ='Revenue generation breakup'!D42/'Revenue generation breakup'!D38 -> 0.1 | F47: =E47 -> 0.1 | G47: =F47 -> 0.1 | H47: =G47 -> 0.1 | I47: =H47 -> 0.1 | J47: =I47 -> 0.1 | K47: =J47 -> 0.1 | L47: =K47 -> 0.1 | M47: =L47 -> 0.1 | N47: =M47 -> 0.1
B48: 2 | D48: Misc Expenses % ( % of Millet Cafeteria ) | E48: ='Revenue generation breakup'!D43/'Revenue generation breakup'!D38 -> 0.04 | F48: =E48 -> 0.04 | G48: =F48 -> 0.04 | H48: =G48 -> 0.04 | I48: =H48 -> 0.04 | J48: =I48 -> 0.04 | K48: =J48 -> 0.04 | L48: =K48 -> 0.04 | M48: =L48 -> 0.04 | N48: =M48 -> 0.04
B50: SI No. | D50: =D46 -> Millet Cafeteria - Expenses | E50: =E46 -> 2025-26 | F50: =F46 -> 2026-27 | G50: =G46 -> 2027-28 | H50: =H46 -> 2028-29 | I50: =I46 -> 2029-30 | J50: =J46 -> 2030-31 | K50: =K46 -> 2031-32 | ... N50: =N46 -> 2034-35
B51: 1 | D51: Rent ( Millet Cafeteria) | E51: =E47*E8 -> 27 | F51: =F47*F8 -> 79.2 | G51: =G47*G8 -> 163.35 | H51: =H47*H8 -> 287.496 | I51: =I47*I8 -> 434.8377 | J51: =J47*J8 -> 581.10129 | K51: =K47*K8 -> 740.90414 | L51: =L47*L8 -> 930.48844 | ... N51: =N47*N8 -> 1362.2122
B52: =B51+1 -> 2 | D52: Misc Expenses (Millet Cafeteria ) | E52: =E48*E8 -> 10.8 | F52: =F48*F8 -> 31.68 | G52: =G48*G8 -> 65.34 | H52: =H48*H8 -> 114.9984 | I52: =I48*I8 -> 173.93508 | J52: =J48*J8 -> 232.44052 | K52: =K48*K8 -> 296.36166 | L52: =L48*L8 -> 372.19538 | ... N52: =N48*N8 -> 544.88488

Sheet DAS
B2: Depreciation And Amortisation Schedule
X3: =Do -> (₹ in Lakhs)
B5: Particulars | F5: =WC!E6 -> 2025-26 | H5: =WC!F6 -> 2026-27 | J5: =WC!G6 -> 2027-28 | L5: =WC!H6 -> 2028-29 | N5: =WC!I6 -> 2029-30 | P5: =WC!J6 -> 2030-31 | R5: =WC!K6 -> 2031-32 | T5: =WC!L6 -> 2032-33 | V5: =WC!M6 -> 2033-34 | X5: =WC!N6 -> 2034-35
B7: Property, Plant and Equipment
D9: Opening | F9: =323333.3/100000 -> 3.233333 | H9: =F15 -> 1.1911701 | J9: =H15 -> 0.4388308 | L9: =J15 -> 0.16166665 | N9: =L15 -> 0.059558503 | P9: =N15 -> 0.02194154 | R9: =P15 -> 0.0080833325 | T9: =R15 -> 0.0029779252 | V9: =T15 -> 0.001097077 | X9: =V15 -> 0.00040416663
B11: Computers & Peripherals | D11: Additions | F11: 0 | H11: 0 | J11: 0 | L11: 0 | N11: 0 | P11: 0 | R11: 0 | T11: 0 | V11: 0 | X11: 0
D13: Depreciation | F13: =(F9+F11)*$B15 -> 2.0421629 | H13: =(H9+H11)*$B15 -> 0.75233926 | J13: =(J9+J11)*$B15 -> 0.27716415 | L13: =(L9+L11)*$B15 -> 0.10210815 | N13: =(N9+N11)*$B15 -> 0.037616963 | P13: =(P9+P11)*$B15 -> 0.013858208 | R13: =(R9+R11)*$B15 -> 0.0051054073 | T13: =(T9+T11)*$B15 -> 0.0018808481 | V13: =(V9+V11)*$B15 -> 0.00069291038 | X13: =(X9+X11)*$B15 -> 0.00025527037
B15: 0.63159685 | D15: Closing | F15: =F9+F11-F13 -> 1.1911701 | H15: =H9+H11-H13 -> 0.4388308 | J15: =J9+J11-J13 -> 0.16166665 | L15: =L9+L11-L13 -> 0.059558503 | N15: =N9+N11-N13 -> 0.02194154 | P15: =P9+P11-P13 -> 0.0080833325 | R15: =R9+R11-R13 -> 0.0029779252 | T15: =T9+T11-T13 -> 0.001097077 | V15: =V9+V11-V13 -> 0.00040416663 | X15: =X9+X11-X13 -> 0.00014889626
B17: Plant and Machinery | D17: Opening | F17: =8998880.77/100000 -> 89.988808 | H17: =F23 -> 108.91301 | J17: =H23 -> 141.60948 | L17: =J23 -> 177.39531 | N17: =L23 -> 224.71981 | P17: =N23 -> 268.39063 | R17: =P23 -> 304.15546 | T17: =R23 -> 363.74721 | V17: =T23 -> 412.55069 | X17: =V23 -> 472.99307
D19: Additions | F19: =43/Ro*Ro -> 43 | H19: =64/Ro*Ro -> 64 | J19: =75/Ro*Ro -> 75 | L19: =97/Ro*Ro -> 97 | N19: =103/Ro*Ro -> 103 | P19: =103/Ro*Ro -> 103 | R19: =140/Ro*Ro -> 140 | T19: =140/Ro*Ro -> 140 | V19: =165/Ro*Ro -> 165 | X19: =220/Ro*Ro -> 220
D21: Depreciation | F21: =(F17+F19)*$B23 -> 24.075798 | H21: =(H17+H19)*$B23 -> 31.303527 | J21: =(J17+J19)*$B23 -> 39.214173 | L21: =(L17+L19)*$B23 -> 49.675504 | N21: =(N17+N19)*$B23 -> 59.329172 | P21: =(P17+P19)*$B23 -> 67.235176 | R21: =(R17+R19)*$B23 -> 80.408248 | T21: =(T17+T19)*$B23 -> 91.196517 | V21: =(V17+V19)*$B23 -> 104.55762 | X21: =(X17+X19)*$B23 -> 125.45688
B23: 0.18103627 | D23: Closing | F23: =F17+F19-F21 -> 108.91301 | H23: =H17+H19-H21 -> 141.60948 | J23: =J17+J19-J21 -> 177.39531 | L23: =L17+L19-L21 -> 224.71981 | N23: =N17+N19-N21 -> 268.39063 | P23: =P17+P19-P21 -> 304.15546 | R23: =R17+R19-R21 -> 363.74721 | T23: =T17+T19-T21 -> 412.55069 | V23: =V17+V19-V21 -> 472.99307 | X23: =X17+X19-X21 -> 567.53619
B25: Furniture and Fixtures | D25: Opening | F25: =564686.5/100000 -> 5.646865 | H25: =F31 -> 4.185085 | J25: =H31 -> 3.1017098 | L25: =J31 -> 2.2987834 | N25: =L31 -> 1.7037071 | P25: =N31 -> 1.2626757 | R25: =P31 -> 0.93581217 | T25: =R31 -> 0.69356245 | V25: =T31 -> 0.51402288 | X25: =V31 -> 0.38095996
D27: Additions | F27: 0 | H27: 0 | J27: 0 | L27: 0 | N27: 0 | P27: 0 | R27: 0 | T27: 0 | V27: 0 | X27: 0
D29: Depreciation | F29: =(F25+F27)*$B31 -> 1.46178 | H29: =(H25+H27)*$B31 -> 1.0833752 | J29: =(J25+J27)*$B31 -> 0.80292646 | L29: =(L25+L27)*$B31 -> 0.59507629 | N29: =(N25+N27)*$B31 -> 0.44103142 | P29: =(P25+P27)*$B31 -> 0.32686349 | R29: =(R25+R27)*$B31 -> 0.24224972 | T29: =(T25+T27)*$B31 -> 0.17953957 | V29: =(V25+V27)*$B31 -> 0.13306292 | X29: =(X25+X27)*$B31 -> 0.098617488
B31: 0.25886576 | D31: Closing | F31: =F25+F27-F29 -> 4.185085 | H31: =H25+H27-H29 -> 3.1017098 | J31: =J25+J27-J29 -> 2.2987834 | L31: =L25+L27-L29 -> 1.7037071 | N31: =N25+N27-N29 -> 1.2626757 | P31: =P25+P27-P29 -> 0.93581217 | R31: =R25+R27-R29 -> 0.69356245 | T31: =T25+T27-T29 -> 0.51402288 | V31: =V25+V27-V29 -> 0.38095996 | X31: =X25+X27-X29 -> 0.28234247
B33: Motor Vehicles | D33: Opening | F33: =447968.16/100000 -> 4.4796816 | H33: =F39 -> 3.0804791 | J33: =H39 -> 2.1183094 | L33: =J39 -> 1.4566678 | N33: =L39 -> 1.0016861 | P33: =N39 -> 0.68881528 | R33: =P39 -> 0.47366783 | T33: =R39 -> 0.32572044 | V33: =T39 -> 0.22398356 | X33: =V39 -> 0.1540236
D35: Additions | F35: 0 | H35: 0 | J35: 0 | L35: 0 | N35: 0 | P35: 0 | R35: 0 | T35: 0 | V35: 0 | X35: 0
D37: Depreciation | F37: =(F33+F35)*$B39 -> 1.3992025 | H37: =(H33+H35)*$B39 -> 0.96216972 | J37: =(J33+J35)*$B39 -> 0.66164161 | L37: =(L33+L35)*$B39 -> 0.45498171 | N37: =(N33+N35)*$B39 -> 0.31287082 | P37: =(P33+P35)*$B39 -> 0.21514744 | R37: =(R33+R35)*$B39 -> 0.14794739 | T37: =(T33+T35)*$B39 -> 0.10173688 | V37: =(V33+V35)*$B39 -> 0.069959961 | X37: =(X33+X35)*$B39 -> 0.048108374
B39: 0.31234418 | D39: Closing | F39: =F33+F35-F37 -> 3.0804791 | H39: =H33+H35-H37 -> 2.1183094 | J39: =J33+J35-J37 -> 1.4566678 | L39: =L33+L35-L37 -> 1.0016861 | N39: =N33+N35-N37 -> 0.68881528 | P39: =P33+P35-P37 -> 0.47366783 | R39: =R33+R35-R37 -> 0.32572044 | T39: =T33+T35-T37 -> 0.22398356 | V39: =V33+V35-V37 -> 0.1540236 | X39: =X33+X35-X37 -> 0.10591522
B41: Lab equipment | D41: Opening | F41: =548174.61/100000 -> 5.4817461 | H41: =F47 -> 4.0627109 | J41: =H47 -> 3.011015 | L41: =J47 -> 2.2315669 | N41: =L47 -> 1.6538911 | P41: =N47 -> 1.2257557 | R41: =P47 -> 0.90844977 | T41: =R47 -> 0.67328342 | V41: =T47 -> 0.49899354 | X41: =V47 -> 0.3698213
D43: Additions | F43: 0 | H43: 0 | J43: 0 | L43: 0 | N43: 0 | P43: 0 | R43: 0 | T43: 0 | V43: 0 | X43: 0
D45: Depreciation | F45: =(F41+F43)*$B47 -> 1.4190352 | H45: =(H41+H43)*$B47 -> 1.0516959 | J45: =(J41+J43)*$B47 -> 0.77944805 | L45: =(L41+L43)*$B47 -> 0.5776758 | N45: =(N41+N43)*$B47 -> 0.42813544 | P45: =(P41+P43)*$B47 -> 0.31730592 | R45: =(R41+R43)*$B47 -> 0.23516635 | T45: =(T41+T43)*$B47 -> 0.17428988 | V45: =(V41+V43)*$B47 -> 0.12917224 | X45: =(X41+X43)*$B47 -> 0.095733994
B47: 0.25886555 | D47: Closing | F47: =F41+F43-F45 -> 4.0627109 | H47: =H41+H43-H45 -> 3.011015 | J47: =J41+J43-J45 -> 2.2315669 | L47: =L41+L43-L45 -> 1.6538911 | N47: =N41+N43-N45 -> 1.2257557 | P47: =P41+P43-P45 -> 0.90844977 | R47: =R41+R43-R45 -> 0.67328342 | T47: =T41+T43-T45 -> 0.49899354 | V47: =V41+V43-V45 -> 0.3698213 | X47: =X41+X43-X45 -> 0.2740873
B49: Electricals & Fittings | D49: Opening | F49: =541693.96/100000 -> 5.4169396 | H49: =F55 -> 4.0146805 | J49: =H55 -> 2.9754181 | L49: =J55 -> 2.2051848 | N49: =L55 -> 1.6343384 | P49: =N55 -> 1.2112645 | R49: =P55 -> 0.89770986 | T49: =R55 -> 0.6653237 | V49: =T55 -> 0.49309432 | X49: =V55 -> 0.36544918
D51: Additions | F51: 0 | H51: 0 | J51: 0 | L51: 0 | N51: 0 | P51: 0 | R51: 0 | T51: 0 | V51: 0 | X51: 0
D53: Depreciation | F53: =(F49+F51)*$B55 -> 1.4022591 | H53: =(H49+H51)*$B55 -> 1.0392625 | J53: =(J49+J51)*$B55 -> 0.77023323 | L53: =(L49+L51)*$B55 -> 0.57084638 | N53: =(N49+N51)*$B55 -> 0.42307392 | P53: =(P49+P51)*$B55 -> 0.31355466 | R53: =(R49+R51)*$B55 -> 0.23238616 | T53: =(T49+T51)*$B55 -> 0.17222939 | V53: =(V49+V51)*$B55 -> 0.12764513 | X53: =(X49+X51)*$B55 -> 0.094602204
B55: 0.25886555 | D55: Closing | F55: =F49+F51-F53 -> 4.0146805 | H55: =H49+H51-H53 -> 2.9754181 | J55: =J49+J51-J53 -> 2.2051848 | L55: =L49+L51-L53 -> 1.6343384 | N55: =N49+N51-N53 -> 1.2112645 | P55: =P49+P51-P53 -> 0.89770986 | R55: =R49+R51-R53 -> 0.6653237 | T55: =T49+T51-T53 -> 0.49309432 | V55: =V49+V51-V53 -> 0.36544918 | X55: =X49+X51-X53 -> 0.27084698
B57: Office equipment | D57: Opening | F57: =486356.03/100000 -> 4.8635603 | H57: =F63 -> 2.6714577 | J57: =H63 -> 1.467379 | L57: =J63 -> 0.80600235 | N57: =L63 -> 0.44272119 | P57: =N63 -> 0.24317802 | R57: =P63 -> 0.13357289 | T57: =R63 -> 0.073368951 | V57: =T63 -> 0.040300117 | X57: =V63 -> 0.022136059
D59: Additions | F59: 0 | H59: 0 | J59: 0 | L59: 0 | N59: 0 | P59: 0 | R59: 0 | T59: 0 | V59: 0 | X59: 0
D61: Depreciation | F61: =(F57+F59)*$B63 -> 2.1921026 | H61: =(H57+H59)*$B63 -> 1.2040787 | J61: =(J57+J59)*$B63 -> 0.66137667 | L61: =(L57+L59)*$B63 -> 0.36328116 | N61: =(N57+N59)*$B63 -> 0.19954317 | P61: =(P57+P59)*$B63 -> 0.10960513 | R61: =(R57+R59)*$B63 -> 0.060203935 | T61: =(T57+T59)*$B63 -> 0.033068834 | V61: =(V57+V59)*$B63 -> 0.018164058 | X61: =(X57+X59)*$B63 -> 0.0099771587
B63: 0.45071973 | D63: Closing | F63: =F57+F59-F61 -> 2.6714577 | H63: =H57+H59-H61 -> 1.467379 | J63: =J57+J59-J61 -> 0.80600235 | L63: =L57+L59-L61 -> 0.44272119 | N63: =N57+N59-N61 -> 0.24317802 | P63: =P57+P59-P61 -> 0.13357289 | R63: =R57+R59-R61 -> 0.073368951 | T63: =T57+T59-T61 -> 0.040300117 | V63: =V57+V59-V61 -> 0.022136059 | X63: =X57+X59-X61 -> 0.012158901
B65: Leasehold improvements | D65: Opening | F65: =1772388.54/100000 -> 17.723885 | H65: =F71 -> 13.135971 | J65: =H71 -> 9.7356601 | L65: =J71 -> 7.2155367 | N65: =L71 -> 5.3477596 | P65: =N71 -> 3.9634657 | R65: =P71 -> 2.9375032 | T65: =R71 -> 2.177116 | V65: =T71 -> 1.6135589 | X65: =V71 -> 1.1958812
D67: Additions | F67: 0 | H67: 0 | J67: 0 | L67: 0 | N67: 0 | P67: 0 | R67: 0 | T67: 0 | V67: 0 | X67: 0
D69: Depreciation | F69: =(F65+F67)*$B71 -> 4.5879148 | H69: =(H65+H67)*$B71 -> 3.4003105 | J69: =(J65+J67)*$B71 -> 2.5201234 | L69: =(L65+L67)*$B71 -> 1.8677771 | N69: =(N65+N67)*$B71 -> 1.3842938 | P69: =(P65+P67)*$B71 -> 1.0259626 | R69: =(R65+R67)*$B71 -> 0.76038712 | T69: =(T65+T67)*$B71 -> 0.56355718 | V69: =(V65+V67)*$B71 -> 0.41767764 | X69: =(X65+X67)*$B71 -> 0.30955973
B71: 0.25885491 | D71: Closing | F71: =F65+F67-F69 -> 13.135971 | H71: =H65+H67-H69 -> 9.7356601 | J71: =J65+J67-J69 -> 7.2155367 | L71: =L65+L67-L69 -> 5.3477596 | N71: =N65+N67-N69 -> 3.9634657 | P71: =P65+P67-P69 -> 2.9375032 | R71: =R65+R67-R69 -> 2.177116 | T71: =T65+T67-T69 -> 1.6135589 | V71: =V65+V67-V69 -> 1.1958812 | X71: =X65+X67-X69 -> 0.88632149
B73: Barcode Rights | D73: Opening | F73: =38540.92/100000 -> 0.3854092 | H73: =F79 -> 0.21169767 | J73: =H79 -> 0.11628135 | L73: =J79 -> 0.063871054 | N73: =L79 -> 0.03508311 | P73: =N79 -> 0.01927046 | R73: =P79 -> 0.010584884 | T73: =R79 -> 0.0058140677 | V73: =T79 -> 0.0031935527 | X73: =V79 -> 0.0017541555
D75: Additions | F75: 0 | H75: 0 | J75: 0 | L75: 0 | N75: 0 | P75: 0 | R75: 0 | T75: 0 | V75: 0 | X75: 0
D77: Depreciation | F77: =(F73+F75)*$B79 -> 0.17371153 | H77: =(H73+H75)*$B79 -> 0.095416316 | J77: =(J73+J75)*$B79 -> 0.0524103 | L77: =(L73+L75)*$B79 -> 0.028787944 | N77: =(N73+N75)*$B79 -> 0.01581265 | P77: =(P73+P75)*$B79 -> 0.0086855765 | R77: =(R73+R75)*$B79 -> 0.0047708158 | T77: =(T73+T75)*$B79 -> 0.002620515 | V77: =(V73+V75)*$B79 -> 0.0014393972 | X77: =(X73+X75)*$B79 -> 0.00079063248
B79: 0.45071973 | D79: Closing | F79: =F73+F75-F77 -> 0.21169767 | H79: =H73+H75-H77 -> 0.11628135 | J79: =J73+J75-J77 -> 0.063871054 | L79: =L73+L75-L77 -> 0.03508311 | N79: =N73+N75-N77 -> 0.01927046 | P79: =P73+P75-P77 -> 0.010584884 | R79: =R73+R75-R77 -> 0.0058140677 | T79: =T73+T75-T77 -> 0.0031935527 | V79: =V73+V75-V77 -> 0.0017541555 | X79: =X73+X75-X77 -> 0.000963523
B81: Total of Property, Plant and Equipment | D81: Opening | F81: =F9+F17+F25+F33+F41+F49+F57+F65+F73 -> 137.22023 | H81: =F87 -> 142.86852 | J81: =H87 -> 167.01561 | L81: =J87 -> 197.04634 | N81: =L87 -> 240.38115 | P81: =N87 -> 281.23268 | R81: =P87 -> 314.98007 | T81: =R87 -> 373.11599 | V81: =T87 -> 420.86278 | X81: =V87 -> 480.53499
D83: Additions | F83: =F75+F67+F59+F43+F35+F27+F19+F11 -> 43 | H83: =H75+H67+H59+H43+H35+H27+H19+H11 -> 64 | J83: =J75+J67+J59+J43+J35+J27+J19+J11 -> 75 | L83: =L75+L67+L59+L43+L35+L27+L19+L11 -> 97 | N83: =N75+N67+N59+N43+N35+N27+N19+N11 -> 103 | P83: =P75+P67+P59+P43+P35+P27+P19+P11 -> 103 | R83: =R75+R67+R59+R43+R35+R27+R19+R11 -> 140 | T83: =T75+T67+T59+T43+T35+T27+T19+T11 -> 140 | V83: =V75+V67+V59+V43+V35+V27+V19+V11 -> 165 | X83: =X75+X67+X59+X43+X35+X27+X19+X11 -> 220
D85: Depreciation | F85: =F77+F69+F61+F45+F37+F29+F21+F13 -> 37.351708 | H85: =H77+H69+H61+H45+H37+H29+H21+H13 -> 39.852912 | J85: =J77+J69+J61+J45+J37+J29+J21+J13 -> 44.969264 | L85: =L77+L69+L61+L45+L37+L29+L21+L13 -> 53.665192 | N85: =N77+N69+N61+N45+N37+N29+N21+N13 -> 62.148476 | P85: =P77+P69+P61+P45+P37+P29+P21+P13 -> 69.252604 | R85: =R77+R69+R61+R45+R37+R29+R21+R13 -> 81.864079 | T85: =T77+T69+T61+T45+T37+T29+T21+T13 -> 92.253211 | V85: =V77+V69+V61+V45+V37+V29+V21+V13 -> 105.32779 | X85: =X77+X69+X61+X45+X37+X29+X21+X13 -> 126.01992
D87: Closing | F87: =F81+F83-F85 -> 142.86852 | H87: =H81+H83-H85 -> 167.01561 | J87: =J81+J83-J85 -> 197.04634 | L87: =L81+L83-L85 -> 240.38115 | N87: =N81+N83-N85 -> 281.23268 | P87: =P81+P83-P85 -> 314.98007 | R87: =R81+R83-R85 -> 373.11599 | T87: =T81+T83-T85 -> 420.86278 | V87: =V81+V83-V85 -> 480.53499 | X87: =X81+X83-X85 -> 574.51506
B90: Closing of PPE | F90: =F87 -> 142.86852 | H90: =H87 -> 167.01561 | J90: =J87 -> 197.04634 | L90: =L87 -> 240.38115 | N90: =N87 -> 281.23268 | P90: =P87 -> 314.98007 | R90: =R87 -> 373.11599 | T90: =T87 -> 420.86278 | V90: =V87 -> 480.53499 | X90: =X87 -> 574.51506

Sheet BEA
B2: Break Even Analysis
X3: =Do -> (₹ in Lakhs)
B5: SI No. | D5: Particulars | F5: ='P&L'!F5 -> 2025-26 | H5: ='P&L'!G5 -> 2026-27 | J5: ='P&L'!H5 -> 2027-28 | L5: ='P&L'!I5 -> 2028-29 | N5: ='P&L'!J5 -> 2029-30 | P5: ='P&L'!K5 -> 2030-31 | R5: ='P&L'!L5 -> 2031-32 | T5: ='P&L'!M5 -> 2032-33 | V5: ='P&L'!N5 -> 2033-34 | X5: ='P&L'!O5 -> 2034-35
B7: A | D7: Sales | F7: ='P&L'!F7 -> 630 | H7: ='P&L'!G7 -> 2154 | J7: ='P&L'!H7 -> 3816 | L7: ='P&L'!I7 -> 5942.085 | N7: ='P&L'!J7 -> 8682.9833 | P7: ='P&L'!K7 -> 11295.181 | R7: ='P&L'!L7 -> 14349.934 | T7: ='P&L'!M7 -> 18092.388 | V7: ='P&L'!N7 -> 22500.973 | X7: ='P&L'!O7 -> 27721.848
B9: Variable Expenses
B11: B | D11: Material Cost & Direct Labour | F11: ='P&L'!F17 -> 272.4 | H11: ='P&L'!G17 -> 1088.94 | J11: ='P&L'!H17 -> 1818.645 | L11: ='P&L'!I17 -> 2682.005 | N11: ='P&L'!J17 -> 3850.5811 | P11: ='P&L'!K17 -> 4947.2554 | R11: ='P&L'!L17 -> 6282.8625 | T11: ='P&L'!M17 -> 7950.0489 | V11: ='P&L'!N17 -> 9993.4588 | X11: ='P&L'!O17 -> 12508.28
B13: C | D13: Customs and Handling Charges | F13: ='P&L'!F30 -> 101.25 | H13: ='P&L'!G30 -> 238.5 | J13: ='P&L'!H30 -> 459 | L13: ='P&L'!I30 -> 782.02125 | N13: ='P&L'!J30 -> 1166.1958 | P13: ='P&L'!K30 -> 1551.6302 | R13: ='P&L'!L30 -> 1975.8566 | T13: ='P&L'!M30 -> 2480.7163 | V13: ='P&L'!N30 -> 3036.0663 | X13: ='P&L'!O30 -> 3646.9293
B15: D | D15: Advertise and Marktg Exp | F15: ='P&L'!F32 -> 20.25 | H15: ='P&L'!G32 -> 47.7 | J15: ='P&L'!H32 -> 91.8 | L15: ='P&L'!I32 -> 156.40425 | N15: ='P&L'!J32 -> 233.23916 | P15: ='P&L'!K32 -> 310.32604 | R15: ='P&L'!L32 -> 395.17131 | T15: ='P&L'!M32 -> 496.14327 | V15: ='P&L'!N32 -> 607.21326 | X15: ='P&L'!O32 -> 729.38586
B17: E | D17: Staff Salary | F17: ='P&L'!F36 -> 13.5 | H17: ='P&L'!G36 -> 16.2 | J17: ='P&L'!H36 -> 20.25 | L17: ='P&L'!I36 -> 25.3125 | N17: ='P&L'!J36 -> 31.640625 | P17: ='P&L'!K36 -> 39.550781 | R17: ='P&L'!L36 -> 49.438477 | T17: ='P&L'!M36 -> 61.798096 | V17: ='P&L'!N36 -> 77.24762 | X17: ='P&L'!O36 -> 96.559525
B19: F | D19: Legal & Professional Fee | F19: ='P&L'!F38 -> 10.8 | H19: ='P&L'!G38 -> 31.68 | J19: ='P&L'!H38 -> 65.34 | L19: ='P&L'!I38 -> 114.9984 | N19: ='P&L'!J38 -> 173.93508 | P19: ='P&L'!K38 -> 232.44052 | R19: ='P&L'!L38 -> 296.36166 | T19: ='P&L'!M38 -> 372.19538 | V19: ='P&L'!N38 -> 454.87156 | X19: ='P&L'!O38 -> 544.88488
B23: H | D23: Total of Variable Expenses | F23: =SUM(F11:F21) -> 418.2 | H23: =SUM(H11:H21) -> 1423.02 | J23: =SUM(J11:J21) -> 2455.035 | L23: =SUM(L11:L21) -> 3760.7414 | N23: =SUM(N11:N21) -> 5455.5918 | P23: =SUM(P11:P21) -> 7081.2029 | R23: =SUM(R11:R21) -> 8999.6905 | T23: =SUM(T11:T21) -> 11360.902 | V23: =SUM(V11:V21) -> 14168.858 | X23: =SUM(X11:X21) -> 17526.039
B25: I | D25: Contribution Margin (A-J) | F25: =F7-F23 -> 211.8 | H25: =H7-H23 -> 730.98 | J25: =J7-J23 -> 1360.965 | L25: =L7-L23 -> 2181.3437 | N25: =N7-N23 -> 3227.3914 | P25: =P7-P23 -> 4213.9778 | R25: =R7-R23 -> 5350.2437 | T25: =T7-T23 -> 6731.4863 | V25: =V7-V23 -> 8332.1156 | X25: =X7-X23 -> 10195.808
B27: J | D27: Contribution Margin Ratio (K/A) | F27: =F25/F7 -> 0.33619048 | H27: =H25/H7 -> 0.33935933 | J27: =J25/J7 -> 0.35664701 | L27: =L25/L7 -> 0.36710071 | N27: =N25/N7 -> 0.37169154 | P27: =P25/P7 -> 0.3730775 | R27: =R25/R7 -> 0.37284099 | T27: =T25/T7 -> 0.37206179 | V27: =V25/V7 -> 0.37030023 | X27: =X25/X7 -> 0.36778963
B29: Fixed Expenses
B31: K | D31: Rent Expenses | F31: ='P&L'!F34 -> 27 | H31: ='P&L'!G34 -> 79.2 | J31: ='P&L'!H34 -> 163.35 | L31: ='P&L'!I34 -> 287.496 | N31: ='P&L'!J34 -> 434.8377 | P31: ='P&L'!K34 -> 581.10129 | R31: ='P&L'!L34 -> 740.90414 | T31: ='P&L'!M34 -> 930.48844 | V31: ='P&L'!N34 -> 1137.1789 | X31: ='P&L'!O34 -> 1362.2122
B33: L | D33: Depreciation & Amortization | F33: ='P&L'!F44 -> 37.351708 | H33: ='P&L'!G44 -> 39.852912 | J33: ='P&L'!H44 -> 44.969264 | L33: ='P&L'!I44 -> 53.665192 | N33: ='P&L'!J44 -> 62.148476 | P33: ='P&L'!K44 -> 69.252604 | R33: ='P&L'!L44 -> 81.864079 | T33: ='P&L'!M44 -> 92.253211 | V33: ='P&L'!N44 -> 105.32779 | X33: ='P&L'!O44 -> 126.01992
B35: M | D35: Finance Cost | F35: ='P&L'!F49 -> 179.66495 | H35: ='P&L'!G49 -> 173.67528 | J35: ='P&L'!H49 -> 167.01762 | L35: ='P&L'!I49 -> 159.61466 | N35: ='P&L'!J49 -> 151.37989 | P35: ='P&L'!K49 -> 142.31144 | R35: ='P&L'!L49 -> 135.77614 | T35: ='P&L'!M49 -> 132.7635 | V35: ='P&L'!N49 -> 129.48547 | X35: ='P&L'!O49 -> 125.917
B37: N | D37: Tax Expenses | F37: ='P&L'!F54 -> 0 | H37: ='P&L'!G54 -> 131.47554 | J37: ='P&L'!H54 -> 417.49898 | L37: ='P&L'!I54 -> 842.81432 | N37: ='P&L'!J54 -> 728.90861 | P37: ='P&L'!K54 -> 1026.3937 | R37: ='P&L'!L54 -> 1317.5098 | T37: ='P&L'!M54 -> 1672.7943 | V37: ='P&L'!N54 -> 2088.037 | X37: ='P&L'!O54 -> 2574.4977
B39: O | D39: Total of Fixed Expenses | F39: =SUM(F31:F37) -> 244.01666 | H39: =SUM(H31:H37) -> 424.20373 | J39: =SUM(J31:J37) -> 792.83587 | L39: =SUM(L31:L37) -> 1343.5902 | N39: =SUM(N31:N37) -> 1377.2747 | P39: =SUM(P31:P37) -> 1819.0591 | R39: =SUM(R31:R37) -> 2276.0542 | T39: =SUM(T31:T37) -> 2828.2995 | V39: =SUM(V31:V37) -> 3460.0292 | X39: =SUM(X31:X37) -> 4188.6468
B41: P | D41: Fixed Expenses Ratio (T/A) | F41: =F39/F7 -> 0.38732803 | H41: =H39/H7 -> 0.19693767 | J41: =J39/J7 -> 0.20776621 | L41: =L39/L7 -> 0.22611426 | N41: =N39/N7 -> 0.15861768 | P41: =P39/P7 -> 0.16104736 | R41: =R39/R7 -> 0.15861077 | T41: =T39/T7 -> 0.15632538 | V41: =V39/V7 -> 0.15377242 | X41: =X39/X7 -> 0.15109551
B43: Q | D43: Break-Even Sales (T/L) | F43: =F39/F27 -> 725.82859 | H43: =H39/H27 -> 1250.0135 | J43: =J39/J27 -> 2223.0268 | L43: =L39/L27 -> 3660.0042 | N43: =N39/N27 -> 3705.4238 | P43: =P39/P27 -> 4875.8209 | R43: =R39/R27 -> 6104.6243 | T43: =T39/T27 -> 7601.6931 | V43: =V39/V27 -> 9343.8483 | X43: =X39/X27 -> 11388.703
B45: R | D45: Break-Even Percentage (V/A) | F45: =F43/F7 -> 1.1521089 | H45: =H43/H7 -> 0.58032194 | J45: =J43/J7 -> 0.58255419 | L45: =L43/L7 -> 0.61594613 | N45: =N43/N7 -> 0.42674547 | P45: =P43/P7 -> 0.43167267 | R45: =R43/R7 -> 0.42541131 | T45: =T43/T7 -> 0.42015973 | V45: =V43/V7 -> 0.41526419 | X45: =X43/X7 -> 0.41082048
D47: Average Break-Even Sales | F47: =AVERAGE(F43:X43) -> 5087.8986
D49: Average Break-Even Percentage | F49: =AVERAGE(F45:X45) -> 0.5461005

Sheet WC
D3: Assessment of Trade Receivables
B6: SI No. | D6: Sales | E6: ='P&L'!F5 -> 2025-26 | F6: ='P&L'!G5 -> 2026-27 | G6: ='P&L'!H5 -> 2027-28 | H6: ='P&L'!I5 -> 2028-29 | I6: ='P&L'!J5 -> 2029-30 | J6: ='P&L'!K5 -> 2030-31 | K6: ='P&L'!L5 -> 2031-32 | L6: ='P&L'!M5 -> 2032-33 | ... N6: ='P&L'!O5 -> 2034-35
B7: 1 | D7: Corporate Sales | E7: ='P&L'!F9 -> 135 | F7: ='P&L'!G9 -> 162 | G7: ='P&L'!H9 -> 202.5 | H7: ='P&L'!I9 -> 253.125 | I7: ='P&L'!J9 -> 316.40625 | J7: ='P&L'!K9 -> 395.50781 | K7: ='P&L'!L9 -> 494.38477 | L7: ='P&L'!M9 -> 617.98096 | ... N7: ='P&L'!O9 -> 965.59525
B8: 2 | D8: Millet Cafeteria | E8: ='P&L'!F11 -> 270 | F8: ='P&L'!G11 -> 792 | G8: ='P&L'!H11 -> 1633.5 | H8: ='P&L'!I11 -> 2874.96 | I8: ='P&L'!J11 -> 4348.377 | J8: ='P&L'!K11 -> 5811.0129 | K8: ='P&L'!L11 -> 7409.0414 | L8: ='P&L'!M11 -> 9304.8844 | ... N8: ='P&L'!O11 -> 13622.122
B9: 3 | D9: Retail Market Sales | E9: ='P&L'!F13 -> 75 | F9: ='P&L'!G13 -> 600 | G9: ='P&L'!H13 -> 1200 | H9: ='P&L'!I13 -> 1800 | I9: ='P&L'!J13 -> 2700 | J9: ='P&L'!K13 -> 3375 | K9: ='P&L'!L13 -> 4218.75 | L9: ='P&L'!M13 -> 5273.4375 | ... N9: ='P&L'!O13 -> 8239.7461
B10: 4 | D10: Export Sales | E10: ='P&L'!F15 -> 150 | F10: ='P&L'!G15 -> 600 | G10: ='P&L'!H15 -> 780 | H10: ='P&L'!I15 -> 1014 | I10: ='P&L'!J15 -> 1318.2 | J10: ='P&L'!K15 -> 1713.66 | K10: ='P&L'!L15 -> 2227.758 | L10: ='P&L'!M15 -> 2896.0854 | ... N10: ='P&L'!O15 -> 4894.3843
B12: SI No. | D12: Trade Receivables Days | E12: =E6 -> 2025-26 | F12: =F6 -> 2026-27 | G12: =G6 -> 2027-28 | H12: =H6 -> 2028-29 | I12: =I6 -> 2029-30 | J12: =J6 -> 2030-31 | K12: =K6 -> 2031-32 | L12: =L6 -> 2032-33 | ... N12: =N6 -> 2034-35
B13: 1 | D13: Corporate Sales | E13: 30 | F13: 30 | G13: 30 | H13: 30 | I13: 30 | J13: 30 | K13: 30 | L13: 30 | M13: 30 | N13: 30
B14: 2 | D14: Millet Cafeteria | E14: 30 | F14: 30 | G14: 30 | H14: 30 | I14: 30 | J14: 30 | K14: 30 | L14: 30 | M14: 30 | N14: 30
B15: 3 | D15: Retail Market Sales | E15: 30 | F15: 30 | G15: 30 | H15: 30 | I15: 30 | J15: 30 | K15: 30 | L15: 30 | M15: 30 | N15: 30
B16: 4 | D16: Export Sales | E16: 30 | F16: 30 | G16: 30 | H16: 30 | I16: 30 | J16: 30 | K16: 30 | L16: 30 | M16: 30 | N16: 30
B18: SI No. | D18: Trade Receivables | E18: =E6 -> 2025-26 | F18: =F6 -> 2026-27 | G18: =G6 -> 2027-28 | H18: =H6 -> 2028-29 | I18: =I6 -> 2029-30 | J18: =J6 -> 2030-31 | K18: =K6 -> 2031-32 | L18: =L6 -> 2032-33 | ... N18: =N6 -> 2034-35
B19: 1 | D19: ='PAG-2'!D9 -> Corporate Sales | E19: =E7*E13/365 -> 11.09589 | F19: =F7*F13/365 -> 13.315068 | G19: =G7*G13/365 -> 16.643836 | H19: =H7*H13/365 -> 20.804795 | I19: =I7*I13/365 -> 26.005993 | J19: =J7*J13/365 -> 32.507491 | K19: =K7*K13/365 -> 40.634364 | L19: =L7*L13/365 -> 50.792955 | ... N19: =N7*N13/365 -> 79.363993
B20: =B19+1 -> 2 | D20: ='PAG-2'!D11 -> Millet Cafeteria | E20: =E8*E14/365 -> 22.191781 | F20: =F8*F14/365 -> 65.09589 | G20: =G8*G14/365 -> 134.26027 | H20: =H8*H14/365 -> 236.29808 | I20: =I8*I14/365 -> 357.40085 | J20: =J8*J14/365 -> 477.6175 | K20: =K8*K14/365 -> 608.96231 | L20: =L8*L14/365 -> 764.78502 | ... N20: =N8*N14/365 -> 1119.6265
B21: =B20+1 -> 3 | D21: ='PAG-2'!D13 -> Retail Market Sales | E21: =E9*E15/365 -> 6.1643836 | F21: =F9*F15/365 -> 49.315068 | G21: =G9*G15/365 -> 98.630137 | H21: =H9*H15/365 -> 147.94521 | I21: =I9*I15/365 -> 221.91781 | J21: =J9*J15/365 -> 277.39726 | K21: =K9*K15/365 -> 346.74658 | L21: =L9*L15/365 -> 433.43322 | ... N21: =N9*N15/365 -> 677.2394
B22: =B21+1 -> 4 | D22: ='PAG-2'!D15 -> Export Sales | E22: =E10*E16/365 -> 12.328767 | F22: =F10*F16/365 -> 49.315068 | G22: =G10*G16/365 -> 64.109589 | H22: =H10*H16/365 -> 83.342466 | I22: =I10*I16/365 -> 108.34521 | J22: =J10*J16/365 -> 140.84877 | K22: =K10*K16/365 -> 183.1034 | L22: =L10*L16/365 -> 238.03442 | ... N22: =N10*N16/365 -> 402.27816
B24: Trade Receivables | E24: =E19+E20+E21+E22 -> 51.780822 | F24: =F19+F20+F21+F22 -> 177.0411 | G24: =G19+G20+G21+G22 -> 313.64384 | H24: =H19+H20+H21+H22 -> 488.39055 | I24: =I19+I20+I21+I22 -> 713.66986 | J24: =J19+J20+J21+J22 -> 928.37102 | K24: =K19+K20+K21+K22 -> 1179.4466 | L24: =L19+L20+L21+L22 -> 1487.0456 | ... N24: =N19+N20+N21+N22 -> 2278.508
D26: Assessment of Trade Payables
B29: SI No. | D29: Direct Cost | E29: =E18 -> 2025-26 | F29: =F18 -> 2026-27 | G29: =G18 -> 2027-28 | H29: =H18 -> 2028-29 | I29: =I18 -> 2029-30 | J29: =J18 -> 2030-31 | K29: =K18 -> 2031-32 | L29: =L18 -> 2032-33 | ... N29: =N18 -> 2034-35
B30: 1 | D30: Total Direct Cost | E30: ='P&L'!F17 -> 272.4 | F30: ='P&L'!G17 -> 1088.94 | G30: ='P&L'!H17 -> 1818.645 | H30: ='P&L'!I17 -> 2682.005 | I30: ='P&L'!J17 -> 3850.5811 | J30: ='P&L'!K17 -> 4947.2554 | K30: ='P&L'!L17 -> 6282.8625 | L30: ='P&L'!M17 -> 7950.0489 | ... N30: ='P&L'!O17 -> 12508.28
B32: SI No. | D32: Trade Payables Days | E32: =E29 -> 2025-26 | F32: =F29 -> 2026-27 | G32: =G29 -> 2027-28 | H32: =H29 -> 2028-29 | I32: =I29 -> 2029-30 | J32: =J29 -> 2030-31 | K32: =K29 -> 2031-32 | L32: =L29 -> 2032-33 | ... N32: =N29 -> 2034-35
B33: 1 | D33: Payables Days | E33: 10 | F33: 10 | G33: 10 | H33: 10 | I33: 10 | J33: 10 | K33: 10 | L33: 10 | M33: 10 | N33: 10
B35: SI No. | D35: Trade Payables | E35: =E29 -> 2025-26 | F35: =F29 -> 2026-27 | G35: =G29 -> 2027-28 | H35: =H29 -> 2028-29 | I35: =I29 -> 2029-30 | J35: =J29 -> 2030-31 | K35: =K29 -> 2031-32 | L35: =L29 -> 2032-33 | ... N35: =N29 -> 2034-35
B36: 1 | D36: Trade Payables | E36: =E30*E33/365 -> 7.4630137 | F36: =F30*F33/365 -> 29.833973 | G36: =G30*G33/365 -> 49.82589 | H36: =H30*H33/365 -> 73.479588 | I36: =I30*I33/365 -> 105.49537 | J36: =J30*J33/365 -> 135.54124 | K36: =K30*K33/365 -> 172.13322 | L36: =L30*L33/365 -> 217.80956 | ... N36: =N30*N33/365 -> 342.6926
B38: Trade Payables | E38: =E36 -> 7.4630137 | F38: =F36 -> 29.833973 | G38: =G36 -> 49.82589 | H38: =H36 -> 73.479588 | I38: =I36 -> 105.49537 | J38: =J36 -> 135.54124 | K38: =K36 -> 172.13322 | L38: =L36 -> 217.80956 | ... N38: =N36 -> 342.6926
D40: Assessment of Inventory
B43: SI No. | D43: Direct Cost | E43: =E32 -> 2025-26 | F43: =F32 -> 2026-27 | G43: =G32 -> 2027-28 | H43: =H32 -> 2028-29 | I43: =I32 -> 2029-30 | J43: =J32 -> 2030-31 | K43: =K32 -> 2031-32 | L43: =L32 -> 2032-33 | ... N43: =N32 -> 2034-35
B44: 1 | D44: Total Direct Cost | E44: ='P&L'!F17 -> 272.4 | F44: ='P&L'!G17 -> 1088.94 | G44: ='P&L'!H17 -> 1818.645 | H44: ='P&L'!I17 -> 2682.005 | I44: ='P&L'!J17 -> 3850.5811 | J44: ='P&L'!K17 -> 4947.2554 | K44: ='P&L'!L17 -> 6282.8625 | L44: ='P&L'!M17 -> 7950.0489 | ... N44: ='P&L'!O17 -> 12508.28
B46: SI No. | D46: Inventory Days | E46: =E43 -> 2025-26 | F46: =F43 -> 2026-27 | G46: =G43 -> 2027-28 | H46: =H43 -> 2028-29 | I46: =I43 -> 2029-30 | J46: =J43 -> 2030-31 | K46: =K43 -> 2031-32 | L46: =L43 -> 2032-33 | ... N46: =N43 -> 2034-35
B47: 1 | D47: =D46 -> Inventory Days | E47: 45 | F47: 45 | G47: 45 | H47: 45 | I47: 45 | J47: 45 | K47: 45 | L47: 45 | M47: 45 | N47: 45
B49: SI No. | D49: Inventory | E49: =E43 -> 2025-26 | F49: =F43 -> 2026-27 | G49: =G43 -> 2027-28 | H49: =H43 -> 2028-29 | I49: =I43 -> 2029-30 | J49: =J43 -> 2030-31 | K49: =K43 -> 2031-32 | L49: =L43 -> 2032-33 | ... N49: =N43 -> 2034-35
B50: 1 | D50: Inventory | E50: =E44*E47/365 -> 33.583562 | F50: =F44*F47/365 -> 134.25288 | G50: =G44*G47/365 -> 224.21651 | H50: =H44*H47/365 -> 330.65814 | I50: =I44*I47/365 -> 474.72918 | J50: =J44*J47/365 -> 609.93559 | K50: =K44*K47/365 -> 774.59949 | L50: =L44*L47/365 -> 980.14301 | ... N50: =N44*N47/365 -> 1542.1167
B52: Inventory | E52: =E50 -> 33.583562 | F52: =F50 -> 134.25288 | G52: =G50 -> 224.21651 | H52: =H50 -> 330.65814 | I52: =I50 -> 474.72918 | J52: =J50 -> 609.93559 | K52: =K50 -> 774.59949 | L52: =L50 -> 980.14301 | ... N52: =N50 -> 1542.1167
D54: Working Capital | E54: =E49 -> 2025-26 | F54: =F49 -> 2026-27 | G54: =G49 -> 2027-28 | H54: =H49 -> 2028-29 | I54: =I49 -> 2029-30 | J54: =J49 -> 2030-31 | K54: =K49 -> 2031-32 | L54: =L49 -> 2032-33 | ... N54: =N49 -> 2034-35
D55: Working Capital | E55: =E24-E38+E52 -> 77.90137 | F55: =F24-F38+F52 -> 281.46 | G55: =G24-G38+G52 -> 488.03445 | H55: =H24-H38+H52 -> 745.5691 | I55: =I24-I38+I52 -> 1082.9037 | J55: =J24-J38+J52 -> 1402.7654 | K55: =K24-K38+K52 -> 1781.9129 | L55: =L24-L38+L52 -> 2249.3791 | ... N55: =N24-N38+N52 -> 3477.9321
D56: Increase in Working Capital | E56: =E55-(Config!C9+Config!C10-Config!G8) -> 68.307524 | F56: =F55-E55 -> 203.55863 | G56: =G55-F55 -> 206.57445 | H56: =H55-G55 -> 257.53465 | I56: =I55-H55 -> 337.33456 | J56: =J55-I55 -> 319.86171 | K56: =K55-J55 -> 379.14755 | L56: =L55-K55 -> 467.46615 | M56: =M55-L55 -> 558.29286 | N56: =N55-M55 -> 670.2602

Sheet Debt Schedule
B2: Debt Schedule
B4: Loans/Debts as on Date | C4: Opening Balance | D4: Loan Rate | E4: Term(Months) | F4: Loan Taken in Month | G4: EMI
B5: Existing Loan on 31st March 2025 | C5: =13706613.83/100000 -> 137.06614 | D5: 0.1 | E5: 120 | F5: 1 | G5: =-PMT(D5/12,E5,C5) -> 1.8113391
B7: Timeline (Months) | C7: 1 | D7: 2 | E7: 3 | F7: 4 | G7: 5 | H7: 6 | I7: 7 | J7: 8 | K7: 9 | L7: 10 | M7: 11 | N7: 12 | O7: 13 | P7: 14 | Q7: 15 | R7: 16 | S7: 17 | T7: 18 | U7: 19 | V7: 20 | W7: 21 | X7: 22 | Y7: 23 | Z7: 24 | AA7: 25 | AB7: 26 | AC7: 27 | AD7: 28 | AE7: 29 | AF7: 30 | AG7: 31 | AH7: 32 | AI7: 33 | AJ7: 34 | AK7: 35 | AL7: 36 | AM7: 37 | AN7: 38 | AO7: 39 | AP7: 40 | AQ7: 41 | AR7: 42 | AS7: 43 | AT7: 44 | AU7: 45 | AV7: 46 | AW7: 47 | AX7: 48 | AY7: 49 | AZ7: 50 | BA7: 51 | BB7: 52 | BC7: 53 | BD7: 54 | BE7: 55 | BF7: 56 | BG7: 57 | BH7: 58 | BI7: 59 | BJ7: 60 | BK7: 61 | BL7: 62 | BM7: 63 | BN7: 64 | BO7: 65 | BP7: 66 | BQ7: 67 | BR7: 68 | BS7: 69 | BT7: 70 | BU7: 71 | BV7: 72 | BW7: 73 | BX7: 74 | BY7: 75 | BZ7: 76 | CA7: 77 | CB7: 78 | CC7: 79 | CD7: 80 | CE7: 81 | CF7: 82 | CG7: 83 | CH7: 84 | CI7: 85 | CJ7: 86 | CK7: 87 | CL7: 88 | CM7: 89 | CN7: 90 | CO7: 91 | CP7: 92 | CQ7: 93 | CR7: 94 | CS7: 95 | CT7: 96 | CU7: 97 | CV7: 98 | CW7: 99 | CX7: 100 | CY7: 101 | CZ7: 102 | DA7: 103 | DB7: 104 | DC7: 105 | DD7: 106 | DE7: 107 | DF7: 108 | DG7: 109 | DH7: 110 | DI7: 111 | DJ7: 112 | DK7: 113 | DL7: 114 | DM7: 115 | DN7: 116 | DO7: 117 | DP7: 118 | DQ7: 119 | DR7: 120
B8: Loan Payments | C8: 1 | D8: 2 | E8: 3 | F8: 4 | G8: 5 | H8: 6 | I8: 7 | J8: 8 | K8: 9 | L8: 10 | M8: 11 | N8: 12 | O8: 13 | P8: 14 | Q8: 15 | R8: 16 | S8: 17 | T8: 18 | U8: 19 | V8: 20 | W8: 21 | X8: 22 | Y8: 23 | Z8: 24 | AA8: 25 | AB8: 26 | AC8: 27 | AD8: 28 | AE8: 29 | AF8: 30 | AG8: 31 | AH8: 32 | AI8: 33 | AJ8: 34 | AK8: 35 | AL8: 36 | AM8: 37 | AN8: 38 | AO8: 39 | AP8: 40 | AQ8: 41 | AR8: 42 | AS8: 43 | AT8: 44 | AU8: 45 | AV8: 46 | AW8: 47 | AX8: 48 | AY8: 49 | AZ8: 50 | BA8: 51 | BB8: 52 | BC8: 53 | BD8: 54 | BE8: 55 | BF8: 56 | BG8: 57 | BH8: 58 | BI8: 59 | BJ8: 60 | BK8: 61 | BL8: 62 | BM8: 63 | BN8: 64 | BO8: 65 | BP8: 66 | BQ8: 67 | BR8: 68 | BS8: 69 | BT8: 70 | BU8: 71 | BV8: 72 | BW8: 73 | BX8: 74 | BY8: 75 | BZ8: 76 | CA8: 77 | CB8: 78 | CC8: 79 | CD8: 80 | CE8: 81 | CF8: 82 | CG8: 83 | CH8: 84 | CI8: 85 | CJ8: 86 | CK8: 87 | CL8: 88 | CM8: 89 | CN8: 90 | CO8: 91 | CP8: 92 | CQ8: 93 | CR8: 94 | CS8: 95 | CT8: 96 | CU8: 97 | CV8: 98 | CW8: 99 | CX8: 100 | CY8: 101 | CZ8: 102 | DA8: 103 | DB8: 104 | DC8: 105 | DD8: 106 | DE8: 107 | DF8: 108 | DG8: 109 | DH8: 110 | DI8: 111 | DJ8: 112 | DK8: 113 | DL8: 114 | DM8: 115 | DN8: 116 | DO8: 117 | DP8: 118 | DQ8: 119 | DR8: 120
B9: Principal Paid | C9: =-IFERROR(PPMT($D$5/12,C8,$E$5,$C$5),0) -> 0.6691213 | D9: =-IFERROR(PPMT($D$5/12,D8,$E$5,$C$5),0) -> 0.67469731 | E9: =-IFERROR(PPMT($D$5/12,E8,$E$5,$C$5),0) -> 0.68031979 | F9: =-IFERROR(PPMT($D$5/12,F8,$E$5,$C$5),0) -> 0.68598912 | G9: =-IFERROR(PPMT($D$5/12,G8,$E$5,$C$5),0) -> 0.69170569 | H9: =-IFERROR(PPMT($D$5/12,H8,$E$5,$C$5),0) -> 0.69746991 | I9: =-IFERROR(PPMT($D$5/12,I8,$E$5,$C$5),0) -> 0.70328216 | J9: =-IFERROR(PPMT($D$5/12,J8,$E$5,$C$5),0) -> 0.70914284 | ... DR9: =-IFERROR(PPMT($D$5/12,DR8,$E$5,$C$5),0) -> 1.7963694
B10: Interest Paid | C10: =-IFERROR(IPMT($D$5/12,C8,$E$5,$C$5),0) -> 1.1422178 | D10: =-IFERROR(IPMT($D$5/12,D8,$E$5,$C$5),0) -> 1.1366418 | E10: =-IFERROR(IPMT($D$5/12,E8,$E$5,$C$5),0) -> 1.1310193 | F10: =-IFERROR(IPMT($D$5/12,F8,$E$5,$C$5),0) -> 1.12535 | G10: =-IFERROR(IPMT($D$5/12,G8,$E$5,$C$5),0) -> 1.1196334 | H10: =-IFERROR(IPMT($D$5/12,H8,$E$5,$C$5),0) -> 1.1138692 | I10: =-IFERROR(IPMT($D$5/12,I8,$E$5,$C$5),0) -> 1.108057 | J10: =-IFERROR(IPMT($D$5/12,J8,$E$5,$C$5),0) -> 1.1021963 | ... DR10: =-IFERROR(IPMT($D$5/12,DR8,$E$5,$C$5),0) -> 0.014969745
B11: Total Loan Payment | C11: =C9+C10 -> 1.8113391 | D11: =D9+D10 -> 1.8113391 | E11: =E9+E10 -> 1.8113391 | F11: =F9+F10 -> 1.8113391 | G11: =G9+G10 -> 1.8113391 | H11: =H9+H10 -> 1.8113391 | I11: =I9+I10 -> 1.8113391 | J11: =J9+J10 -> 1.8113391 | ... DR11: =DR9+DR10 -> 1.8113391
B12: Loan Balance | C12: =IF(C7=F5,C5-C9,0) -> 136.39702 | D12: =IF(D7=$F$5,$C$5-D9,C12-D9) -> 135.72232 | E12: =IF(E7=$F$5,$C$5-E9,D12-E9) -> 135.042 | F12: =IF(F7=$F$5,$C$5-F9,E12-F9) -> 134.35601 | G12: =IF(G7=$F$5,$C$5-G9,F12-G9) -> 133.66431 | H12: =IF(H7=$F$5,$C$5-H9,G12-H9) -> 132.96684 | I12: =IF(I7=$F$5,$C$5-I9,H12-I9) -> 132.26355 | J12: =IF(J7=$F$5,$C$5-J9,I12-J9) -> 131.55441 | K12: =IF(K7=$F$5,$C$5-K9,J12-K9) -> 130.83936 | ... DR12: =IF(DR7=$F$5,$C$5-DR9,DQ12-DR9) -> 2.4646951e-14
B13: Current Liability | C13: =IF(C12=0,0,SUM(D9:O9)) -> 8.477955 | D13: =IF(D12=0,0,SUM(E9:P9)) -> 8.5486046 | E13: =IF(E12=0,0,SUM(F9:Q9)) -> 8.619843 | F13: =IF(F12=0,0,SUM(G9:R9)) -> 8.691675 | G13: =IF(G12=0,0,SUM(H9:S9)) -> 8.7641056 | H13: =IF(H12=0,0,SUM(I9:T9)) -> 8.8371398 | I13: =IF(I12=0,0,SUM(J9:U9)) -> 8.9107827 | J13: =IF(J12=0,0,SUM(K9:V9)) -> 8.9850392 | ... DR13: =IF(DR12=0,0,SUM(DS9:ED9)) -> 0
B14: Long-Term Liability | C14: =IF(C12-C13<0,0,C12-C13) -> 127.91906 | D14: =IF(D12-D13<0,0,D12-D13) -> 127.17372 | E14: =IF(E12-E13<0,0,E12-E13) -> 126.42216 | F14: =IF(F12-F13<0,0,F12-F13) -> 125.66434 | G14: =IF(G12-G13<0,0,G12-G13) -> 124.9002 | H14: =IF(H12-H13<0,0,H12-H13) -> 124.1297 | I14: =IF(I12-I13<0,0,I12-I13) -> 123.35277 | J14: =IF(J12-J13<0,0,J12-J13) -> 122.56937 | ... DR14: =IF(DR12-DR13<0,0,DR12-DR13) -> 2.4646951e-14
B16: Loans/Debts as on Date | C16: Opening Balance | D16: Loan Rate | E16: Term(Months) | F16: Loan Taken in Month | G16: EMI
B17: Loan 1 | C17: 267 | D17: 0.117 | E17: 72 | F17: 1 | G17: =-PMT(D17/12,E17,C17) -> 5.1783411
B19: Timeline (Months) | C19: 1 | D19: 2 | E19: 3 | F19: 4 | G19: 5 | H19: 6 | I19: 7 | J19: 8 | K19: 9 | L19: 10 | M19: 11 | N19: 12 | O19: 13 | P19: 14 | Q19: 15 | R19: 16 | S19: 17 | T19: 18 | U19: 19 | V19: 20 | W19: 21 | X19: 22 | Y19: 23 | Z19: 24 | AA19: 25 | AB19: 26 | AC19: 27 | AD19: 28 | AE19: 29 | AF19: 30 | AG19: 31 | AH19: 32 | AI19: 33 | AJ19: 34 | AK19: 35 | AL19: 36 | AM19: 37 | AN19: 38 | AO19: 39 | AP19: 40 | AQ19: 41 | AR19: 42 | AS19: 43 | AT19: 44 | AU19: 45 | AV19: 46 | AW19: 47 | AX19: 48 | AY19: 49 | AZ19: 50 | BA19: 51 | BB19: 52 | BC19: 53 | BD19: 54 | BE19: 55 | BF19: 56 | BG19: 57 | BH19: 58 | BI19: 59 | BJ19: 60 | BK19: 61 | BL19: 62 | BM19: 63 | BN19: 64 | BO19: 65 | BP19: 66 | BQ19: 67 | BR19: 68 | BS19: 69 | BT19: 70 | BU19: 71 | BV19: 72 | BW19: 73 | BX19: 74 | BY19: 75 | BZ19: 76 | CA19: 77 | CB19: 78 | CC19: 79 | CD19: 80 | CE19: 81 | CF19: 82 | CG19: 83 | CH19: 84 | CI19: 85 | CJ19: 86 | CK19: 87 | CL19: 88 | CM19: 89 | CN19: 90 | CO19: 91 | CP19: 92 | CQ19: 93 | CR19: 94 | CS19: 95 | CT19: 96 | CU19: 97 | CV19: 98 | CW19: 99 | CX19: 100 | CY19: 101 | CZ19: 102 | DA19: 103 | DB19: 104 | DC19: 105 | DD19: 106 | DE19: 107 | DF19: 108 | DG19: 109 | DH19: 110 | DI19: 111 | DJ19: 112 | DK19: 113 | DL19: 114 | DM19: 115 | DN19: 116 | DO19: 117 | DP19: 118 | DQ19: 119 | DR19: 120
B20: Loan Payments | C20: 1 | D20: 2 | E20: 3 | F20: 4 | G20: 5 | H20: 6 | I20: 7 | J20: 8 | K20: 9 | L20: 10 | M20: 11 | N20: 12 | O20: 13 | P20: 14 | Q20: 15 | R20: 16 | S20: 17 | T20: 18 | U20: 19 | V20: 20 | W20: 21 | X20: 22 | Y20: 23 | Z20: 24 | AA20: 25 | AB20: 26 | AC20: 27 | AD20: 28 | AE20: 29 | AF20: 30 | AG20: 31 | AH20: 32 | AI20: 33 | AJ20: 34 | AK20: 35 | AL20: 36 | AM20: 37 | AN20: 38 | AO20: 39 | AP20: 40 | AQ20: 41 | AR20: 42 | AS20: 43 | AT20: 44 | AU20: 45 | AV20: 46 | AW20: 47 | AX20: 48 | AY20: 49 | AZ20: 50 | BA20: 51 | BB20: 52 | BC20: 53 | BD20: 54 | BE20: 55 | BF20: 56 | BG20: 57 | BH20: 58 | BI20: 59 | BJ20: 60 | BK20: 61 | BL20: 62 | BM20: 63 | BN20: 64 | BO20: 65 | BP20: 66 | BQ20: 67 | BR20: 68 | BS20: 69 | BT20: 70 | BU20: 71 | BV20: 72 | BW20: 73 | BX20: 74 | BY20: 75 | BZ20: 76 | CA20: 77 | CB20: 78 | CC20: 79 | CD20: 80 | CE20: 81 | CF20: 82 | CG20: 83 | CH20: 84 | CI20: 85 | CJ20: 86 | CK20: 87 | CL20: 88 | CM20: 89 | CN20: 90 | CO20: 91 | CP20: 92 | CQ20: 93 | CR20: 94 | CS20: 95 | CT20: 96 | CU20: 97 | CV20: 98 | CW20: 99 | CX20: 100 | CY20: 101 | CZ20: 102 | DA20: 103 | DB20: 104 | DC20: 105 | DD20: 106 | DE20: 107 | DF20: 108 | DG20: 109 | DH20: 110 | DI20: 111 | DJ20: 112 | DK20: 113 | DL20: 114 | DM20: 115 | DN20: 116 | DO20: 117 | DP20: 118 | DQ20: 119 | DR20: 120
B21: Principal Paid | C21: =-IFERROR(PPMT($D$17/12,C20,$E$17,$C$17),0) -> 2.5750911 | D21: =-IFERROR(PPMT($D$17/12,D20,$E$17,$C$17),0) -> 2.6001983 | E21: =-IFERROR(PPMT($D$17/12,E20,$E$17,$C$17),0) -> 2.6255502 | F21: =-IFERROR(PPMT($D$17/12,F20,$E$17,$C$17),0) -> 2.6511493 | G21: =-IFERROR(PPMT($D$17/12,G20,$E$17,$C$17),0) -> 2.676998 | H21: =-IFERROR(PPMT($D$17/12,H20,$E$17,$C$17),0) -> 2.7030988 | I21: =-IFERROR(PPMT($D$17/12,I20,$E$17,$C$17),0) -> 2.729454 | J21: =-IFERROR(PPMT($D$17/12,J20,$E$17,$C$17),0) -> 2.7560662 | ... DR21: =-IFERROR(PPMT($D$17/12,DR20,$E$17,$C$17),0) -> 0
B22: Interest Paid | C22: =-IFERROR(IPMT($D$17/12,C20,$E$17,$C$17),0) -> 2.60325 | D22: =-IFERROR(IPMT($D$17/12,D20,$E$17,$C$17),0) -> 2.5781429 | E22: =-IFERROR(IPMT($D$17/12,E20,$E$17,$C$17),0) -> 2.5527909 | F22: =-IFERROR(IPMT($D$17/12,F20,$E$17,$C$17),0) -> 2.5271918 | G22: =-IFERROR(IPMT($D$17/12,G20,$E$17,$C$17),0) -> 2.5013431 | H22: =-IFERROR(IPMT($D$17/12,H20,$E$17,$C$17),0) -> 2.4752424 | I22: =-IFERROR(IPMT($D$17/12,I20,$E$17,$C$17),0) -> 2.4488872 | J22: =-IFERROR(IPMT($D$17/12,J20,$E$17,$C$17),0) -> 2.422275 | ... DR22: =-IFERROR(IPMT($D$17/12,DR20,$E$17,$C$17),0) -> 0
B23: Total Loan Payment | C23: =C21+C22 -> 5.1783411 | D23: =D21+D22 -> 5.1783411 | E23: =E21+E22 -> 5.1783411 | F23: =F21+F22 -> 5.1783411 | G23: =G21+G22 -> 5.1783411 | H23: =H21+H22 -> 5.1783411 | I23: =I21+I22 -> 5.1783411 | J23: =J21+J22 -> 5.1783411 | ... DR23: =DR21+DR22 -> 0
B24: Loan Balance | C24: =IF(C19=F17,C17-C21,0) -> 264.42491 | D24: =IF(D19=$F$17,$C$17-D21,C24-D21) -> 261.82471 | E24: =IF(E19=$F$17,$C$17-E21,D24-E21) -> 259.19916 | F24: =IF(F19=$F$17,$C$17-F21,E24-F21) -> 256.54801 | G24: =IF(G19=$F$17,$C$17-G21,F24-G21) -> 253.87101 | H24: =IF(H19=$F$17,$C$17-H21,G24-H21) -> 251.16791 | I24: =IF(I19=$F$17,$C$17-I21,H24-I21) -> 248.43846 | J24: =IF(J19=$F$17,$C$17-J21,I24-J21) -> 245.68239 | K24: =IF(K19=$F$17,$C$17-K21,J24-K21) -> 242.89946 | ... DR24: =IF(DR19=$F$17,$C$17-DR21,DQ24-DR21) -> -3.8191672e-14
B25: Current Liability | C25: =IF(C24=0,0,SUM(D21:O21)) -> 32.931199 | D25: =IF(D24=0,0,SUM(E21:P21)) -> 33.252278 | E25: =IF(E24=0,0,SUM(F21:Q21)) -> 33.576488 | F25: =IF(F24=0,0,SUM(G21:R21)) -> 33.903858 | G25: =IF(G24=0,0,SUM(H21:S21)) -> 34.234421 | H25: =IF(H24=0,0,SUM(I21:T21)) -> 34.568207 | I25: =IF(I24=0,0,SUM(J21:U21)) -> 34.905247 | J25: =IF(J24=0,0,SUM(K21:V21)) -> 35.245573 | ... DR25: =IF(DR24=0,0,SUM(DS21:ED21)) -> 0
B26: Long-Term Liability | C26: =IF(C24-C25<0,0,C24-C25) -> 231.49371 | D26: =IF(D24-D25<0,0,D24-D25) -> 228.57243 | E26: =IF(E24-E25<0,0,E24-E25) -> 225.62267 | F26: =IF(F24-F25<0,0,F24-F25) -> 222.64415 | G26: =IF(G24-G25<0,0,G24-G25) -> 219.63659 | H26: =IF(H24-H25<0,0,H24-H25) -> 216.59971 | I26: =IF(I24-I25<0,0,I24-I25) -> 213.53321 | J26: =IF(J24-J25<0,0,J24-J25) -> 210.43682 | ... DR26: =IF(DR24-DR25<0,0,DR24-DR25) -> 0
B28: Loans/Debts as on Date | C28: Opening Balance | D28: Loan Rate | E28: Term(Months) | F28: Loan Taken in Month | G28: EMI
B29: Loan 2 | C29: 7.16 | D29: 0.108 | E29: 60 | F29: 1 | G29: =-PMT(D29/12,E29,C29) -> 0.15496255
B31: Timeline (Months) | C31: 1 | D31: 2 | E31: 3 | F31: 4 | G31: 5 | H31: 6 | I31: 7 | J31: 8 | K31: 9 | L31: 10 | M31: 11 | N31: 12 | O31: 13 | P31: 14 | Q31: 15 | R31: 16 | S31: 17 | T31: 18 | U31: 19 | V31: 20 | W31: 21 | X31: 22 | Y31: 23 | Z31: 24 | AA31: 25 | AB31: 26 | AC31: 27 | AD31: 28 | AE31: 29 | AF31: 30 | AG31: 31 | AH31: 32 | AI31: 33 | AJ31: 34 | AK31: 35 | AL31: 36 | AM31: 37 | AN31: 38 | AO31: 39 | AP31: 40 | AQ31: 41 | AR31: 42 | AS31: 43 | AT31: 44 | AU31: 45 | AV31: 46 | AW31: 47 | AX31: 48 | AY31: 49 | AZ31: 50 | BA31: 51 | BB31: 52 | BC31: 53 | BD31: 54 | BE31: 55 | BF31: 56 | BG31: 57 | BH31: 58 | BI31: 59 | BJ31: 60
B32: Loan Payments | C32: =IF(C31=F29,1,0) -> 1 | D32: =IF(AND(C32=0,D31<>$F$29),0,C32+1) -> 2 | E32: =IF(AND(D32=0,E31<>$F$29),0,D32+1) -> 3 | F32: =IF(AND(E32=0,F31<>$F$29),0,E32+1) -> 4 | G32: =IF(AND(F32=0,G31<>$F$29),0,F32+1) -> 5 | H32: =IF(AND(G32=0,H31<>$F$29),0,G32+1) -> 6 | I32: =IF(AND(H32=0,I31<>$F$29),0,H32+1) -> 7 | J32: =IF(AND(I32=0,J31<>$F$29),0,I32+1) -> 8 | K32: =IF(AND(J32=0,K31<>$F$29),0,J32+1) -> 9 | ... BJ32: =IF(AND(BI32=0,BJ31<>$F$29),0,BI32+1) -> 60
B33: Principal Paid | C33: =-IFERROR(PPMT($D$29/12,C32,$E$29,$C$29),0) -> 0.09052255 | D33: =-IFERROR(PPMT($D$29/12,D32,$E$29,$C$29),0) -> 0.091337253 | E33: =-IFERROR(PPMT($D$29/12,E32,$E$29,$C$29),0) -> 0.092159289 | F33: =-IFERROR(PPMT($D$29/12,F32,$E$29,$C$29),0) -> 0.092988722 | G33: =-IFERROR(PPMT($D$29/12,G32,$E$29,$C$29),0) -> 0.093825621 | H33: =-IFERROR(PPMT($D$29/12,H32,$E$29,$C$29),0) -> 0.094670051 | I33: =-IFERROR(PPMT($D$29/12,I32,$E$29,$C$29),0) -> 0.095522082 | J33: =-IFERROR(PPMT($D$29/12,J32,$E$29,$C$29),0) -> 0.09638178 | ... BJ33: =-IFERROR(PPMT($D$29/12,BJ32,$E$29,$C$29),0) -> 0.15358033
B34: Interest Paid | C34: =-IFERROR(IPMT($D$29/12,C32,$E$29,$C$29),0) -> 0.06444 | D34: =-IFERROR(IPMT($D$29/12,D32,$E$29,$C$29),0) -> 0.063625297 | E34: =-IFERROR(IPMT($D$29/12,E32,$E$29,$C$29),0) -> 0.062803262 | F34: =-IFERROR(IPMT($D$29/12,F32,$E$29,$C$29),0) -> 0.061973828 | G34: =-IFERROR(IPMT($D$29/12,G32,$E$29,$C$29),0) -> 0.06113693 | H34: =-IFERROR(IPMT($D$29/12,H32,$E$29,$C$29),0) -> 0.060292499 | I34: =-IFERROR(IPMT($D$29/12,I32,$E$29,$C$29),0) -> 0.059440469 | J34: =-IFERROR(IPMT($D$29/12,J32,$E$29,$C$29),0) -> 0.05858077 | ... BJ34: =-IFERROR(IPMT($D$29/12,BJ32,$E$29,$C$29),0) -> 0.0013822229
B35: Total Loan Payment | C35: =C33+C34 -> 0.15496255 | D35: =D33+D34 -> 0.15496255 | E35: =E33+E34 -> 0.15496255 | F35: =F33+F34 -> 0.15496255 | G35: =G33+G34 -> 0.15496255 | H35: =H33+H34 -> 0.15496255 | I35: =I33+I34 -> 0.15496255 | J35: =J33+J34 -> 0.15496255 | ... BJ35: =BJ33+BJ34 -> 0.15496255
B36: Loan Balance | C36: =IF(C31=F29,C29-C33,0) -> 7.0694774 | D36: =IF(D31=$F$29,$C$29-D33,C36-D33) -> 6.9781402 | E36: =IF(E31=$F$29,$C$29-E33,D36-E33) -> 6.8859809 | F36: =IF(F31=$F$29,$C$29-F33,E36-F33) -> 6.7929922 | G36: =IF(G31=$F$29,$C$29-G33,F36-G33) -> 6.6991666 | H36: =IF(H31=$F$29,$C$29-H33,G36-H33) -> 6.6044965 | I36: =IF(I31=$F$29,$C$29-I33,H36-I33) -> 6.5089744 | J36: =IF(J31=$F$29,$C$29-J33,I36-J33) -> 6.4125927 | K36: =IF(K31=$F$29,$C$29-K33,J36-K33) -> 6.3153434 | ... BJ36: =IF(BJ31=$F$29,$C$29-BJ33,BI36-BJ33) -> -2.3037128e-15
B37: Current Liability | C37: =IF(C36=0,0,SUM(D33:O33)) -> 1.1519624 | D37: =IF(D36=0,0,SUM(E33:P33)) -> 1.1623301 | E37: =IF(E36=0,0,SUM(F33:Q33)) -> 1.1727911 | F37: =IF(F36=0,0,SUM(G33:R33)) -> 1.1833462 | G37: =IF(G36=0,0,SUM(H33:S33)) -> 1.1939963 | H37: =IF(H36=0,0,SUM(I33:T33)) -> 1.2047423 | I37: =IF(I36=0,0,SUM(J33:U33)) -> 1.215585 | J37: =IF(J36=0,0,SUM(K33:V33)) -> 1.2265252 | ... BJ37: =IF(BJ36=0,0,SUM(BK33:BV33)) -> 0
B38: Long-Term Liability | C38: =IF(C36-C37<0,0,C36-C37) -> 5.917515 | D38: =IF(D36-D37<0,0,D36-D37) -> 5.8158101 | E38: =IF(E36-E37<0,0,E36-E37) -> 5.7131898 | F38: =IF(F36-F37<0,0,F36-F37) -> 5.609646 | G38: =IF(G36-G37<0,0,G36-G37) -> 5.5051703 | H38: =IF(H36-H37<0,0,H36-H37) -> 5.3997542 | I38: =IF(I36-I37<0,0,I36-I37) -> 5.2933895 | J38: =IF(J36-J37<0,0,J36-J37) -> 5.1860674 | ... BJ38: =IF(BJ36-BJ37<0,0,BJ36-BJ37) -> 0
B40: Loans/Debts as on Date | C40: Opening Balance | D40: Loan Rate | E40: Term(Months) | F40: Loan Taken in Month | G40: EMI
B41: Loan 3 | C41: 2500 | D41: 0.06 | E41: 120 | F41: 1 | G41: =-PMT(D41/12,E41,C41) -> 27.755125
B43: Timeline (Months) | C43: 1 | D43: 2 | E43: 3 | F43: 4 | G43: 5 | H43: 6 | I43: 7 | J43: 8 | K43: 9 | L43: 10 | M43: 11 | N43: 12 | O43: 13 | P43: 14 | Q43: 15 | R43: 16 | S43: 17 | T43: 18 | U43: 19 | V43: 20 | W43: 21 | X43: 22 | Y43: 23 | Z43: 24 | AA43: 25 | AB43: 26 | AC43: 27 | AD43: 28 | AE43: 29 | AF43: 30 | AG43: 31 | AH43: 32 | AI43: 33 | AJ43: 34 | AK43: 35 | AL43: 36 | AM43: 37 | AN43: 38 | AO43: 39 | AP43: 40 | AQ43: 41 | AR43: 42 | AS43: 43 | AT43: 44 | AU43: 45 | AV43: 46 | AW43: 47 | AX43: 48 | AY43: 49 | AZ43: 50 | BA43: 51 | BB43: 52 | BC43: 53 | BD43: 54 | BE43: 55 | BF43: 56 | BG43: 57 | BH43: 58 | BI43: 59 | BJ43: 60 | BK43: 61 | BL43: 62 | BM43: 63 | BN43: 64 | BO43: 65 | BP43: 66 | BQ43: 67 | BR43: 68 | BS43: 69 | BT43: 70 | BU43: 71 | BV43: 72 | BW43: 73 | BX43: 74 | BY43: 75 | BZ43: 76 | CA43: 77 | CB43: 78 | CC43: 79 | CD43: 80 | CE43: 81 | CF43: 82 | CG43: 83 | CH43: 84 | CI43: 85 | CJ43: 86 | CK43: 87 | CL43: 88 | CM43: 89 | CN43: 90 | CO43: 91 | CP43: 92 | CQ43: 93 | CR43: 94 | CS43: 95 | CT43: 96 | CU43: 97 | CV43: 98 | CW43: 99 | CX43: 100 | CY43: 101 | CZ43: 102 | DA43: 103 | DB43: 104 | DC43: 105 | DD43: 106 | DE43: 107 | DF43: 108 | DG43: 109 | DH43: 110 | DI43: 111 | DJ43: 112 | DK43: 113 | DL43: 114 | DM43: 115 | DN43: 116 | DO43: 117 | DP43: 118 | DQ43: 119 | DR43: 120
B44: Loan Payments | C44: 1 | D44: 2 | E44: 3 | F44: 4 | G44: 5 | H44: 6 | I44: 7 | J44: 8 | K44: 9 | L44: 10 | M44: 11 | N44: 12 | O44: 13 | P44: 14 | Q44: 15 | R44: 16 | S44: 17 | T44: 18 | U44: 19 | V44: 20 | W44: 21 | X44: 22 | Y44: 23 | Z44: 24 | AA44: 25 | AB44: 26 | AC44: 27 | AD44: 28 | AE44: 29 | AF44: 30 | AG44: 31 | AH44: 32 | AI44: 33 | AJ44: 34 | AK44: 35 | AL44: 36 | AM44: 37 | AN44: 38 | AO44: 39 | AP44: 40 | AQ44: 41 | AR44: 42 | AS44: 43 | AT44: 44 | AU44: 45 | AV44: 46 | AW44: 47 | AX44: 48 | AY44: 49 | AZ44: 50 | BA44: 51 | BB44: 52 | BC44: 53 | BD44: 54 | BE44: 55 | BF44: 56 | BG44: 57 | BH44: 58 | BI44: 59 | BJ44: 60 | BK44: 61 | BL44: 62 | BM44: 63 | BN44: 64 | BO44: 65 | BP44: 66 | BQ44: 67 | BR44: 68 | BS44: 69 | BT44: 70 | BU44: 71 | BV44: 72 | BW44: 73 | BX44: 74 | BY44: 75 | BZ44: 76 | CA44: 77 | CB44: 78 | CC44: 79 | CD44: 80 | CE44: 81 | CF44: 82 | CG44: 83 | CH44: 84 | CI44: 85 | CJ44: 86 | CK44: 87 | CL44: 88 | CM44: 89 | CN44: 90 | CO44: 91 | CP44: 92 | CQ44: 93 | CR44: 94 | CS44: 95 | CT44: 96 | CU44: 97 | CV44: 98 | CW44: 99 | CX44: 100 | CY44: 101 | CZ44: 102 | DA44: 103 | DB44: 104 | DC44: 105 | DD44: 106 | DE44: 107 | DF44: 108 | DG44: 109 | DH44: 110 | DI44: 111 | DJ44: 112 | DK44: 113 | DL44: 114 | DM44: 115 | DN44: 116 | DO44: 117 | DP44: 118 | DQ44: 119 | DR44: 120
B45: Principal Paid | C45: =-IFERROR(PPMT($D$41/12,C44,$E$41,$C$41),0) -> 15.255125 | D45: =-IFERROR(PPMT($D$41/12,D44,$E$41,$C$41),0) -> 15.331401 | E45: =-IFERROR(PPMT($D$41/12,E44,$E$41,$C$41),0) -> 15.408058 | F45: =-IFERROR(PPMT($D$41/12,F44,$E$41,$C$41),0) -> 15.485098 | G45: =-IFERROR(PPMT($D$41/12,G44,$E$41,$C$41),0) -> 15.562524 | H45: =-IFERROR(PPMT($D$41/12,H44,$E$41,$C$41),0) -> 15.640337 | I45: =-IFERROR(PPMT($D$41/12,I44,$E$41,$C$41),0) -> 15.718538 | J45: =-IFERROR(PPMT($D$41/12,J44,$E$41,$C$41),0) -> 15.797131 | ... DR45: =-IFERROR(PPMT($D$41/12,DR44,$E$41,$C$41),0) -> 27.61704
B46: Interest Paid | C46: =-IFERROR(IPMT($D$41/12,C45,$E$41,$C$41),0) -> 11.375904 | D46: =-IFERROR(IPMT($D$41/12,D45,$E$41,$C$41),0) -> 11.369671 | E46: =-IFERROR(IPMT($D$41/12,E45,$E$41,$C$41),0) -> 11.363405 | F46: =-IFERROR(IPMT($D$41/12,F45,$E$41,$C$41),0) -> 11.357106 | G46: =-IFERROR(IPMT($D$41/12,G45,$E$41,$C$41),0) -> 11.350772 | H46: =-IFERROR(IPMT($D$41/12,H45,$E$41,$C$41),0) -> 11.344405 | I46: =-IFERROR(IPMT($D$41/12,I45,$E$41,$C$41),0) -> 11.338003 | J46: =-IFERROR(IPMT($D$41/12,J45,$E$41,$C$41),0) -> 11.331566 | ... DR46: =-IFERROR(IPMT($D$41/12,DR45,$E$41,$C$41),0) -> 10.334252
B47: Total Loan Payment | C47: =C45+C46 -> 26.631029 | D47: =D45+D46 -> 26.701072 | E47: =E45+E46 -> 26.771464 | F47: =F45+F46 -> 26.842204 | G47: =G45+G46 -> 26.913296 | H47: =H45+H46 -> 26.984741 | I47: =I45+I46 -> 27.056541 | J47: =J45+J46 -> 27.128697 | ... DR47: =DR45+DR46 -> 37.951292
B48: Loan Balance | C48: =IF(C43=F41,C41-C45,0) -> 2484.7449 | D48: =IF(D43=$F$41,$C$41-D45,C48-D45) -> 2469.4135 | E48: =IF(E43=$F$41,$C$41-E45,D48-E45) -> 2454.0054 | F48: =IF(F43=$F$41,$C$41-F45,E48-F45) -> 2438.5203 | G48: =IF(G43=$F$41,$C$41-G45,F48-G45) -> 2422.9578 | H48: =IF(H43=$F$41,$C$41-H45,G48-H45) -> 2407.3175 | I48: =IF(I43=$F$41,$C$41-I45,H48-I45) -> 2391.5989 | J48: =IF(J43=$F$41,$C$41-J45,I48-J45) -> 2375.8018 | K48: =IF(K43=$F$41,$C$41-K45,J48-K45) -> 2359.9257 | ... DR48: =IF(DR43=$F$41,$C$41-DR45,DQ48-DR45) -> 1.2789769e-13
B49: Current Liability | C49: =IF(C48=0,0,SUM(D45:O45)) -> 189.12145 | D49: =IF(D48=0,0,SUM(E45:P45)) -> 190.06706 | E49: =IF(E48=0,0,SUM(F45:Q45)) -> 191.0174 | F49: =IF(F48=0,0,SUM(G45:R45)) -> 191.97248 | G49: =IF(G48=0,0,SUM(H45:S45)) -> 192.93235 | H49: =IF(H48=0,0,SUM(I45:T45)) -> 193.89701 | I49: =IF(I48=0,0,SUM(J45:U45)) -> 194.86649 | J49: =IF(J48=0,0,SUM(K45:V45)) -> 195.84083 | ... DR49: =IF(DR48=0,0,SUM(DS45:ED45)) -> 0
B50: Long-Term Liability | C50: =IF(C48-C49<0,0,C48-C49) -> 2295.6234 | D50: =IF(D48-D49<0,0,D48-D49) -> 2279.3464 | E50: =IF(E48-E49<0,0,E48-E49) -> 2262.988 | F50: =IF(F48-F49<0,0,F48-F49) -> 2246.5478 | G50: =IF(G48-G49<0,0,G48-G49) -> 2230.0254 | H50: =IF(H48-H49<0,0,H48-H49) -> 2213.4204 | I50: =IF(I48-I49<0,0,I48-I49) -> 2196.7324 | J50: =IF(J48-J49<0,0,J48-J49) -> 2179.961 | ... DR50: =IF(DR48-DR49<0,0,DR48-DR49) -> 1.2789769e-13
B52: Loan Summary
B54: Timeline (Months) | C54: 1 | D54: 2 | E54: 3 | F54: 4 | G54: 5 | H54: 6 | I54: 7 | J54: 8 | K54: 9 | L54: 10 | M54: 11 | N54: 12 | O54: 13 | P54: 14 | Q54: 15 | R54: 16 | S54: 17 | T54: 18 | U54: 19 | V54: 20 | W54: 21 | X54: 22 | Y54: 23 | Z54: 24 | AA54: 25 | AB54: 26 | AC54: 27 | AD54: 28 | AE54: 29 | AF54: 30 | AG54: 31 | AH54: 32 | AI54: 33 | AJ54: 34 | AK54: 35 | AL54: 36 | AM54: 37 | AN54: 38 | AO54: 39 | AP54: 40 | AQ54: 41 | AR54: 42 | AS54: 43 | AT54: 44 | AU54: 45 | AV54: 46 | AW54: 47 | AX54: 48 | AY54: 49 | AZ54: 50 | BA54: 51 | BB54: 52 | BC54: 53 | BD54: 54 | BE54: 55 | BF54: 56 | BG54: 57 | BH54: 58 | BI54: 59 | BJ54: 60 | BK54: 61 | BL54: 62 | BM54: 63 | BN54: 64 | BO54: 65 | BP54: 66 | BQ54: 67 | BR54: 68 | BS54: 69 | BT54: 70 | BU54: 71 | BV54: 72 | BW54: 73 | BX54: 74 | BY54: 75 | BZ54: 76 | CA54: 77 | CB54: 78 | CC54: 79 | CD54: 80 | CE54: 81 | CF54: 82 | CG54: 83 | CH54: 84 | CI54: 85 | CJ54: 86 | CK54: 87 | CL54: 88 | CM54: 89 | CN54: 90 | CO54: 91 | CP54: 92 | CQ54: 93 | CR54: 94 | CS54: 95 | CT54: 96 | CU54: 97 | CV54: 98 | CW54: 99 | CX54: 100 | CY54: 101 | CZ54: 102 | DA54: 103 | DB54: 104 | DC54: 105 | DD54: 106 | DE54: 107 | DF54: 108 | DG54: 109 | DH54: 110 | DI54: 111 | DJ54: 112 | DK54: 113 | DL54: 114 | DM54: 115 | DN54: 116 | DO54: 117 | DP54: 118 | DQ54: 119 | DR54: 120
B55: Principal Paid | C55: =C21+C33+C45+C9 -> 18.58986 | D55: =D21+D33+D45+D9 -> 18.697634 | E55: =E21+E33+E45+E9 -> 18.806087 | F55: =F21+F33+F45+F9 -> 18.915226 | G55: =G21+G33+G45+G9 -> 19.025053 | H55: =H21+H33+H45+H9 -> 19.135575 | I55: =I21+I33+I45+I9 -> 19.246796 | J55: =J21+J33+J45+J9 -> 19.358722 | ... DR55: =DR21+DR33+DR45+DR9 -> 29.41341
B56: Interest Paid | C56: =C22+C34+C46+C10 -> 15.185811 | D56: =D22+D34+D46+D10 -> 15.148081 | E56: =E22+E34+E46+E10 -> 15.110019 | F56: =F22+F34+F46+F10 -> 15.071621 | G56: =G22+G34+G46+G10 -> 15.032886 | H56: =H22+H34+H46+H10 -> 14.993809 | I56: =I22+I34+I46+I10 -> 14.954387 | J56: =J22+J34+J46+J10 -> 14.914618 | ... DR56: =DR22+DR34+DR46+DR10 -> 10.349221
B57: Total Loan Payment | C57: =C23+C35+C47+C11 -> 33.775672 | D57: =D23+D35+D47+D11 -> 33.845715 | E57: =E23+E35+E47+E11 -> 33.916106 | F57: =F23+F35+F47+F11 -> 33.986847 | G57: =G23+G35+G47+G11 -> 34.057939 | H57: =H23+H35+H47+H11 -> 34.129384 | I57: =I23+I35+I47+I11 -> 34.201184 | J57: =J23+J35+J47+J11 -> 34.27334 | ... DR57: =DR23+DR35+DR47+DR11 -> 39.762631
B58: Loan Balance | C58: =C24+C36+C48+C12 -> 2892.6363 | D58: =D24+D36+D48+D12 -> 2873.9386 | E58: =E24+E36+E48+E12 -> 2855.1326 | F58: =F24+F36+F48+F12 -> 2836.2173 | G58: =G24+G36+G48+G12 -> 2817.1923 | H58: =H24+H36+H48+H12 -> 2798.0567 | I58: =I24+I36+I48+I12 -> 2778.8099 | J58: =J24+J36+J48+J12 -> 2759.4512 | ... DR58: =DR24+DR36+DR48+DR12 -> 1.1435297e-13
B59: Current Liability | C59: =C25+C37+C49+C13 -> 231.68257 | D59: =D25+D37+D49+D13 -> 233.03027 | E59: =E25+E37+E49+E13 -> 234.38652 | F59: =F25+F37+F49+F13 -> 235.75136 | G59: =G25+G37+G49+G13 -> 237.12487 | H59: =H25+H37+H49+H13 -> 238.5071 | I59: =I25+I37+I49+I13 -> 239.89811 | J59: =J25+J37+J49+J13 -> 241.29796 | ... DR59: =DR25+DR37+DR49+DR13 -> 0
B60: Long-Term Liability | C60: =C26+C38+C50+C14 -> 2660.9537 | D60: =D26+D38+D50+D14 -> 2640.9084 | E60: =E26+E38+E50+E14 -> 2620.746 | F60: =F26+F38+F50+F14 -> 2600.466 | G60: =G26+G38+G50+G14 -> 2580.0674 | H60: =H26+H38+H50+H14 -> 2559.5496 | I60: =I26+I38+I50+I14 -> 2538.9118 | J60: =J26+J38+J50+J14 -> 2518.1532 | ... DR60: =DR26+DR38+DR50+DR14 -> 1.5254464e-13
B62: Loan Summary
B64: Timeline (Years) | C64: Year-1 | D64: Year-2 | E64: Year-3 | F64: Year-4 | G64: Year-5 | H64: Year-6 | I64: Year-7 | J64: Year-8 | K64: Year-9 | L64: Year-10
B65: Principal Paid | C65: =SUM(C55:N55) -> 230.34335 | D65: =SUM(O55:Z55) -> 246.98709 | E65: =SUM(AA55:AL55) -> 264.95088 | F65: =SUM(AM55:AX55) -> 284.3516 | G65: =SUM(AY55:BJ55) -> 305.31765 | H65: =SUM(BK55:BV55) -> 326.03574 | I65: =SUM(BW55:CH55) -> 284.76501 | J65: =SUM(CI55:CT55) -> 302.98637 | K65: =SUM(CU55:DF55) -> 322.40044 | L65: =SUM(DG55:DR55) -> 343.08801
B66: Interest Paid | C66: =SUM(C56:N56) -> 179.66495 | D66: =SUM(O56:Z56) -> 173.67528 | E66: =SUM(AA56:AL56) -> 167.01762 | F66: =SUM(AM56:AX56) -> 159.61466 | G66: =SUM(AY56:BJ56) -> 151.37989 | H66: =SUM(BK56:BV56) -> 142.31144 | I66: =SUM(BW56:CH56) -> 135.77614 | J66: =SUM(CI56:CT56) -> 132.7635 | K66: =SUM(CU56:DF56) -> 129.48547 | L66: =SUM(DG56:DR56) -> 125.917
B67: Total Loan Payment | C67: =C65+C66 -> 410.0083 | D67: =D65+D66 -> 420.66236 | E67: =E65+E66 -> 431.9685 | F67: =F65+F66 -> 443.96626 | G67: =G65+G66 -> 456.69755 | H67: =H65+H66 -> 468.34717 | I67: =I65+I66 -> 420.54115 | J67: =J65+J66 -> 435.74987 | ... L67: =L65+L66 -> 469.00501
B68: Loan Balance | C68: =SUM(C58:N58) -> 33453.389 | D68: =SUM(O58:Z58) -> 30582.341 | E68: =SUM(AA58:AL58) -> 27503.098 | F68: =SUM(AM58:AX58) -> 24199.071 | G68: =SUM(AY58:BJ58) -> 20652.195 | H68: =SUM(BK58:BV58) -> 16855.276 | I68: =SUM(BW58:CH58) -> 13205.432 | J68: =SUM(CI58:CT58) -> 9670.9592 | K68: =SUM(CU58:DF58) -> 5910.1549 | L68: =SUM(DG58:DR58) -> 1908.1869
B69: Current Liability | C69: =N13+N25+N37+N49 -> 246.98709 | D69: =Z49+Z37+Z25+Z13 -> 264.95088 | E69: =AL13+AL25+AL37+AL49 -> 284.3516 | F69: =AX13+AX25+AX37+AX49 -> 305.31765 | G69: =BJ13+BJ25+BJ37+BJ49 -> 326.03574 | H69: =BV13+BV24+BV49 -> 284.76501 | I69: =CH49+CH25+CH13 -> 302.98637 | J69: =CT49+CT25+CT13 -> 322.40044 | K69: =DF49+DF25+DF13 -> 343.08801 | L69: =DR49+DR25+DR13 -> 0
B70: Long-Term Liability | C70: =N14+N26+N38+N50 -> 2433.8957 | D70: =Z50+Z38+Z26+Z14 -> 2168.9448 | E70: =AL14+AL26+AL38+AL50 -> 1884.5932 | F70: =AX14+AX26+AX38+AX50 -> 1579.2756 | G70: =BJ14+BJ26+BJ38+BJ50 -> 1253.2398 | H70: =BV14+BV25+BV50 -> 968.47482 | I70: =CH50+CH26+CH14 -> 665.48845 | J70: =CT50+CT26+CT14 -> 343.08801 | K70: =DF50+DF26+DF14 -> 1.3855583e-13 | L70: =DR50+DR26+DR14 -> 1.5254464e-13
B72: Timeline (Years) | C72: Year-1 | D72: Year-2 | E72: Year-3 | F72: Year-4 | G72: Year-5 | H72: Year-6 | I72: Year-7 | J72: Year-8 | K72: Year-9 | L72: Year-10
B73: New Borrowing | C73: =C17+C29+C41 -> 2774.16

Sheet Valuation-DCF-Terminal Growth 
B2: Valuation - Discounted Cash Flow (DCF)
B5: Perpetual Growth Method | I5: WACC Calculation
B7: Particulars | C7: Year-1 | D7: Year-2 | E7: Year-3 | F7: Year-4 | G7: Year-5 | I7: Capital Structure
B8: Years Timeline | C8: 1 | D8: 2 | E8: 3 | F8: 4 | G8: 5 | I8: Debt to Total Capitalization | J8: 0
B9: EBIT | C9: ='P&L'!F46 -> 147.44829 | D9: ='P&L'!G46 -> 611.92709 | E9: ='P&L'!H46 -> 1152.6457 | F9: ='P&L'!I46 -> 1840.1825 | G9: ='P&L'!J46 -> 2730.4053 | I9: Equity to Total Capitalization | J9: 1
B10: (-) Tax | C10: ='P&L'!F54 -> 0 | D10: ='P&L'!G54 -> 131.47554 | E10: ='P&L'!H54 -> 417.49898 | F10: ='P&L'!I54 -> 842.81432 | G10: ='P&L'!J54 -> 728.90861 | I10: Debt/Equity | J10: =J8/J9 -> 0
B11: (+) Depreciation | C11: ='P&L'!F44 -> 37.351708 | D11: ='P&L'!G44 -> 39.852912 | E11: ='P&L'!H44 -> 44.969264 | F11: ='P&L'!I44 -> 53.665192 | G11: ='P&L'!J44 -> 62.148476
B12: (-) Change in Capex | C12: =DAS!F83 -> 43 | D12: =DAS!H83 -> 64 | E12: =DAS!J83 -> 75 | F12: =DAS!L83 -> 97 | G12: =DAS!N83 -> 103 | I12: Cost of Equity Calculation
B13: (-) WC Increase | C13: =WC!E56 -> 68.307524 | D13: =WC!F56 -> 203.55863 | E13: =WC!G56 -> 206.57445 | F13: =WC!H56 -> 257.53465 | G13: =WC!I56 -> 337.33456 | I13: Risk free Rate | J13: 0.0652
B14: Free Cash Flow | C14: =C9-C10+C11-C12-C13 -> 73.492476 | D14: =D9-D10+D11-D12-D13 -> 252.74583 | E14: =E9-E10+E11-E12-E13 -> 498.54157 | F14: =F9-F10+F11-F12-F13 -> 696.49868 | G14: =G9-G10+G11-G12-G13 -> 1623.3106 | I14: Equity Risk Premium | J14: 0.0726
I15: Size Risk premium for Startups | J15: 0.2
B16: ='Valuation-DCF-Terminal Growth '!I25 -> Adjusted WACC | C16: ='Valuation-DCF-Terminal Growth '!J25 -> 0.3378 | D16: =C16 -> 0.3378 | E16: =D16 -> 0.3378 | F16: =E16 -> 0.3378 | G16: =F16 -> 0.3378 | I16: Levered Beta | J16: 1
B17: Terminal Growth Rate | C17: ='Valuation-DCF-Terminal Growth '!J26 -> 0.045 | D17: =C17 -> 0.045 | E17: =D17 -> 0.045 | F17: =E17 -> 0.045 | G17: =F17 -> 0.045 | I17: Company Specific Risk Premium | J17: 0
B18: Discounting Factor | C18: =1/(1+C16)^C8 -> 0.74749589 | D18: =1/(1+D16)^D8 -> 0.5587501 | E18: =1/(1+E16)^E8 -> 0.41766341 | F18: =1/(1+F16)^F8 -> 0.31220168 | G18: =1/(1+G16)^G8 -> 0.23336947 | I18: Adjusted Cost of Equity | J18: =J13+(J14*J16)+J15+J17 -> 0.3378
B20: Present Value of Cashflows | C20: =C14*C18 -> 54.935324 | D20: =D14*D18 -> 141.22176 | E20: =E14*E18 -> 208.22257 | F20: =F14*F18 -> 217.44806 | G20: =G14*G18 -> 378.83113 | I20: Cost of Debt Calculation
B21: Terminal Value | G21: =G14*(1+G17)/(G16-G17) -> 5793.5777 | I21: Cost of Debt | J21: 0
B22: Present Value of Terminal Value | G22: =G21*G18 -> 1352.0442 | I22: Tax rate | J22: ='P&L'!Q54 -> 0.3
I23: After Tax Cost of Debt | J23: =J21*(1-J22) -> 0
B24: Value as per DCF (INR Lakhs) | G24: =SUM(C20:G20)+G22 -> 2352.703
B25: Value as per DCF (INR Crore) | G25: =G24/10^2 -> 23.52703 | I25: Adjusted WACC | J25: =(J8*J23)+(J9*J18) -> 0.3378
I26: Sustainable Growth rate post 5 Y | J26: 0.045
I27: Discount for Lack of Marketability | J27: 0.2
B28: Particulars | C28: INR Lakhs | D28: INR Crores
B29: Value as per DCF | C29: =G24 -> 2352.703 | D29: =C29/10^2 -> 23.52703
B30: Add- Cash and Cash Equivalent at Start Date | C30: =Config!C8 -> 0.3696979 | D30: =C30/10^2 -> 0.003696979
B31: Total Company Valuation | C31: =C29+C30 -> 2353.0727 | D31: =C31/10^2 -> 23.530727
B32: Less-Debt Outstanding at Start Date | C32: =Config!G9 -> 137.06614 | D32: =C32/10^2 -> 1.3706614
B33: Equity Value of Company | C33: =C31-C32 -> 2216.0066 | D33: =C33/10^2 -> 22.160066
B34: Less-Discount for Lack of Marketability | C34: =C33*'Valuation-DCF-Terminal Growth '!J27 -> 443.20131 | D34: =C34/10^2 -> 4.4320131
B35: Valuation of Equity (Post funding) | C35: =C33-C34 -> 1772.8052 | D35: =C35/10^2 -> 17.728052
B37: Sensitivity Analysis
C38: WACC
B39: =D35 -> 17.728052 | C39: =D39-1% -> 0.3178 | D39: =E39-1% -> 0.3278 | E39: =J25 -> 0.3378 | F39: =E39+1% -> 0.3478 | G39: =F39+1% -> 0.3578
B40: =B41-1% -> 0.025 | C40: 18.587997 | D40: 17.678699 | E40: 16.842694 | F40: 16.072526 | G40: 15.361663
B41: =B42-1% -> 0.035 | C41: 19.108044 | D41: 18.14993 | E41: 17.270754 | F41: 16.462279 | G41: 15.71732
B42: =J26 -> 0.045 | C42: 19.666219 | D42: 18.654487 | E42: 17.728052 | F42: 16.877775 | G42: 16.095717
B43: =B42+1% -> 0.055 | C43: 20.266872 | D43: 19.196035 | E43: 18.217692 | F43: 17.321652 | G43: 16.499108
B44: =B43+1% -> 0.065 | C44: 20.915045 | D44: 19.778797 | E44: 18.743229 | F44: 17.796921 | G44: 16.930053
B46: Terminal Growth Rate

Sheet Valuation-Comparables
B2: Comparable Company Valuation
B6: Company Name | D6: EV/Revenue | F6: Sources
B8: Slurrp Farm | D8: =532/73.2 -> 7.2677596 | F8: https://canvasbusinessmodel.com/blogs/competitors/slurrp-farm-competitive-landscape
B9: Millet Amma | D9: =33.33/5 -> 6.666 | F9: https://www.sharktankindiaclub.com/millet-amma-owner-networth-after-shark-tank-updates/
B11: Median | D11: =MEDIAN(D8:D9) -> 6.9668798
B12: Current Monthly Revenue (Lacs) | D12: 35
B13: Annualized Revenue | D13: =D12*12 -> 420
B14: Enterprise Value in Lakhs | D14: =D11*D13 -> 2926.0895
B15: Enterprise Value (in Crs) | D15: =D14/10^2 -> 29.260895

Sheet Valuation-VC 
B2: Company Valuation-Venture Capital
B6: Particulars | C6: In INR Lakhs | D6: In INR Cr
B7: Exit Multiple (5 xRevenue Multiple) | C7: 5
B8: Revenue in 5th Year | C8: ='P&L'!J7 -> 8682.9833 | D8: =C8/10^2 -> 86.829833
B9: Value of Company in 5th Year | C9: =C7*C8 -> 43414.916 | D9: =C9/10^2 -> 434.14916
B10: Expected ROI for Investor (Number of Times) | C10: 10
B11: Present Valuation of Company | C11: =C9/C10 -> 4341.4916 | D11: =C11/10^2 -> 43.414916
B12: Future Equity Dilution % | C12: 0.2
B13: Present Valuation of Company (after future dilution) | C13: =C11*(1-C12) -> 3473.1933 | D13: =C13/10^2 -> 34.731933
